Workbook

Sheet Contents
A1: GCP ERP Migration: Supporting Workbook
A2: Karoo Retail Group (Pty) Ltd (fictitious client) | Supports the SPMP for PFD473S Assessment T3 | Prepared by Thabiso Matsaba (220296006) | 09 October 2026
A4: Sheet | B4: Contents | C4: SPMP reference | D4: Self-check
A5: Business Case | B5: Weighted option scoring, run-cost comparison, 5-year NPV, IRR, payback, BCR, ROI | C5: Section 2 (Tables 9-12) | D5: n/a
A6: WBS | B6: Level-3 WBS dictionary: 95 work packages with owner, effort and dates; phase totals | C6: Section 4 (Table 15), 5.2 | D6: =IF(AND(WBS!I100="OK",WBS!J112="OK",WBS!G116="OK",WBS!G117="OK"),"OK","CHECK") -> OK
A7: Gantt | B7: 26-week Gantt chart with critical path and milestones (conditional formatting) | C7: Section 5.3, Appendix A.1 | D7: n/a
A8: PERT | B8: Three-point estimates, critical path, go-live probability, float analysis | C8: Section 5.4, Appendix A.2-A.3 (Tables 49-50) | D8: =PERT!E22 -> OK
A9: Resources | B9: Staffing, hours, allocation, rates and labour cost | C9: Section 5.5 (Table 18), 13.2, Appendix E | D9: =IF(AND(Resources!G23="OK",Resources!G24="OK",Resources!G25="OK"),"OK","CHECK") -> OK
A10: Budget | B10: Non-labour estimate, budget summary and reserves, phase allocation | C10: Section 6 (Tables 19-21) | D10: =IF(AND(Budget!C41="OK",Budget!C42="OK",Budget!C43="OK"),"OK","CHECK") -> OK
A11: Cash Flow | B11: Monthly cash flow projection, contingency, cumulative baseline and chart | C11: Appendix B (Table 51, Figure 5) | D11: =IF(COUNTIF('Cash Flow'!H24:H28,"OK")=5,"OK","CHECK") -> OK
A12: Risk Register | B12: 17 risks scored P x I with rating, response, owner and EMV | C12: Section 11, Appendix C (Table 52) | D12: ='Risk Register'!C33 -> OK
A13: RACI | B13: Responsibility assignment for 20 activities across 9 roles | C13: Appendix D (Table 53) | D13: =RACI!M27 -> OK
A14: EVM | B14: Earned value worked example with CPI, SPI, EAC, VAC, TCPI | C14: Sections 6.5, 14.1-14.2 | D14: n/a
A16: All self-checks | D16: =IF(COUNTIF(D5:D14,"CHECK")=0,"OK","CHECK") -> OK
A18: Legend
A19: Blue text | B19: Input value (estimate or assumption); change it and dependent cells update
A20: Black text | B20: Formula
A21: Green text | B21: Formula that links to another sheet
A22: Yellow fill | B22: Key assumption (rates, hurdle rate, approved baseline figures)
A23: OK / CHECK | B23: Self-check against the figures stated in the SPMP
A25: All amounts in South African Rand (ZAR), excluding VAT at 15%. Figures are planning estimates for a fictitious client.

Sheet Business Case
A1: GCP ERP Migration: Options Scoring and Financial Appraisal
A2: Supports SPMP Section 2.2 (Table 9) and 2.3 (Tables 10 to 12). R million unless stated.
A4: Criterion | B4: Weight | C4: A: Do nothing | D4: B: On-prem refresh | E4: C: GCP replatform (selected) | F4: D: Replace with SaaS ERP
A5: Strategic alignment | B5: 0.25 | C5: 1 | D5: 2 | E5: 5 | F5: 5
A6: Financial return | B6: 0.25 | C6: 1 | D6: 2 | E6: 4 | F6: 3
A7: Risk (5 = low) | B7: 0.15 | C7: 1 | D7: 3 | E7: 3 | F7: 2
A8: Feasibility in 6 months | B8: 0.15 | C8: 5 | D8: 4 | E8: 4 | F8: 1
A9: Compliance and security | B9: 0.1 | C9: 1 | D9: 3 | E9: 4 | F9: 4
A10: Scalability and agility | B10: 0.1 | C10: 1 | D10: 2 | E10: 5 | F10: 5
A11: Weighted score (out of 5) | B11: =SUM(B5:B10) -> 1 | C11: =SUMPRODUCT($B$5:$B$10,C5:C10) -> 1.6 | D11: =SUMPRODUCT($B$5:$B$10,D5:D10) -> 2.55 | E11: =SUMPRODUCT($B$5:$B$10,E5:E10) -> 4.2 | F11: =SUMPRODUCT($B$5:$B$10,F5:F10) -> 3.35
A12: Selected option (highest score) | C12: =INDEX($C$4:$F$4,MATCH(MAX($C$11:$F$11),$C$11:$F$11,0)) -> C: GCP replatform (selected)
A15: Annual run-cost line (R) | B15: Current on-prem | C15: Post-migration GCP
A16: Hardware maintenance and depreciation | B16: 1600000 | C16: 0
A17: Data centre, power, backup power | B17: 1200000 | C17: 0
A18: Infrastructure staff (allocated) / MSP managed services | B18: 1500000 | C18: 700000
A19: Software licences / cloud licences | B19: 1400000 | C19: 600000
A20: DR and backup | B20: 500000 | C20: 0
A21: GCP consumption (committed use discounts after stabilisation) | B21: 0 | C21: 2600000
A22: Total | B22: =SUM(B16:B21) -> 6200000 | C22: =SUM(C16:C21) -> 3900000
A23: Annual run-cost saving | C23: =B22-C22 -> 2300000
A26: Hurdle rate (assumed WACC, to be confirmed by Finance) | B26: 0.11
A27: Investment: total funding envelope (R m) | B27: ='Cash Flow'!H23/1000000 -> 8.1236
A28: Annual BI / decision-making benefit (R m) | B28: 1.8
A29: Avoided hardware refresh in Year 1, base case only (R m) | B29: 5.5
A31: Year | B31: Discount factor | C31: Base case: net flow | D31: Base case: PV | E31: Conservative: net flow | F31: Conservative: PV
A32: 0 | B32: =1/(1+$B$26)^A32 -> 1 | C32: =-B27 -> -8.1236 | D32: =C32*B32 -> -8.1236 | E32: =-B27 -> -8.1236 | F32: =E32*B32 -> -8.1236
A33: 1 | B33: =1/(1+$B$26)^A33 -> 0.9009009 | C33: =$C$23/1000000+$B$28+$B$29 -> 9.6 | D33: =C33*B33 -> 8.6486486 | E33: =$C$23/1000000+$B$28 -> 4.1 | F33: =E33*B33 -> 3.6936937
A34: 2 | B34: =1/(1+$B$26)^A34 -> 0.81162243 | C34: =$C$23/1000000+$B$28 -> 4.1 | D34: =C34*B34 -> 3.327652 | E34: =$C$23/1000000+$B$28 -> 4.1 | F34: =E34*B34 -> 3.327652
A35: 3 | B35: =1/(1+$B$26)^A35 -> 0.73119138 | C35: =$C$23/1000000+$B$28 -> 4.1 | D35: =C35*B35 -> 2.9978847 | E35: =$C$23/1000000+$B$28 -> 4.1 | F35: =E35*B35 -> 2.9978847
A36: 4 | B36: =1/(1+$B$26)^A36 -> 0.65873097 | C36: =$C$23/1000000+$B$28 -> 4.1 | D36: =C36*B36 -> 2.700797 | E36: =$C$23/1000000+$B$28 -> 4.1 | F36: =E36*B36 -> 2.700797
A37: 5 | B37: =1/(1+$B$26)^A37 -> 0.59345133 | C37: =$C$23/1000000+$B$28 -> 4.1 | D37: =C37*B37 -> 2.4331504 | E37: =$C$23/1000000+$B$28 -> 4.1 | F37: =E37*B37 -> 2.4331504
A39: Metric | B39: Base case | C39: Conservative case
A40: NPV (5 years) R m | B40: =SUM(D32:D37) -> 11.984533 | C40: =SUM(F32:F37) -> 7.0295778
A41: IRR | B41: =IRR(C32:C37) -> 0.77025963 | C41: =IRR(E32:E37) -> 0.41606422
A42: Payback (months after go-live) | B42: =IF(C33>=-C32,-C32/C33*12,12+(-C32-C33)/C34*12) -> 10.1545 | C42: =IF(E33>=-E32,-E32/E33*12,12+(-E32-E33)/E34*12) -> 23.77639
A43: Benefit-cost ratio (PV benefits / investment) | B43: =SUM(D33:D37)/-D32 -> 2.4752736 | C43: =SUM(F33:F37)/-F32 -> 1.8653279
A44: 5-year ROI (undiscounted) | B44: n/a | C44: =(SUM(E33:E37)+E32)/-E32 -> 1.5235117
A46: SPMP Table 12 reports NPV R11.99 m / R7.03 m, IRR about 77% / 41%, payback about 10 / 24 months, BCR 2.48 / 1.87 and ROI 152%.

Sheet WBS
A1: GCP ERP Migration: Work Breakdown Structure and Dictionary (Level 3)
A2: Owner = accountable role; effort covers all roles working on the package. Total matches the 6,880 planned hours in SPMP Section 5.5. Blue = input (effort, start/end week); dates are formulas from the week numbers.
A4: WBS ID | B4: Level | C4: Work package | D4: Level-1 phase | E4: Level-2 group | F4: Owner | G4: Effort (h) | H4: Start week | I4: End week | J4: Start date | K4: End date
A5: 1.1.1 | B5: 3 | C5: Charter and mandate approved | D5: 1.0 Initiation and Planning | E5: 1.1 Project initiation | F5: PM | G5: 40 | H5: 1 | I5: 2 | J5: =DATE(2026,10,5)+(H5-1)*7 -> 46300 | K5: =DATE(2026,10,5)+(I5-1)*7+4 -> 46311
A6: 1.1.2 | B6: 3 | C6: Stakeholder register and engagement plan | D6: 1.0 Initiation and Planning | E6: 1.1 Project initiation | F6: BA | G6: 40 | H6: 1 | I6: 2 | J6: =DATE(2026,10,5)+(H6-1)*7 -> 46300 | K6: =DATE(2026,10,5)+(I6-1)*7+4 -> 46311
A7: 1.1.3 | B7: 3 | C7: Governance set-up (SteerCo, CCB, RACI) | D7: 1.0 Initiation and Planning | E7: 1.1 Project initiation | F7: PM | G7: 30 | H7: 1 | I7: 2 | J7: =DATE(2026,10,5)+(H7-1)*7 -> 46300 | K7: =DATE(2026,10,5)+(I7-1)*7+4 -> 46311
A8: 1.2.1 | B8: 3 | C8: SPMP and management plans | D8: 1.0 Initiation and Planning | E8: 1.2 Project planning | F8: PM | G8: 120 | H8: 1 | I8: 3 | J8: =DATE(2026,10,5)+(H8-1)*7 -> 46300 | K8: =DATE(2026,10,5)+(I8-1)*7+4 -> 46318
A9: 1.2.2 | B9: 3 | C9: Schedule, cost and resource baselines | D9: 1.0 Initiation and Planning | E9: 1.2 Project planning | F9: PM | G9: 80 | H9: 1 | I9: 3 | J9: =DATE(2026,10,5)+(H9-1)*7 -> 46300 | K9: =DATE(2026,10,5)+(I9-1)*7+4 -> 46318
A10: 1.2.3 | B10: 3 | C10: Tooling and environments | D10: 1.0 Initiation and Planning | E10: 1.2 Project planning | F10: CE | G10: 50 | H10: 1 | I10: 3 | J10: =DATE(2026,10,5)+(H10-1)*7 -> 46300 | K10: =DATE(2026,10,5)+(I10-1)*7+4 -> 46318
A11: 1.3.1 | B11: 3 | C11: Onboarding and access provisioning | D11: 1.0 Initiation and Planning | E11: 1.3 Team mobilisation | F11: CE | G11: 30 | H11: 1 | I11: 2 | J11: =DATE(2026,10,5)+(H11-1)*7 -> 46300 | K11: =DATE(2026,10,5)+(I11-1)*7+4 -> 46311
A12: 1.3.2 | B12: 3 | C12: MSP and vendor RFQ issued | D12: 1.0 Initiation and Planning | E12: 1.3 Team mobilisation | F12: PM | G12: 30 | H12: 1 | I12: 2 | J12: =DATE(2026,10,5)+(H12-1)*7 -> 46300 | K12: =DATE(2026,10,5)+(I12-1)*7+4 -> 46311
A13: 2.1.1 | B13: 3 | C13: Migration Center discovery and inventory | D13: 2.0 Discovery and Assessment | E13: 2.1 Estate inventory | F13: SA | G13: 90 | H13: 3 | I13: 5 | J13: =DATE(2026,10,5)+(H13-1)*7 -> 46314 | K13: =DATE(2026,10,5)+(I13-1)*7+4 -> 46332
A14: 2.1.2 | B14: 3 | C14: Dependency and 14-interface mapping | D14: 2.0 Discovery and Assessment | E14: 2.1 Estate inventory | F14: AD | G14: 90 | H14: 3 | I14: 5 | J14: =DATE(2026,10,5)+(H14-1)*7 -> 46314 | K14: =DATE(2026,10,5)+(I14-1)*7+4 -> 46332
A15: 2.1.3 | B15: 3 | C15: Licence and support-status review | D15: 2.0 Discovery and Assessment | E15: 2.1 Estate inventory | F15: SA | G15: 30 | H15: 3 | I15: 5 | J15: =DATE(2026,10,5)+(H15-1)*7 -> 46314 | K15: =DATE(2026,10,5)+(I15-1)*7+4 -> 46332
A16: 2.2.1 | B16: 3 | C16: Data profiling and quality baseline | D16: 2.0 Discovery and Assessment | E16: 2.2 Data assessment | F16: DE | G16: 80 | H16: 3 | I16: 6 | J16: =DATE(2026,10,5)+(H16-1)*7 -> 46314 | K16: =DATE(2026,10,5)+(I16-1)*7+4 -> 46339
... A99: 8.4.3 | B99: 3 | C99: Vendor performance reviews | D99: 8.0 PM, Quality and Governance | E99: 8.4 Procurement | F99: PM | G99: 10 | H99: 1 | I99: 26 | J99: =DATE(2026,10,5)+(H99-1)*7 -> 46300 | K99: =DATE(2026,10,5)+(I99-1)*7+4 -> 46479
C100: Total planned effort | G100: =SUM(G5:G99) -> 6880 | H100: Check | I100: =IF(G100=6880,"OK","CHECK") -> OK
C103: Effort by phase | G103: Effort (h) | H103: % of total | I103: SPMP Table 15 | J103: Check
C104: 1.0 Initiation and Planning | G104: =SUMIF(A$5:A$99,"1.*",G$5:G$99) -> 420 | H104: =G104/$G$100 -> 0.061046512 | I104: 420 | J104: =IF(G104=I104,"OK","CHECK") -> OK
C105: 2.0 Discovery and Assessment | G105: =SUMIF(A$5:A$99,"2.*",G$5:G$99) -> 700 | H105: =G105/$G$100 -> 0.10174419 | I105: 700 | J105: =IF(G105=I105,"OK","CHECK") -> OK
C106: 3.0 Architecture and Landing Zone | G106: =SUMIF(A$5:A$99,"3.*",G$5:G$99) -> 900 | H106: =G106/$G$100 -> 0.13081395 | I106: 900 | J106: =IF(G106=I106,"OK","CHECK") -> OK
C107: 4.0 Build and Migration | G107: =SUMIF(A$5:A$99,"4.*",G$5:G$99) -> 2640 | H107: =G107/$G$100 -> 0.38372093 | I107: 2640 | J107: =IF(G107=I107,"OK","CHECK") -> OK
C108: 5.0 Testing, Hardening and Readiness | G108: =SUMIF(A$5:A$99,"5.*",G$5:G$99) -> 1200 | H108: =G108/$G$100 -> 0.1744186 | I108: 1200 | J108: =IF(G108=I108,"OK","CHECK") -> OK
C109: 6.0 Cutover and Go-Live | G109: =SUMIF(A$5:A$99,"6.*",G$5:G$99) -> 300 | H109: =G109/$G$100 -> 0.043604651 | I109: 300 | J109: =IF(G109=I109,"OK","CHECK") -> OK
C110: 7.0 Hypercare and Closure | G110: =SUMIF(A$5:A$99,"7.*",G$5:G$99) -> 380 | H110: =G110/$G$100 -> 0.055232558 | I110: 380 | J110: =IF(G110=I110,"OK","CHECK") -> OK
C111: 8.0 PM, Quality and Governance | G111: =SUMIF(A$5:A$99,"8.*",G$5:G$99) -> 340 | H111: =G111/$G$100 -> 0.049418605 | I111: 340 | J111: =IF(G111=I111,"OK","CHECK") -> OK
C112: Total | G112: =SUM(G104:G111) -> 6880 | H112: =SUM(H104:H111) -> 1 | I112: =SUM(I104:I111) -> 6880 | J112: =IF(G112=G100,"OK","CHECK") -> OK
C114: Level-3 work packages (SPMP: 95) | G114: =COUNTA(A5:A99) -> 95
C115: Level-2 deliverable groups (SPMP: 28) | G115: =SUMPRODUCT((E5:E99<>E6:E100)*1) -> 28
C116: Check: Mock 1 ends at G4 (22 Jan 2027) | G116: =IF(K40=DATE(2027,1,22),"OK","CHECK") -> OK
C117: Check: Mock 2 ends at G5 (19 Feb 2027) | G117: =IF(K41=DATE(2027,2,19),"OK","CHECK") -> OK

Sheet Gantt
A1: GCP ERP Migration: Gantt Chart (26 weeks, 5 Oct 2026 to 2 Apr 2027)
A2: Bars are drawn by conditional formatting from the Start/End week columns; change a week and the bar moves. Red = critical path. Can be imported into MS Project.
F3: =DATE(2026,10,5)+0*7 -> 46300 | G3: =DATE(2026,10,5)+1*7 -> 46307 | H3: =DATE(2026,10,5)+2*7 -> 46314 | I3: =DATE(2026,10,5)+3*7 -> 46321 | J3: =DATE(2026,10,5)+4*7 -> 46328 | K3: =DATE(2026,10,5)+5*7 -> 46335 | L3: =DATE(2026,10,5)+6*7 -> 46342 | M3: =DATE(2026,10,5)+7*7 -> 46349 | N3: =DATE(2026,10,5)+8*7 -> 46356 | O3: =DATE(2026,10,5)+9*7 -> 46363 | P3: =DATE(2026,10,5)+10*7 -> 46370 | Q3: =DATE(2026,10,5)+11*7 -> 46377 | R3: =DATE(2026,10,5)+12*7 -> 46384 | S3: =DATE(2026,10,5)+13*7 -> 46391 | T3: =DATE(2026,10,5)+14*7 -> 46398 | U3: =DATE(2026,10,5)+15*7 -> 46405 | V3: =DATE(2026,10,5)+16*7 -> 46412 | W3: =DATE(2026,10,5)+17*7 -> 46419 | X3: =DATE(2026,10,5)+18*7 -> 46426 | Y3: =DATE(2026,10,5)+19*7 -> 46433 | Z3: =DATE(2026,10,5)+20*7 -> 46440 | AA3: =DATE(2026,10,5)+21*7 -> 46447 | AB3: =DATE(2026,10,5)+22*7 -> 46454 | AC3: =DATE(2026,10,5)+23*7 -> 46461 | AD3: =DATE(2026,10,5)+24*7 -> 46468 | AE3: =DATE(2026,10,5)+25*7 -> 46475
A4: ID | B4: Task | C4: Start wk | D4: End wk | E4: Critical | F4: W1 | G4: W2 | H4: W3 | I4: W4 | J4: W5 | K4: W6 | L4: W7 | M4: W8 | N4: W9 | O4: W10 | P4: W11 | Q4: W12 | R4: W13 | S4: W14 | T4: W15 | U4: W16 | V4: W17 | W4: W18 | X4: W19 | Y4: W20 | Z4: W21 | AA4: W22 | AB4: W23 | AC4: W24 | AD4: W25 | AE4: W26
A5: 1.0 | B5: Initiation and Planning | C5: 1 | D5: 3 | E5: 1
A6: 1.1 | B6: Project initiation | C6: 1 | D6: 2 | E6: 1
A7: 1.2 | B7: Project planning | C7: 1 | D7: 3 | E7: 1
A8: 1.3 | B8: Team mobilisation | C8: 1 | D8: 2 | E8: 0
A9: 2.0 | B9: Discovery and Assessment | C9: 3 | D9: 6 | E9: 1
A10: 2.1 | B10: Estate inventory | C10: 3 | D10: 5 | E10: 1
A11: 2.2 | B11: Data assessment | C11: 3 | D11: 6 | E11: 1
A12: 2.3 | B12: Requirements | C12: 3 | D12: 5 | E12: 1
A13: 2.4 | B13: Migration strategy | C13: 5 | D13: 6 | E13: 1
A14: 3.0 | B14: Architecture and Landing Zone | C14: 6 | D14: 9 | E14: 1
A15: 3.1 | B15: Target architecture | C15: 6 | D15: 8 | E15: 1
A16: 3.2 | B16: Landing zone build | C16: 7 | D16: 9 | E16: 1
... A40: 8.4 | B40: Procurement | C40: 1 | D40: 26 | E40: 0
A41: M1 | B41: ◆ G1 SPMP approved | C41: 3 | D41: 3 | E41: M
A42: M2 | B42: ◆ G2 Strategy approved | C42: 6 | D42: 6 | E42: M
A43: M3 | B43: ◆ G3 Landing zone live | C43: 9 | D43: 9 | E43: M
A44: M4 | B44: ◆ G4 Mock 1 | C44: 16 | D44: 16 | E44: M
A45: M5 | B45: ◆ G5 Build complete, Mock 2 | C45: 20 | D45: 20 | E45: M
A46: M6 | B46: ◆ G6 Go/No-Go | C46: 22 | D46: 22 | E46: M
A47: M7 | B47: ◆ Go-live (12–14 Mar) | C47: 23 | D47: 23 | E47: M
A48: M8 | B48: ◆ G7 Closure | C48: 26 | D48: 26 | E48: M
B50: Legend: blue = activity; red = critical path; gold = milestone. Critical column: 1 = critical, 0 = has float.

Sheet PERT
A1: GCP ERP Migration: PERT Three-Point Estimates, Critical Path and Float
A2: Supports SPMP Section 5.4 and Appendix A.2 / A.3 (Tables 49 and 50). Durations in weeks.
A4: Critical activity | B4: o | C4: m | D4: p | E4: te = (o+4m+p)/6 | F4: σ = (p-o)/6 | G4: Variance σ² | H4: te (rounded)
A5: 1.0 Initiation and planning (to G1) | B5: 1.5 | C5: 2 | D5: 2.5 | E5: =(B5+4*C5+D5)/6 -> 2 | F5: =(D5-B5)/6 -> 0.16666667 | G5: =F5^2 -> 0.027777778 | H5: =ROUND(E5,0) -> 2
A6: 2.0 Discovery and assessment | B6: 2.5 | C6: 3 | D6: 3.5 | E6: =(B6+4*C6+D6)/6 -> 3 | F6: =(D6-B6)/6 -> 0.16666667 | G6: =F6^2 -> 0.027777778 | H6: =ROUND(E6,0) -> 3
A7: 3.0 Architecture and landing zone | B7: 2 | C7: 3 | D7: 4 | E7: =(B7+4*C7+D7)/6 -> 3 | F7: =(D7-B7)/6 -> 0.33333333 | G7: =F7^2 -> 0.11111111 | H7: =ROUND(E7,0) -> 3
A8: 4.1 Data migration pipelines + Mock 1 | B8: 7 | C8: 8 | D8: 9.5 | E8: =(B8+4*C8+D8)/6 -> 8.0833333 | F8: =(D8-B8)/6 -> 0.41666667 | G8: =F8^2 -> 0.17361111 | H8: =ROUND(E8,0) -> 8
A9: 4.1.4 Mock 2 (dress rehearsal) | B9: 3 | C9: 4 | D9: 5 | E9: =(B9+4*C9+D9)/6 -> 4 | F9: =(D9-B9)/6 -> 0.33333333 | G9: =F9^2 -> 0.11111111 | H9: =ROUND(E9,0) -> 4
A10: 5.4 SIT close, UAT and readiness | B10: 1.5 | C10: 2 | D10: 2.5 | E10: =(B10+4*C10+D10)/6 -> 2 | F10: =(D10-B10)/6 -> 0.16666667 | G10: =F10^2 -> 0.027777778 | H10: =ROUND(E10,0) -> 2
A11: 6.0 Cutover (time-boxed weekend) | B11: 1 | C11: 1 | D11: 1 | E11: =(B11+4*C11+D11)/6 -> 1 | F11: =(D11-B11)/6 -> 0 | G11: =F11^2 -> 0 | H11: =ROUND(E11,0) -> 1
A12: 7.0 Hypercare (contracted 3-week time-box) | B12: 3 | C12: 3 | D12: 3 | E12: =(B12+4*C12+D12)/6 -> 3 | F12: =(D12-B12)/6 -> 0 | G12: =F12^2 -> 0 | H12: =ROUND(E12,0) -> 3
A13: Critical path total | E13: =SUM(E5:E12) -> 26.083333 | F13: =SQRT(G13) -> 0.69221866 | G13: =SUM(G5:G12) -> 0.47916667 | H13: =SUM(H5:H12) -> 26
A15: Expected weeks to go-live (to end of cutover week) | E15: =SUM(E5:E11) -> 23.083333
A16: Planned go-live: end of week | E16: 23
A17: Fallback window: end of week | E17: 24
A18: Z (planned) | E18: =(E16-E15)/F13 -> -0.12038585
A19: P(go-live by planned weekend) | E19: =NORMSDIST(E18) -> 0.45208875
A20: Z (fallback) | E20: =(E17-E15)/F13 -> 1.3242444
A21: P(go-live by fallback window) | E21: =NORMSDIST(E20) -> 0.90728905
A22: Check: rounded critical path = 26-week baseline | E22: =IF(H13=26,"OK","CHECK") -> OK
A25: Non-critical activity | B25: Dur. | C25: ES | D25: EF | E25: LS | F25: LF | G25: TF = LS-ES | H25: FF | I25: Controlling successor
A26: 4.2 Application modernisation | B26: 11 | C26: 8 | D26: =C26+B26 -> 19 | E26: 9 | F26: =E26+B26 -> 20 | G26: =E26-C26 -> 1 | H26: 1 | I26: 5.4 UAT (ES 20); 5.1 SIT start-to-start + 7 weeks
A27: 4.3 Identity and access management | B27: 4 | C27: 8 | D27: =C27+B27 -> 12 | E27: 11 | F27: =E27+B27 -> 15 | G27: =E27-C27 -> 3 | H27: 2 | I27: 5.2 Security hardening (LS 15)
A28: 4.4 Looker analytics layer | B28: 8 | C28: 11 | D28: =C28+B28 -> 19 | E28: 12 | F28: =E28+B28 -> 20 | G28: =E28-C28 -> 1 | H28: 1 | I28: 5.4 UAT (ES 20)
A29: 5.1 System integration testing | B29: 4 | C29: 15 | D29: =C29+B29 -> 19 | E29: 16 | F29: =E29+B29 -> 20 | G29: =E29-C29 -> 1 | H29: 0 | I29: 5.3 Performance and DR testing (ES 19)
A30: 5.2 Security hardening and pen test | B30: 7 | C30: 14 | D30: =C30+B30 -> 21 | E30: 15 | F30: =E30+B30 -> 22 | G30: =E30-C30 -> 1 | H30: 1 | I30: 6.0 Cutover (ES 22)
A31: 5.3 Performance and DR testing | B31: 2 | C31: 19 | D31: =C31+B31 -> 21 | E31: 20 | F31: =E31+B31 -> 22 | G31: =E31-C31 -> 1 | H31: 1 | I31: 6.0 Cutover (ES 22)
A33: ES/EF/LS/LF are week numbers from project start (week 0 = 5 Oct 2026). Critical activities have zero total float.

Sheet Resources
A1: GCP ERP Migration: Human Resource Plan and Labour Cost (ZAR, excl. VAT)
A2: Supports SPMP Section 5.5 (Table 18), Section 13.2 (P9) and Appendix E. Blue = input; black = formula.
A4: Capacity per full-time person (h) | B4: 960 | C4: 26 weeks x 40 h, less 6 public holidays and festive-leave / training allowance (SPMP 5.5)
A6: Role | B6: Abbrev. | C6: Sourcing | D6: Planned hours | E6: Allocation of capacity | F6: Rate (R/h) | G6: Cost (R) | H6: WBS hours as accountable owner
A7: Project Manager | B7: PM | C7: Contractor | D7: 960 | E7: =D7/$B$4 -> 1 | F7: 750 | G7: =D7*F7 -> 720000 | H7: =SUMIF(WBS!$F$5:$F$99,B7,WBS!$G$5:$G$99) -> 850
A8: Solution Architect | B8: SA | C8: Contractor | D8: 720 | E8: =D8/$B$4 -> 0.75 | F8: 950 | G8: =D8*F8 -> 684000 | H8: =SUMIF(WBS!$F$5:$F$99,B8,WBS!$G$5:$G$99) -> 550
A9: Cloud Migration Engineer | B9: CE | C9: Contractor | D9: 920 | E9: =D9/$B$4 -> 0.95833333 | F9: 700 | G9: =D9*F9 -> 644000 | H9: =SUMIF(WBS!$F$5:$F$99,B9,WBS!$G$5:$G$99) -> 1100
A10: Data Migration Engineer | B10: DE | C10: Contractor | D10: 870 | E10: =D10/$B$4 -> 0.90625 | F10: 700 | G10: =D10*F10 -> 609000 | H10: =SUMIF(WBS!$F$5:$F$99,B10,WBS!$G$5:$G$99) -> 1520
A11: App Modernisation Developer | B11: AD | C11: Secondee | D11: 760 | E11: =D11/$B$4 -> 0.79166667 | F11: 650 | G11: =D11*F11 -> 494000 | H11: =SUMIF(WBS!$F$5:$F$99,B11,WBS!$G$5:$G$99) -> 820
A12: Looker Developer | B12: BI | C12: Contractor | D12: 570 | E12: =D12/$B$4 -> 0.59375 | F12: 650 | G12: =D12*F12 -> 370500 | H12: =SUMIF(WBS!$F$5:$F$99,B12,WBS!$G$5:$G$99) -> 500
A13: Security and IAM Engineer | B13: SE | C13: Contractor | D13: 710 | E13: =D13/$B$4 -> 0.73958333 | F13: 800 | G13: =D13*F13 -> 568000 | H13: =SUMIF(WBS!$F$5:$F$99,B13,WBS!$G$5:$G$99) -> 690
A14: QA / Test Lead | B14: QA | C14: Secondee | D14: 650 | E14: =D14/$B$4 -> 0.67708333 | F14: 550 | G14: =D14*F14 -> 357500 | H14: =SUMIF(WBS!$F$5:$F$99,B14,WBS!$G$5:$G$99) -> 430
A15: Business Analyst and Change Lead | B15: BA | C15: Secondee | D15: 720 | E15: =D15/$B$4 -> 0.75 | F15: 600 | G15: =D15*F15 -> 432000 | H15: =SUMIF(WBS!$F$5:$F$99,B15,WBS!$G$5:$G$99) -> 420
A16: Total (9-person team) | D16: =SUM(D7:D15) -> 6880 | E16: =D16/(COUNTA(A7:A15)*$B$4) -> 0.7962963 | F16: =G16/D16 -> 709.15698 | G16: =SUM(G7:G15) -> 4879000 | H16: =SUM(H7:H15) -> 6880
A18: Team capacity (h) | D18: =COUNTA(A7:A15)*B4 -> 8640
A19: Team utilisation | D19: =D16/D18 -> 0.7962963
A20: Contractor labour (procured via agency panel, P9) | G20: =SUMIF(C7:C15,"Contractor",G7:G15) -> 3595500
A21: Secondee labour (internal recovery) | G21: =SUMIF(C7:C15,"Secondee",G7:G15) -> 1283500
A23: Check: planned hours = WBS total effort | G23: =IF(D16=WBS!G100,"OK","CHECK") -> OK
A24: Check: labour cost = Cash Flow labour total | G24: =IF(G16='Cash Flow'!H5,"OK","CHECK") -> OK
A25: Check: contractor + secondee = total | G25: =IF(G20+G21=G16,"OK","CHECK") -> OK
A27: Note: Planned hours are what each person books across all work packages. Column H shows only the hours of packages where the role is the accountable owner in the WBS sheet, so the two columns differ by role but have the same total (6,880 h).

Sheet Budget
A1: GCP ERP Migration: Cost Estimate and Budget (ZAR, excl. VAT)
A2: Supports SPMP Section 6.2 (Table 19), 6.3 (Table 20) and 6.4 (Table 21).
A4: # | B4: Non-labour item | C4: Cost (R) | D4: Basis of estimate
A5: 1 | B5: GCP consumption during project | C5: 620000 | D5: Google Cloud Pricing Calculator; ramps with environments
A6: 2 | B6: Google Cloud Partner (MSP) | C6: 450000 | D6: Bidder A RFQ price (Table 45)
A7: 3 | B7: Connectivity | C7: 180000 | D7: Carrier quotations (Dedicated Interconnect + Cloud VPN)
A8: 4 | B8: Security and identity licences | C8: 140000 | D8: Reseller quotation
A9: 5 | B9: Looker licences | C9: 95000 | D9: 60 Looker Studio Pro users (D-09)
A10: 6 | B10: Independent penetration test and POPIA review | C10: 220000 | D10: Fixed-price RFQ, 3 firms
A11: 7 | B11: Training and certification | C11: 160000 | D11: Authorised training partner (Table 25)
A12: 8 | B12: Migration, validation and DevOps tooling | C12: 120000 | D12: Quotation
A13: 9 | B13: Load-shedding resilience | C13: 60000 | D13: UPS, inverters, LTE failover
A14: 10 | B14: Travel (Cape Town and Johannesburg) | C14: 90000 | D14: Trip plan
A15: 11 | B15: Project office and miscellaneous | C15: 50000 | D15: Allowance
B16: Non-labour subtotal | C16: =SUM(C5:C15) -> 2185000
B19: Budget component | C19: Amount (R) | D19: % of direct
B20: Labour (Resources sheet) | C20: =Resources!G16 -> 4879000 | D20: =C20/$C$22 -> 0.69068516
B21: Non-labour (above) | C21: =C16 -> 2185000 | D21: =C21/$C$22 -> 0.30931484
B22: Direct costs | C22: =C20+C21 -> 7064000 | D22: =C22/$C$22 -> 1
B23: Contingency reserve | C23: =C22*'Cash Flow'!K5 -> 706400 | D23: =C23/$C$22 -> 0.1
B24: Cost baseline (BAC) | C24: =C22+C23 -> 7770400
B25: Management reserve (SteerCo controlled) | C25: =C22*'Cash Flow'!K6 -> 353200 | D25: =C25/$C$22 -> 0.05
B26: Total funding envelope | C26: =C24+C25 -> 8123600
A29: WBS | B29: Phase | C29: Amount (R) | D29: % of direct
A30: 1.0 | B30: Initiation and Planning | C30: 330000 | D30: =C30/$C$38 -> 0.046715742
A31: 2.0 | B31: Discovery and Assessment | C31: 520000 | D31: =C31/$C$38 -> 0.073612684
A32: 3.0 | B32: Architecture and Landing Zone | C32: 1000000 | D32: =C32/$C$38 -> 0.14156285
A33: 4.0 | B33: Build and Migration | C33: 2264000 | D33: =C33/$C$38 -> 0.3204983
A34: 5.0 | B34: Testing, Hardening and Readiness | C34: 1000000 | D34: =C34/$C$38 -> 0.14156285
A35: 6.0 | B35: Cutover and Go-Live | C35: 420000 | D35: =C35/$C$38 -> 0.059456399
A36: 7.0 | B36: Hypercare and Closure | C36: 640000 | D36: =C36/$C$38 -> 0.090600227
A37: 8.0 | B37: PM, Quality and Governance (PM labour, travel, PMO, tooling) | C37: 890000 | D37: =C37/$C$38 -> 0.12599094
B38: Total direct | C38: =SUM(C30:C37) -> 7064000 | D38: =SUM(D30:D37) -> 1
B39: Shared costs (GCP, MSP, licences) are apportioned to phases by effort share.
B41: Check: phase allocation = direct cost | C41: =IF(C38=C22,"OK","CHECK") -> OK
B42: Check: direct cost = Cash Flow direct total | C42: =IF(C22='Cash Flow'!H16,"OK","CHECK") -> OK
B43: Check: BAC = Cash Flow BAC | C43: =IF(C24='Cash Flow'!H18,"OK","CHECK") -> OK

Sheet Cash Flow
A1: GCP ERP Migration: Monthly Cash Flow Projection (ZAR, excluding VAT)
A2: Karoo Retail Group | 5 Oct 2026 to 2 Apr 2027 | Matches SPMP Appendix B (Table 51). Blue = input; black = formula; green = link to another sheet.
A4: Cost line | B4: M1 (Oct) | C4: M2 (Nov) | D4: M3 (Dec) | E4: M4 (Jan) | F4: M5 (Feb) | G4: M6 (Mar) | H4: Total | J4: Assumption | K4: Value
A5: Labour (9 roles) | B5: 589000 | C5: 760500 | D5: 782500 | E5: 856000 | F5: 933000 | G5: 958000 | H5: =SUM(B5:G5) -> 4879000 | J5: Contingency rate (% of direct) | K5: 0.1
A6: GCP consumption | B6: 0 | C6: 30000 | D6: 90000 | E6: 110000 | F6: 150000 | G6: 240000 | H6: =SUM(B6:G6) -> 620000 | J6: Management reserve rate (% of direct) | K6: 0.05
A7: Google Cloud Partner (MSP) | B7: 0 | C7: 100000 | D7: 100000 | E7: 60000 | F7: 60000 | G7: 130000 | H7: =SUM(B7:G7) -> 450000 | J7: Approved BAC per SPMP (R) | K7: 7770400
A8: Connectivity | B8: 0 | C8: 40000 | D8: 50000 | E8: 30000 | F8: 30000 | G8: 30000 | H8: =SUM(B8:G8) -> 180000 | J8: Approved funding envelope per SPMP (R) | K8: 8123600
A9: Security, identity and Looker licences | B9: 0 | C9: 20000 | D9: 30000 | E9: 60000 | F9: 60000 | G9: 65000 | H9: =SUM(B9:G9) -> 235000
A10: Penetration test and POPIA review | B10: 0 | C10: 0 | D10: 0 | E10: 0 | F10: 150000 | G10: 70000 | H10: =SUM(B10:G10) -> 220000
A11: Training and certification | B11: 0 | C11: 20000 | D11: 20000 | E11: 25000 | F11: 35000 | G11: 60000 | H11: =SUM(B11:G11) -> 160000
A12: Tooling | B12: 30000 | C12: 20000 | D12: 20000 | E12: 20000 | F12: 15000 | G12: 15000 | H12: =SUM(B12:G12) -> 120000
A13: Load-shedding resilience | B13: 30000 | C13: 20000 | D13: 10000 | E13: 0 | F13: 0 | G13: 0 | H13: =SUM(B13:G13) -> 60000
A14: Travel | B14: 15000 | C14: 15000 | D14: 10000 | E14: 15000 | F14: 15000 | G14: 20000 | H14: =SUM(B14:G14) -> 90000
A15: Project office and miscellaneous | B15: 10000 | C15: 8000 | D15: 8000 | E15: 8000 | F15: 8000 | G15: 8000 | H15: =SUM(B15:G15) -> 50000
A16: Total direct cost | B16: =SUM(B5:B15) -> 674000 | C16: =SUM(C5:C15) -> 1033500 | D16: =SUM(D5:D15) -> 1120500 | E16: =SUM(E5:E15) -> 1184000 | F16: =SUM(F5:F15) -> 1456000 | G16: =SUM(G5:G15) -> 1596000 | H16: =SUM(H5:H15) -> 7064000
A17: Contingency (10% of month's direct cost) | B17: =B16*$K$5 -> 67400 | C17: =C16*$K$5 -> 103350 | D17: =D16*$K$5 -> 112050 | E17: =E16*$K$5 -> 118400 | F17: =F16*$K$5 -> 145600 | G17: =G16*$K$5 -> 159600 | H17: =H16*$K$5 -> 706400
A18: Planned spend incl. contingency | B18: =B16+B17 -> 741400 | C18: =C16+C17 -> 1136850 | D18: =D16+D17 -> 1232550 | E18: =E16+E17 -> 1302400 | F18: =F16+F17 -> 1601600 | G18: =G16+G17 -> 1755600 | H18: =H16+H17 -> 7770400
A19: Cumulative (cost baseline) | B19: =B18 -> 741400 | C19: =B19+C18 -> 1878250 | D19: =C19+D18 -> 3110800 | E19: =D19+E18 -> 4413200 | F19: =E19+F18 -> 6014800 | G19: =F19+G18 -> 7770400
A20: Cumulative % of BAC | B20: =B19/$H$18 -> 0.095413364 | C20: =C19/$H$18 -> 0.24171857 | D20: =D19/$H$18 -> 0.40033975 | E20: =E19/$H$18 -> 0.56795017 | F20: =F19/$H$18 -> 0.77406569 | G20: =G19/$H$18 -> 1
A21: Cumulative direct only | B21: =B16 -> 674000 | C21: =B21+C16 -> 1707500 | D21: =C21+D16 -> 2828000 | E21: =D21+E16 -> 4012000 | F21: =E21+F16 -> 5468000 | G21: =F21+G16 -> 7064000
A22: Management reserve (5% of direct, SteerCo; outside BAC) | H22: =H16*$K$6 -> 353200
A23: Total funding envelope | H23: =H18+H22 -> 8123600
A24: Check: BAC equals approved baseline | H24: =IF(ROUND(H18,0)=K7,"OK","CHECK") -> OK
A25: Check: funding envelope equals approved figure | H25: =IF(ROUND(H23,0)=K8,"OK","CHECK") -> OK
A26: Check: labour total equals Resources sheet (hours x rate) | H26: =IF(H5=Resources!G16,"OK","CHECK") -> OK
A27: Check: non-labour total equals Budget sheet (Table 19) | H27: =IF(SUM(H6:H15)=Budget!C16,"OK","CHECK") -> OK
A28: Check: cumulative baseline ends at BAC | H28: =IF(G19=H18,"OK","CHECK") -> OK

Sheet Risk Register
A1: GCP ERP Migration: Risk Register
A2: Supports SPMP Section 11 and Appendix C (Table 52). Score = P x I. Low 1-4, Medium 5-9, High 10-14, Critical 15-25.
A4: ID | B4: Risk (cause → event → effect) | C4: P | D4: I | E4: Score | F4: Rating | G4: Strategy | H4: Response actions | I4: Owner | J4: EMV probability | K4: EMV impact (R) | L4: EMV (R)
A5: R01 | B5: Data loss or corruption during extract, transform and load → incorrect stock, financial or customer data | C5: 3 | D5: 5 | E5: =C5*D5 -> 15 | F5: =IF(E5>=15,"Critical",IF(E5>=10,"High",IF(E5>=5,"Medium","Low"))) -> Critical | G5: Mitigate | H5: Two full mock migrations; checksums and row counts; financial control totals signed by Finance; immutable backups; legacy kept intact for rollback | I5: Data Migration Engineer | J5: 0.35 | K5: 400000 | L5: =IF(J5="","",J5*K5) -> 140000
A6: R02 | B6: Cutover exceeds the approved window (slow sync, failed step) → trading disruption | C6: 3 | D6: 5 | E6: =C6*D6 -> 15 | F6: =IF(E6>=15,"Critical",IF(E6>=10,"High",IF(E6>=5,"Medium","Low"))) -> Critical | G6: Mitigate + contingency | H6: Timed runbook rehearsed twice; delta-sync; checkpoints CP1-CP4; MSP surge; rollback; fallback window 19-22 Mar | I6: Cloud Migration Engineer | J6: 0.35 | K6: 250000 | L6: =IF(J6="","",J6*K6) -> 87500
A7: R03 | B7: GCP cost overrun (oversized VMs, orphaned resources, data egress) → budget breach | C7: 4 | D7: 3 | E7: =C7*D7 -> 12 | F7: =IF(E7>=15,"Critical",IF(E7>=10,"High",IF(E7>=5,"Medium","Low"))) -> High | G7: Mitigate | H7: Budgets and alerts (70/85/100%); mandatory tags; auto-shutdown; right-sizing each sprint; reserved capacity only after stabilisation; monthly FinOps review | I7: Solution Architect | J7: 0.6 | K7: 150000 | L7: =IF(J7="","",J7*K7) -> 90000
A8: R04 | B8: Security breach or cloud misconfiguration (open storage, excessive privileges) → personal information exposed | C8: 3 | D8: 5 | E8: =C8*D8 -> 15 | F8: =IF(E8>=15,"Critical",IF(E8>=10,"High",IF(E8>=5,"Medium","Low"))) -> Critical | G8: Mitigate + transfer | H8: Policy-as-code guardrails; MFA and Context-Aware Access; PAM; private endpoints; Security Command Center; CIS hardening; independent pen test; incident plan; cyber-insurance check | I8: Security and IAM Engineer | J8: 0.35 | K8: 300000 | L8: =IF(J8="","",J8*K8) -> 105000
A9: R05 | B9: POPIA non-compliance (missing operator agreements, unlawful cross-border transfer, late breach notification) → regulatory action and reputational loss | C9: 2 | D9: 5 | E9: =C9*D9 -> 10 | F9: =IF(E9>=15,"Critical",IF(E9>=10,"High",IF(E9>=5,"Medium","Low"))) -> High | G9: Avoid + mitigate | H9: Production data in africa-south1 only; DR copies in europe-west4 justified under POPIA s72(1)(a), encrypted with keys held in South Africa; operator agreements (s21) before data loads; DPIA; breach-response process; Information Officer sign-off at G3 and G6 | I9: Project Manager | L9: =IF(J9="","",J9*K9)
A10: R06 | B10: Skills gap in GCP, IaC, Looker and cloud operations → errors, delay and poor supportability | C10: 4 | D10: 3 | E10: =C10*D10 -> 12 | F10: =IF(E10>=15,"Critical",IF(E10>=10,"High",IF(E10>=5,"Medium","Low"))) -> High | G10: Mitigate | H10: Certification and training plan; MSP knowledge transfer; pair working; runbooks; contractor replacement guarantee | I10: BA and Change Lead | L10: =IF(J10="","",J10*K10)
A11: R07 | B11: Vendor lock-in (GCP-specific PaaS, proprietary tooling, ERP vendor terms) → limited future options | C11: 3 | D11: 3 | E11: =C11*D11 -> 9 | F11: =IF(E11>=15,"Critical",IF(E11>=10,"High",IF(E11>=5,"Medium","Low"))) -> Medium | G11: Mitigate + accept | H11: Terraform IaC; standard interfaces (SQL, REST); data-portability and exit clauses; documented exit strategy | I11: Solution Architect | L11: =IF(J11="","",J11*K11)
A12: R08 | B12: Undocumented ERP dependencies (batch jobs, hard-coded IPs, EDI, POS links) → failures after migration | C12: 4 | D12: 4 | E12: =C12*D12 -> 16 | F12: =IF(E12>=15,"Critical",IF(E12>=10,"High",IF(E12>=5,"Medium","Low"))) -> Critical | G12: Mitigate | H12: Migration Center dependency analysis; capture network flows across a month-end; inventory of 14 interfaces; SIT for every interface; business walk-through | I12: App Modernisation Developer | J12: 0.55 | K12: 200000 | L12: =IF(J12="","",J12*K12) -> 110000
A13: R09 | B13: Scope creep (new ERP features, extra BI reports) → schedule and cost overrun | C13: 4 | D13: 3 | E13: =C13*D13 -> 12 | F13: =IF(E13>=15,"Critical",IF(E13>=10,"High",IF(E13>=5,"Medium","Low"))) -> High | G13: Avoid + mitigate | H13: Signed scope baseline; backlog swap rule; CCB; Product Owner prioritisation; visible change log | I13: Project Manager | L13: =IF(J13="","",J13*K13)
A14: R10 | B14: Load-shedding or power/connectivity failure during data sync, cutover or in the war-room → delay or data-transfer errors | C14: 3 | D14: 3 | E14: =C14*D14 -> 9 | F14: =IF(E14>=15,"Critical",IF(E14>=10,"High",IF(E14>=5,"Medium","Low"))) -> Medium | G14: Mitigate | H14: UPS and inverters; LTE failover; GCP-hosted jump boxes; runbook power and connectivity checks; dual circuits | I14: Cloud Migration Engineer | L14: =IF(J14="","",J14*K14)
A15: R11 | B15: Loss of a key team member in a scarce-skills market → delay and knowledge loss | C15: 3 | D15: 4 | E15: =C15*D15 -> 12 | F15: =IF(E15>=15,"Critical",IF(E15>=10,"High",IF(E15>=5,"Medium","Low"))) -> High | G15: Mitigate + transfer | H15: Backup pairs; documentation in repository; 5-day replacement guarantee; recognition and retention actions; MSP bench | I15: Project Manager | L15: =IF(J15="","",J15*K15)
A16: R12 | B16: Circuit delivery delay or inadequate bandwidth/latency → slow migration and poor performance | C16: 3 | D16: 4 | E16: =C16*D16 -> 12 | F16: =IF(E16>=15,"Critical",IF(E16>=10,"High",IF(E16>=5,"Medium","Low"))) -> High | G16: Mitigate | H16: Order by 30 Oct; Cloud VPN fallback; compressed backup seeding and log shipping; latency tests to stores in Discovery; QoS | I16: Cloud Migration Engineer | L16: =IF(J16="","",J16*K16)
A17: R13 | B17: Business SMEs unavailable during Black Friday, festive trading and month-end → delayed UAT and requirements | C17: 4 | D17: 3 | E17: =C17*D17 -> 12 | F17: =IF(E17>=15,"Critical",IF(E17>=10,"High",IF(E17>=5,"Medium","Low"))) -> High | G17: Avoid + mitigate | H17: Calendar aligned to trading; SME time committed by COO; early sessions in Nov and Jan-Feb; delegates; recorded demos | I17: BA and Change Lead | L17: =IF(J17="","",J17*K17)
A18: R14 | B18: Looker data-quality, performance or governance issues → loss of trust in reports | C18: 3 | D18: 3 | E18: =C18*D18 -> 9 | F18: =IF(E18>=15,"Critical",IF(E18>=10,"High",IF(E18>=5,"Medium","Low"))) -> Medium | G18: Mitigate | H18: KPI definitions signed by owners; reconcile to ERP; row-level access policy test cases; incremental refresh; workspace governance rules | I18: Looker Developer | L18: =IF(J18="","",J18*K18)
A19: R15 | B19: MSP or vendor under-performance, or Google Cloud regional incident in a critical window → delay | C19: 2 | D19: 4 | E19: =C19*D19 -> 8 | F19: =IF(E19>=15,"Critical",IF(E19>=10,"High",IF(E19>=5,"Medium","Low"))) -> Medium | G19: Transfer + mitigate | H19: SLAs with service credits; named deputy; milestone payments; zone-redundant design and DR; freeze windows | I19: Project Manager | L19: =IF(J19="","",J19*K19)
A20: R16 | B20: ZAR depreciation raises USD-linked GCP and licence costs → budget pressure | C20: 3 | D20: 3 | E20: =C20*D20 -> 9 | F20: =IF(E20>=15,"Critical",IF(E20>=10,"High",IF(E20>=5,"Medium","Low"))) -> Medium | G20: Transfer + accept | H20: ZAR billing through Google Cloud reseller; contingency; Finance hedging; reserved capacity after stabilisation | I20: Project Manager | L20: =IF(J20="","",J20*K20)
A21: R17 | B21: Poor user adoption and resistance to change among ERP users and store managers → productivity loss | C21: 3 | D21: 3 | E21: =C21*D21 -> 9 | F21: =IF(E21>=15,"Critical",IF(E21>=10,"High",IF(E21>=5,"Medium","Low"))) -> Medium | G21: Mitigate | H21: Change and communication plan; super-user network; role-based training; early demos; hypercare floorwalkers | I21: BA and Change Lead | L21: =IF(J21="","",J21*K21)
B23: Summary | C23: Count
B24: Critical | C24: =COUNTIF($F$5:$F$21,B24) -> 4
B25: High | C25: =COUNTIF($F$5:$F$21,B25) -> 7
B26: Medium | C26: =COUNTIF($F$5:$F$21,B26) -> 6
B27: Low | C27: =COUNTIF($F$5:$F$21,B27) -> 0
B28: Total baseline exposure (sum of scores) | C28: =SUM(E5:E21) -> 196
B29: Target exposure by G6 (40% reduction) | C29: =ROUND(C28*0.6,0) -> 118
B30: EMV of top five risks (R) | C30: =SUM(L5:L21) -> 532500
B31: Contingency reserve (R) | C31: ='Cash Flow'!H17 -> 706400
B32: EMV as % of contingency | C32: =C30/C31 -> 0.7538222
B33: Check: exposure = 196 (SPMP Appendix C) | C33: =IF(C28=196,"OK","CHECK") -> OK

Sheet RACI
A1: GCP ERP Migration: RACI Matrix
A2: Supports SPMP Appendix D (Table 53). R = Responsible; A = Accountable (exactly one per row); C = Consulted; I = Informed.
A4: # | B4: Activity / deliverable | C4: PM | D4: SA | E4: CE | F4: DE | G4: AD | H4: BI | I4: SE | J4: QA | K4: BA | L4: A count | M4: Check
A5: 1 | B5: Charter, SPMP and baselines | C5: A/R | D5: C | E5: I | F5: I | G5: I | H5: I | I5: C | J5: C | K5: C | L5: =COUNTIF(C5:K5,"A*") -> 1 | M5: =IF(L5=1,"OK","CHECK") -> OK
A6: 2 | B6: Requirements and scope baseline | C6: A | D6: C | E6: I | F6: C | G6: C | H6: C | I6: C | J6: C | K6: R | L6: =COUNTIF(C6:K6,"A*") -> 1 | M6: =IF(L6=1,"OK","CHECK") -> OK
A7: 3 | B7: Discovery and 6R migration strategy | C7: A | D7: R | E7: C | F7: C | G7: C | H7: I | I7: C | J7: I | K7: C | L7: =COUNTIF(C7:K7,"A*") -> 1 | M7: =IF(L7=1,"OK","CHECK") -> OK
A8: 4 | B8: Target architecture and security design | C8: C | D8: A/R | E8: R | F8: C | G8: C | H8: C | I8: R | J8: I | K8: I | L8: =COUNTIF(C8:K8,"A*") -> 1 | M8: =IF(L8=1,"OK","CHECK") -> OK
A9: 5 | B9: Landing zone and connectivity build | C9: I | D9: A | E9: R | F9: I | G9: I | H9: I | I9: R | J9: I | K9: I | L9: =COUNTIF(C9:K9,"A*") -> 1 | M9: =IF(L9=1,"OK","CHECK") -> OK
A10: 6 | B10: Identity and access management | C10: I | D10: C | E10: C | F10: I | G10: C | H10: C | I10: A/R | J10: I | K10: C | L10: =COUNTIF(C10:K10,"A*") -> 1 | M10: =IF(L10=1,"OK","CHECK") -> OK
A11: 7 | B11: Data migration (mapping, ETL, mocks, reconciliation) | C11: I | D11: C | E11: C | F11: A/R | G11: C | H11: C | I11: C | J11: R | K11: C | L11: =COUNTIF(C11:K11,"A*") -> 1 | M11: =IF(L11=1,"OK","CHECK") -> OK
A12: 8 | B12: Application replatform and integrations | C12: I | D12: C | E12: R | F12: C | G12: A/R | H12: I | I12: C | J12: C | K12: C | L12: =COUNTIF(C12:K12,"A*") -> 1 | M12: =IF(L12=1,"OK","CHECK") -> OK
A13: 9 | B13: Looker model and reports | C13: I | D13: C | E13: I | F13: R | G13: C | H13: A/R | I13: C | J13: C | K13: R | L13: =COUNTIF(C13:K13,"A*") -> 1 | M13: =IF(L13=1,"OK","CHECK") -> OK
A14: 10 | B14: Security hardening and pen-test coordination | C14: I | D14: C | E14: R | F14: I | G14: C | H14: I | I14: A/R | J14: C | K14: I | L14: =COUNTIF(C14:K14,"A*") -> 1 | M14: =IF(L14=1,"OK","CHECK") -> OK
A15: 11 | B15: POPIA compliance and DPIA | C15: A | D15: C | E15: I | F15: C | G15: I | H15: C | I15: R | J15: I | K15: C | L15: =COUNTIF(C15:K15,"A*") -> 1 | M15: =IF(L15=1,"OK","CHECK") -> OK
A16: 12 | B16: Test planning, SIT, UAT and defect management | C16: I | D16: C | E16: C | F16: C | G16: C | H16: C | I16: C | J16: A/R | K16: R | L16: =COUNTIF(C16:K16,"A*") -> 1 | M16: =IF(L16=1,"OK","CHECK") -> OK
... A24: 20 | B24: Project closure and lessons learned | C24: A/R | D24: C | E24: C | F24: C | G24: C | H24: C | I24: C | J24: C | K24: C | L24: =COUNTIF(C24:K24,"A*") -> 1 | M24: =IF(L24=1,"OK","CHECK") -> OK
B25: Activities where role is Accountable | C25: =COUNTIF(C5:C24,"A*") -> 11 | D25: =COUNTIF(D5:D24,"A*") -> 2 | E25: =COUNTIF(E5:E24,"A*") -> 0 | F25: =COUNTIF(F5:F24,"A*") -> 1 | G25: =COUNTIF(G5:G24,"A*") -> 1 | H25: =COUNTIF(H5:H24,"A*") -> 1 | I25: =COUNTIF(I5:I24,"A*") -> 2 | J25: =COUNTIF(J5:J24,"A*") -> 1 | K25: =COUNTIF(K5:K24,"A*") -> 1
B26: Activities where role is Responsible | C26: =COUNTIF(C5:C24,"*R") -> 4 | D26: =COUNTIF(D5:D24,"*R") -> 3 | E26: =COUNTIF(E5:E24,"*R") -> 7 | F26: =COUNTIF(F5:F24,"*R") -> 4 | G26: =COUNTIF(G5:G24,"*R") -> 3 | H26: =COUNTIF(H5:H24,"*R") -> 2 | I26: =COUNTIF(I5:I24,"*R") -> 6 | J26: =COUNTIF(J5:J24,"*R") -> 4 | K26: =COUNTIF(K5:K24,"*R") -> 5
B27: Check: every activity has exactly one A | M27: =IF(COUNTIF(M5:M24,"OK")=20,"OK","CHECK") -> OK

Sheet EVM
A1: GCP ERP Migration: Earned Value Worked Example (end of Month 3)
A2: Supports SPMP Sections 6.5, 14.1 and 14.2. EV and AC are illustrative status-date inputs.
A4: Measure | B4: Value | C4: Formula / source | D4: Status
A5: Budget at Completion (BAC) | B5: ='Cash Flow'!H18 -> 7770400 | C5: Cash Flow sheet
A6: Planned Value (PV), cumulative M3 | B6: ='Cash Flow'!D19 -> 3110800 | C6: Cash Flow cumulative baseline, Dec
A7: Earned Value (EV) | B7: 3000000 | C7: Input: value of work completed
A8: Actual Cost (AC) | B8: 3100000 | C8: Input: cost booked to date
A9: Cost Variance (CV) | B9: =B7-B8 -> -100000 | C9: EV - AC
A10: Schedule Variance (SV) | B10: =B7-B6 -> -110800 | C10: EV - PV
A11: CPI | B11: =B7/B8 -> 0.96774194 | C11: EV / AC | D11: =IF(B11>=0.95,"Green",IF(B11>=0.9,"Amber","Red")) -> Green
A12: SPI | B12: =B7/B6 -> 0.96438215 | C12: EV / PV | D12: =IF(B12>=0.95,"Green",IF(B12>=0.9,"Amber","Red")) -> Green
A13: Estimate at Completion (EAC) | B13: =B5/B11 -> 8029413.3 | C13: BAC / CPI
A14: Variance at Completion (VAC) | B14: =B5-B13 -> -259013.33 | C14: BAC - EAC
A15: TCPI (to BAC) | B15: =(B5-B7)/(B5-B8) -> 1.0214114 | C15: (BAC - EV) / (BAC - AC)
A16: EAC within funding envelope? | B16: =IF(B13<='Cash Flow'!H23,"Yes","No") -> Yes | C16: EAC vs total funding envelope
A18: Thresholds (SPMP 6.5 / 14.1): CPI and SPI >= 0.95 green; 0.90-0.95 amber; < 0.90 red (SteerCo exception report).
