Workbook

Sheet 00_Overview_&_PRISMA
A1: AI-DRIVEN MODEL ENGINEERING: SYSTEMATIC LITERATURE REVIEW (SLR)
A3: 1. PRISMA 2020 Study Selection Matrix (Core Databases: N = 27 Included Studies)
A5: Database / Repository | B5: Records Identified (search hits) | C5: Retained after Title & Abstract (database interface) | D5: Records Logged for 2nd-Stage Screening | E5: Candidates after 2nd-Stage (logged, before de-dup) | F5: Included in Synthesis
A6: IEEE Xplore | B6: 318 | C6: 61 | D6: 83 | E6: 71 | F6: =COUNTIF(Final_Included_Studies!B2:B200,A6) -> 2
A7: SpringerLink | B7: 3093 | C7: 1192 | D7: 1050 | E7: 69 | F7: =COUNTIF(Final_Included_Studies!B2:B200,A7) -> 2
A8: ScienceDirect | B8: 1907 | C8: 126 | D8: 126 | E8: 13 | F8: =COUNTIF(Final_Included_Studies!B2:B200,A8) -> 9
A9: ACM Digital Library | B9: 2034 | C9: 23 | D9: 23 | E9: 10 | F9: =COUNTIF(Final_Included_Studies!B2:B200,A9) -> 6
A10: Scopus | B10: 140 | C10: 40 | D10: 40 | E10: 40 | F10: =COUNTIF(Final_Included_Studies!B2:B200,A10) -> 4
A11: Web of Science | B11: 93 | C11: 90 | D11: 90 | E11: 75 | F11: =COUNTIF(Final_Included_Studies!B2:B200,A11) -> 4
A12: Total Core SLR Corpus | B12: =SUM(B6:B11) -> 7585 | C12: =SUM(C6:C11) -> 1532 | D12: =SUM(D6:D11) -> 1412 | E12: =SUM(E6:E11) -> 278 | F12: =SUM(F6:F11) -> 27
A13: After de-duplication | D13: =D12-Dedup_Log!C47 -> 1366 | E13: 249
A14: Note: 'Included' counts each study under the database recorded in Final_Included_Studies. Four ACM studies (P04, P05, P06, P18) have no record in the ACM screening sheet and enter the PRISMA flow as 'identified via other methods'. Records Logged differs from Retained for IEEE Xplore (+22) and SpringerLink (−142); the 120-record net gap is shown in PRISMA_Flow.

Sheet Reconciliation_Summary
A1: FINAL RECONCILIATION — every location must agree on N and the PRISMA figures (FINAL_7)
A2: Location | B2: Value | C2: Expected | D2: Status | E2: Source / note
A3: 00_Overview_&_PRISMA — Included total (F12) | B3: ='00_Overview_&_PRISMA'!F12 -> 27 | C3: =PRISMA_Flow!C18 -> 27 | D3: =IF(B3=C3,"OK","MISMATCH") -> OK | E3: Formula
A4: PRISMA_Flow — Studies included in synthesis | B4: =PRISMA_Flow!C18 -> 27 | C4: =COUNTA(Final_Included_Studies!A2:A200) -> 27 | D4: =IF(B4=C4,"OK","MISMATCH") -> OK | E4: Formula
A5: PRISMA_Flow — Reconciliation check | B5: =PRISMA_Flow!C19 -> OK | C5: OK | D5: =IF(B5=C5,"OK","MISMATCH") -> OK | E5: Formula
A6: Final_Included_Studies — row count | B6: =COUNTA(Final_Included_Studies!A2:A200) -> 27 | C6: =PRISMA_Flow!C18 -> 27 | D6: =IF(B6=C6,"OK","MISMATCH") -> OK | E6: Formula
A7: Data Extraction — row count | B7: =COUNTA('Data Extraction'!A2:A200) -> 27 | C7: =PRISMA_Flow!C18 -> 27 | D7: =IF(B7=C7,"OK","MISMATCH") -> OK | E7: Formula
A8: Quality Assessment — row count | B8: =COUNTIF('Quality Assessment'!A3:A200,"P*") -> 27 | C8: =PRISMA_Flow!C18 -> 27 | D8: =IF(B8=C8,"OK","MISMATCH") -> OK | E8: Formula
A9: Study_Coding — row count | B9: =COUNTIF(Study_Coding!A3:A200,"P*") -> 27 | C9: =PRISMA_Flow!C18 -> 27 | D9: =IF(B9=C9,"OK","MISMATCH") -> OK | E9: Formula
A10: Maturity_Model — studies across Levels 1–6 | B10: =COUNT('Data Extraction'!AE2:AE200) -> 27 | C10: =PRISMA_Flow!C18 -> 27 | D10: =IF(B10=C10,"OK","MISMATCH") -> OK | E10: Formula
A11: Excluded_Records — rows | B11: =COUNTA(Excluded_Records!A2:A1000) -> 226 | C11: =PRISMA_Flow!C13+PRISMA_Flow!C15 -> 226 | D11: =IF(B11=C11,"OK","MISMATCH") -> OK | E11: Not retrieved + excluded with reasons
A12: Excluded_Records vs identified − included − earlier removals | B12: =COUNTA(Excluded_Records!A2:A1000) -> 226 | C12: =PRISMA_Flow!C3+PRISMA_Flow!C4-PRISMA_Flow!C18-PRISMA_Flow!C5-PRISMA_Flow!C7-PRISMA_Flow!C9-PRISMA_Flow!C11 -> 226 | D12: =IF(B12=C12,"OK","MISMATCH") -> OK | E12: 7,585 + 4 − N − 6,053 (title/abstract) − 120 (not logged) − 46 (duplicates) − 1,117 (2nd stage)
A13: Report — Figure 1 (PRISMA diagram) N | B13: 27 | C13: =PRISMA_Flow!C18 -> 27 | D13: =IF(B13=C13,"OK","MISMATCH") -> OK | E13: PRISMA 2020 diagram drawn from PRISMA_Flow; note states retrospective de-duplication
A14: Report — narrative 'N =' mentions (all 6) | B14: 27 | C14: =PRISMA_Flow!C18 -> 27 | D14: =IF(B14=C14,"OK","MISMATCH") -> OK | E14: All 'N =' mentions in SLR_AI_Driven_Model_Engineering_FINAL_7.docx read 27 (scripted check)
A15: Report — Table 5 year total / database total | B15: 27 | C15: =PRISMA_Flow!C18 -> 27 | D15: =IF(B15=C15,"OK","MISMATCH") -> OK | E15: Table 5 in SLR_AI_Driven_Model_Engineering_FINAL_7.docx
A16: Report — abstract N | B16: 27 | C16: =PRISMA_Flow!C18 -> 27 | D16: =IF(B16=C16,"OK","MISMATCH") -> OK | E16: Abstract states 27 primary studies
A18: PRISMA figures used everywhere: 7,585 identified; 6,053 excluded at title/abstract; 1,532 retained; 120 not logged; 1,412 logged; 46 duplicates; 1,366 unique; 1,117 excluded at 2nd stage (EC1 667, EC2 153, EC4 176, EC5 110, EC8 11); 249 sought; 222 not retrieved; 27 assessed; 4 excluded with reasons; 4 via other methods; N = 27.
A20: Report — Figure 3 bands vs Stage_Coverage | B20: match | C20: match | D20: =IF(B20=C20,"OK","MISMATCH") -> OK | E20: 12 stage bands recomputed; figure regenerated from this sheet
A21: Report — body page count (Introduction → before References) | B21: 27 | C21: 30 | D21: =IF(B21<=C21,"OK","MISMATCH") -> OK | E21: ≤ 30 required; total PDF 33 pp incl. cover/declaration (3) and references (3)
A22: Report — excluded studies (P16, P20, P23, P26, P29, P31, P34) cited only in Appendix B | B22: Appendix B only | C22: Appendix B only | D22: =IF(B22=C22,"OK","MISMATCH") -> OK | E22: Each has a reference-list entry; none is used as evidence in sections 3–8

Sheet IEEE Xplore
A1: IEEE Xplore screening log | B1: Database | C1: Reviewer(s) | D1: Title | E1: Authors | F1: Year | G1: Venue | H1: DOI / Link | I1: Abstract (paste) | J1: Reviewer 1 | K1: Reviewer 1 Decision | L1: Reviewer 2 | M1: Reviewer 2 Decision | N1: Final Decision | O1: Exclusion Reason (if excluded)
A2: 1 | B2: IEEE Xplore | C2: Phindile Mposwa, Sibongiseni Tsitsa | D2: A Catalogue of Model Smells and Refactoring Operations for Object-Oriented Software | E2: Brahmaleen K. Sidhu,Kawaljeet Singh,Neeraj Sharma | F2: 2018 | G2: Proceedings of the 2nd International Conference on Inventive Communication and Computational Technologies (ICICCT | H2: https://doi.org/10.1109/ICICCT.2018.8473027 | I2: The advent of Model Driven Engineering has observable behaviour. promoted software quality assurance activities to a higher level Model Driven Engineering (MDE) is being increasingly of abstraction than code, i.e. architectural models. Early adopted in development of complex software systems used quality assessment facilitates better design, reduces in high-reliability domains like aviation, automotive, maintenance costs, manages requirement volatility and leads to aerospace, and other embedded systems [3]. Model Driven faster software development. Less than optimal design decisions made during development and subsequent evolution Development (MDD2) is a model-pivoted development introduce smells in the software. Model Refactoring uncovers paradigm. MDD is followed by Architecture-Driven smells at architectural level and transforms graphical Modernization (ADM), which is a two-step evolutionary, representations of software to enhance design without affecting platform and language-independent maintenance paradigm. its observable behaviour. Focusing on object-oriented software Firstly, a model instance is created by reverse engineering systems, this paper presents a catalogue of smells and source code. This model is successively transformed to refactoring operations for UML class diagrams. The paper concludes by highlighting challenges in model refactoring and reach a higher abstraction level called Knowledge Discovery the potential of learning-based approach in automating the Metamodel (KDM3) [4]. The problems found in the target process. legacy system are solved by applying refactorings and optimizations at this level. In the second step, forward | J2: Phindile Mposwa | K2: Include | L2: Sibongiseni Tsitsa | M2: Include | N2: Include | O2: Included: addresses software/systems modelling; reverse engineers models from code
A3: 2 | B3: IEEE Xplore | C3: Phindile Mposwa, Sibongiseni Tsitsa | D3: A Comparative Study of Large Language Models for Model-Driven Reverse Engineering | E3: Faculty of Sciences and Techniques of Errachidia, UMI Faculty of Sciences and Techniques of Errachidia, UMI | F3: 2026 | H3: A Comparative Study of Large Language Models for Model-Driven Reverse Engineering | I3: The extraction of abstract models from the source In practice, many software systems were developed without codeisoneofthemainfocusesofmodel-drivenreverseengineer- explicit models or with models that are no longer maintained, ingandisparticularlyimportantforlegacysystems,whichdonot especially legacy systems [2]. As a result, understanding, have updated documentation. Recovering abstract models from evolving,ormodernizingsuchsystemsoftenrequiresrecover- legacy systems is complex, given that the technical constructs combinedwithdomain-levelconstructsareimplementedthrough ing high-level domain abstractions directly from source code. multiple layers of technology and system-specific rules. Current This recovery task is difficult because domain concepts are static analysis and heuristic-based approaches can struggle to coupled with technical infrastructure, framework code, and separatetheseconcerns.Therecentemergenceoflargelanguage platform-specific details [3]. models (LLMs) is promising with regard to modeling software, Recovering a PIM from existing code is more challenging but behaviors and expected outcomes related to LLMs when performing reverse engineering tasks are challenging. This pa- than forward modeling because the original domain intent per compares the performance of various LLMs on a reverse is not explicitly represented. Reverse engineering must infer engineeringtaskrelatedtotherecoveryofabstractmodelsfrom abstractions that were never formally modeled and must dis- the source code. This comparison aims to identify the domain tinguish between domain-relevant concepts and purely tech- constructs represented through an intermediate representation nical constructs. Existing model-driven reverse engineering of the source code. Three LLMs, namely ChatGPT, Claude, and Meta AI, were assessed on the same input representation, with (MDRE) approaches rely heavily on static analysis artifacts, each LLM performing the task of recovering abstract models such as abstra | J3: Phindile Mposwa | K3: Include | L3: Sibongiseni Tsitsa | M3: Include | N3: Include | O3: Included: applies AI to reverse engineering/code-to-model extraction; applies AI within model-driven engineering context
A4: 3 | B4: IEEE Xplore | C4: Phindile Mposwa, Sibongiseni Tsitsa | D4: A Digital Twin Modeling Code Generation Framework based on Large Language Model | E4: School of Automation Science and Electrical Engineering School of Automation Science and Electrical Engineering | H4: https://doi.org/10.1109/IECON55916.2024.10905976 | I4: Digital twin has made significant achievements in implementationstepsofdigitaltwintechnology[3].However, applications across various fields by bridging the gap between the process of digital twin modeling faces some challenges virtualandphysicalworld.However,themodelingofdigitaltwin summarized as follows. faces challenges of labor-intensive and time-consuming manual modeling or coding. With the emergence of artificial intelligence (1) Manual labor-intensive modeling: Current modeling foundation models, the integration of large language models software offers a method of manual manipulation, allow- (LLMs) and digital twin may contribute to enhancing modeling ing users to create detailed models by drag-and-drop and efficiency significantly. Therefore, in this paper, a framework interactivemodeling.However,thisprocessisoftenlabor- of digital twin modeling code generation is proposed based on LLMs.Giveninstructionsinnaturallanguageprompts,modeling intensive and time-consuming. code in digital twin software will be generated from LLMs. (2) High level of expertise for coding: Alternatively, some Firstly,atreediagram-basedcodegenerationmethodisproposed software enables users to generate modeling scenes di- to generate main section of modeling code. Additionally, a rectlybycodinganddebugging.Whilethisapproachcan randomized code completion method is proposed to complete be more efficient, it requires a high level of expertise, missing parts which are unspecified or unclear in prompts. Finally,acasestudyisgiveninNVIDIAOmniverseforadigital making it difficult for newcomers to adopt. twin construction based on framework proposed in this paper. (3) HallucinationscausedbyAIGCmodels:Emergingtech- IndexTerms—digitaltwin,largelanguagemodel,modelingand nologies empowered by artificial intelligence generated simulation, code generation, AI foundation model content (AIGC) technologies, like text-to-3D, allow for the rapid generation of 3D models through generative | J4: Phindile Mposwa | K4: Include | L4: Sibongiseni Tsitsa | M4: Include | N4: Include | O4: Included: applies identifiable AI technique; supports model-to-code synthesis
A5: 4 | B5: IEEE Xplore | C5: Phindile Mposwa, Sibongiseni Tsitsa | D5: A Federated Adaptive Large Language Model Fine-Tuning Framework for Software Development | F5: 2025 | H5: https://doi.org/10.1109/TSC.2025.3623626 | I5: Large Language Models (LLMs) have achieved re- stronger performance across a wide spectrum of NLP tasks, markableprogressincodeintelligencetasks,significantlyenhanc- includingmachinetranslationandquestionanswering[2],[3]. ingtheefficiencyofsoftwaredevelopment.However,severalchal- Recognizing that source code possesses structural and seman- lengesremain.First,fine-tuningLLMsforspecifictasksrequires tic characteristics analogous to natural language, researchers alargeamountoftask-specificlabeleddata,whichisoftencostly and time-consuming to acquire. Second, due to the sensitivity of haveextendedLLMstocode-relatedapplications,suchascode code data, high-quality internal datasets from different organi- generation,summarization,andtranslation[4].Theemergence zations cannot be directly shared or combined for fine-tuning. of code-oriented LLMs has further accelerated the paradigm Moreover, variations in programming languages across organi- shift toward Software 3.0, an era in which AI models can zationscanintroduceinterferenceduringthefine-tuningprocess. autonomouslyassist—orevenlead—softwareengineeringpro- Toaddressthesechallenges,weproposeF-CodeLLM,afederated adaptive large language model fine-tuning framework designed cesses[5].Despitetheimpressivezero-shotandfew-shotgen- forreal-worldsoftwaredevelopmentscenarios.Tothebestofour eralization capabilities of general-purpose LLMs, their perfor- knowledge,thisisthefirstapproachtoapplyfederatedlearningto mance often lags behind task-specific fine-tuned models [6]. thefine-tuningofcodeLLMs,enablingcollaborativemodelopti- For example, models such as CodeX tend to underperform mizationwhilepreservingtheprivacyofeachorganization’scode on domain-specific programming languages like SQL, which data.WedesignanefficientLLMfine-tuningmethodtomitigate the computational and communication overhead associated with contains multiple dialects that general LLMs are typically not collaborative fine-tuning. Experimental results demonstrate that t | J5: Phindile Mposwa | K5: Exclude | L5: Sibongiseni Tsitsa | M5: Exclude | N5: Exclude | O5: Excluded: Discusses AI for code/software tasks but does not address software model engineering (no UML, BPMN, DSL, metamodel, or model transformation involved)
A6: 5 | B6: IEEE Xplore | C6: Phindile Mposwa, Sibongiseni Tsitsa | D6: A Generic Metamodel for Cognitive-Affective Training of Users Using Serious Games | E6: GIDITIC, Universidad EAFIT GIDITIC, Universidad EAFIT GIDITIC, Universidad EAFIT, Colombia | F6: 2023 | H6: https://doi.org/10.1109/CLEI60451.2023.10346132 | I6: Model-Driven Engineering can play a crucial emotions [7], [8]. This definition of the metamodel allows role in developing serious training games. Model-Driven its instantiation. Besides, it is an advance regarding the Engineering benefits the creation of serious games by offering automatic code generation using each component of the a structured software modeling approach, resulting in cognitive-affective metamodel. enhanced productivity, quality, and maintainability of the The main objective of our research is to define and game software. These models can then be used to validate the cognitive-affective metamodel using a automatically generate code and other artifacts, significantly modeling tool. To formalize the metamodel, we conducted reducing development time and improving efficiency. We propose a metamodel that describes users' cognitive and several activities, including designing the model in Eclipse affective dimensions during a serious game, utilizing a set of Modeling Framework (EMF), defining semantics and classes that define the relationships between them based on a creating instances. To validate our metamodel, we use theoretical framework of cognitive functions and emotions. examples. We employed the Eclipse Modeling Framework to transform This work uses documentary research to explore the a primary model of the problem domain into a metamodel. metamodeling tools for automatic code generation. First, We then combine the cognitive and affective dimensions of the we conduct a descriptive analysis to compare model and formalize it into a generic metamodel for cognitive- metamodeling frameworks and select an MDE tool for affective training of users using serious games. Finally, we designing the cognitive-affective metamodel. We then use illustrate our approach with an example of instantiation of the model metamodel. We concluded with the importance of the MDE tool to design and validate the metamodel and Model-Driven Engineering in serious game development | J6: Phindile Mposwa | K6: Include | L6: Sibongiseni Tsitsa | M6: Include | N6: Include | O6: Included: addresses software/systems modelling; supports model-to-code synthesis
A7: 6 | B7: IEEE Xplore | C7: Phindile Mposwa, Sibongiseni Tsitsa | D7: A Metamodel for a DSL to Design Decision Support Systems in Smart Tourism | E7: Charaf Ouaddi, Lamya Benaddi, Adnane Souha, Lahbib Naimi, El mahi Bouziane and Abdeslam Jakimi∥ | F7: 2024 | H7: https://doi.org/10.1109/DASA63652.2024.10836366 | I7: ThedevelopmentofDecisionSupportSystems(DSS) Tourism, where decisions need to be made quickly based on for several companies operating in sectors such as tourism, real-time data. healthcare, or others, presents significant challenges due to the One solution to simplify and speed up the development of nature of their multi-component architecture. A typical DSS DSS is the use of Domain-Specific Languages (DSLs). DSLs consists of a data component, a model component incorporating machine learning and deep learning techniques, and a user arespecializedlanguagesdesignedforaspecificfield.InDSS interfacecomponent,eachonerequiresdiversetechnologies.This development,theycanbeusedtocreatemodelsandtemplates, complexity increases development time and effort, hindering the and automatically generate parts of the system’s code. By efficient design of DSS tailored to specific domains like tourism, using DSLs, developers can reduce the effort needed to build where real-time decision-making is essential. One promising ap- a DSS and make the process faster and more efficient. proachtoovercomethesechallengesistheuseofDomain-Specific Languages(DSLs).DSLsallowdeveloperstomodelandgenerate Several studies have proposed DSLs to simplify the de- code more efficiently by providing high-level abstractions suited velopment of applications such as mobile apps [6], websites to the domain. By leveraging DSLs, it is possible to simplify the [7], and chatbots [8]–[11]. These DSLs have been built using design process and automate the generation of code or parts metamodels and Frameworks like EMF (Eclipse Modeling of the DSS, thereby reducing the overall complexity and time Framework) which is widely used to create and edit the required for development. This paper proposes a metamodel for designing DSS, specifically for the Smart Tourism sector. The metamodel of a DSL. metamodel serves as a foundation for the creation of DSL. The The aim of this work is to propose a metamodel for de- goalistoprovideaso | J7: Phindile Mposwa | K7: Include | L7: Sibongiseni Tsitsa | M7: Include | N7: Include | O7: Included: addresses metamodel engineering with AI; applies AI to domain-specific language/model engineering
A8: 7 | B8: IEEE Xplore | C8: Phindile Mposwa, Sibongiseni Tsitsa | D8: A Review of Screenshot-to-Code Generation Systems | E8: Software Engineer, PayPal, USA VP Technology & Consulting, Rocket, USA | F8: 2026 | G8: Proceedings of the 5th International Conference on Communication, Computing and Electronics Systems (ICCCES-2026) | I8: The conversion of screenshots into source code is very than other development jobs. Moreover, the user interface important phase in the automation of user interface consumes 50% of the development time, while it accounts for development. There are artificial-based tools which can 48% of the code for the software on average [4]. understand images and further convert them into executable source code. These system’s performance is further improved In software development, screenshot to code creation with the incorporation of generative artificial intelligence. These becomes more and more crucial, particularly with the generative artificial intelligence-based systems achieve high application of artificial intelligence (AI) and machine accuracy in converting sketches into source code. Further these learning (ML) [5]. Iterative prototyping is used in the design systems are helpful for developers, otherwise it was time consuming and costly to convert images into source code and of GUIs, beginning with the creative method of creating developers often distracted from focusing on logic and drawings, which are basic handmade representations. It is a functionality. This review paper presents the existing studies useful pictorial method for quickly, easily, and affordably which generate source code from sketches using artificial communicating ideas, discussing them, and comparing intelligence and machine learning. In this paper, several studies various options. In the screenshot to code generation process, are evaluated and compared based on different parameters. Sketches are used to develop wireframes, which specify the Their strengths and weaknesses are also discussed in this paper. order of appearance and depict the framework and This review paper will help the researchers and authors working arrangement of the user interface, excluding any graphical in this area to further improve GUI design process and in elements like colors or pictures [6-8]. The design of the development | J8: Phindile Mposwa | K8: Include | L8: Sibongiseni Tsitsa | M8: Include | N8: Include | O8: Included: applies identifiable AI technique; supports model-to-code synthesis
A9: 8 | B9: IEEE Xplore | C9: Phindile Mposwa, Sibongiseni Tsitsa | D9: A Survey of Domain-Specific Fine-Tuned Large Language Models | E9: MobileInnovationsCorporation,NiagaraFalls,ONLGM,Canada | F9: 2026 | H9: https://doi.org/10.1109/ACCESS.2026.3658096 | I9: The advancement of large language models (LLMs), such as GPT-3, BERT, and Llama, has introduced a new era in natural language processing (NLP) as they have demonstrated exceptional capabilitiesacrossdiversetasks.Fine-tuningtheseLLMswithdomain-specificdatahasbecomeapopular practice,particularlyindomainslikeeducation,law,medicine,andsoftwaredevelopment.Thisprocessnot onlyempowersLLMswithdomainknowledgebutalsoenhancestheircapabilitiesbyaddressingissuessuch asreliabilityandreducingthechanceofhallucination.Thissurveyexaminesarangeofdomain-specificfine- tunedmodelsbyhighlightingtheiruniquecharacteristics,enhancementsinperformance,andthechallenges theyaddress,includingthedemandforextensivecomputationalresources.Furthermore,weexplorethefine- tuningmethodologies,includinginstructiontuningusedinthedevelopmentofthesemodels,andultimately, inform future research on the existing gaps and how to enhance the effective application of LLMs across diversedomains. INDEXTERMS Fine-tuning,fine-tunedlargelanguagemodels,largelanguagemodels,LLM. | J9: Phindile Mposwa | K9: Exclude | L9: Sibongiseni Tsitsa | M9: Exclude | N9: Exclude | O9: Excluded: Discusses AI for code/software tasks but does not address software model engineering (no UML, BPMN, DSL, metamodel, or model transformation involved)
A10: 9 | B10: IEEE Xplore | C10: Phindile Mposwa, Sibongiseni Tsitsa | D10: Accurate and Consistent Graph Model Generation from Text with Large Language Models | E10: Accurate and Consistent Graph Model Generation | F10: 2025 | H10: https://doi.org/10.1109/MODELS67397.2025.00018 | I10: Graphmodelgenerationfromnaturallanguagede- prioritizes generating models that accurately reflect such tex- scriptionisanimportanttaskwithmanyapplicationsinsoftware tualdescription,ignoringanyconstraints.Althoughsyntactical engineering. With the rise of large language models (LLMs), correctness is typically addressed in both cases, ensuring there is a growing interest in using LLMs for graph model bothaccuracyandconsistencyiscriticalforeffectivelyutiliz- generation. Nevertheless, LLM-based graph model generation typicallyproducespartiallycorrectmodelsthatsufferfromthree ing generated models in subsequent model-driven automation main issues: (1) syntax violations: the generated model may not processes, such as code generation [12] and model-based adhere to the syntax defined by its metamodel, (2) constraint testing [13]. Therefore, jointly considering both the accuracy inconsistencies: the structure of the model might not conform and consistency of models generated by LLMs is essential. to some domain-specific constraints, and (3) inaccuracy: due Problemstatement.DuetotheintrinsiclimitationsofLLMs, to the inherent uncertainty in LLMs, the models can include inaccurate, hallucinated elements. While the first issue is often the models they generate are typically partially correct and addressed through techniques such as constraint decoding or may exhibit issues in all three aspects: (1) syntax: the filtering, the latter two remain largely unaddressed. Motivated textual representation of the model may violate the syntax by recent self-consistency approaches in LLMs, we propose specified by the metamodel; (2) consistency: the structure a novel abstraction-concretization framework that enhances the of the graph model may conflict with domain-specific well- consistencyandqualityofgeneratedgraphmodelsbyconsidering multipleoutputsfromanLLM.Ourapproachfirstconstructsa formedness constraints [11]; and (3) quality: the generated probabilisticpartialmodelthataggregatesallcandidat | J10: Phindile Mposwa | K10: Include | L10: Sibongiseni Tsitsa | M10: Include | N10: Include | O10: Included: applies AI to model generation; addresses metamodel engineering with AI; applies AI within model-driven engineering context
A11: 10 | B11: IEEE Xplore | C11: Phindile Mposwa, Sibongiseni Tsitsa | D11: Aligning Crowd-Sourced Human Feedback for Reinforcement Learning on Code Generation by Large Language Models | F11: 2024 | G11: 4104 IEEETRANSACTIONSONBIGDATA,VOL.XX,NO.X,NOVEMBER2023 1 | H11: https://doi.org/10.1109/TBDATA.2024.3524104 | I11: This paper studies how AI-assisted programming program compared to how experienced programmers analyze and large language models (LLM) improve software developers’ acodesnippetonalgorithms?Withthegrowingavailabilityof ability via AI tools (LLM agents) like Github Copilot and extensive data, a key question arises: How can we effectively Amazon CodeWhisperer, while integrating human feedback to leverage unsupervised machine learning in combination with enhance reinforcement learning (RLHF) with crowd-sourced computationtoenhancetext-to-codegeneration.Additionally,we the naturalness hypothesis, while integrating human feedback demonstratethatourBayesianoptimizationframeworksupports through human-in-the-loop computation, to enhance and eval- AI alignment in code generation by distributing the feedback uate LLMs and LLM agents? collection burden, highlighting the value of collecting human Human-in-the-loop computation has the potential to greatly feedbackofgoodquality.Ourempiricalevaluationsdemonstrate improvethereadability,reliability,andtestabilityofgenerated the efficacy of this approach, showcasing how LLM agents can be effectively trained for improved text-to-code generation. Our code,whileeffectivelyaddressingAIalignmentissuesincode Bayesian optimization framework can be designed for general generation [15], [16], [17], [18]. The AI alignment challenge domain-specific languages, promoting the alignment of large inLLM-basedcodegenerationinvolvesensuringthatthegen- language model capabilities with human feedback in AI-assisted erated code meets requirements and is executable. LLMs may programming for code generation. prioritizefluencyoveraccuracy,producingcodethatcompiles | J11: Phindile Mposwa | K11: Include | L11: Sibongiseni Tsitsa | M11: Include | N11: Include | O11: Included: applies AI to model transformation; applies AI to domain-specific language/model engineering
A12: 11 | B12: IEEE Xplore | C12: Phindile Mposwa, Sibongiseni Tsitsa | D12: AskIt Unified Programming Interface for Programming with Large Language Models | E12: Amagasaki, Japan | F12: 2024 | H12: https://doi.org/10.1109/CGO57630.2024.10444830 | I12: Large Language Models (LLMs) exhibit a unique The rise of these emergent abilities holds significant im- phenomenonknownasemergentabilities,demonstratingadeptness plications for software development, potentially altering the across numerous tasks, from text summarization to code genera- very methods by which software is crafted. Developers can tion. While these abilities open up novel avenues in software incorporate LLMs within applications to handle tasks such as design and crafting, their incorporation presents substantial challenges. Developers face decisions regarding the use of LLMs questionanswering,textsummarization,orlanguagetranslation. for directly performing tasks within applications as well as Another application of LLMs is in code generation. Tools like for generating and executing code to accomplish these tasks. Jigsaw [13] and Codex/Copilot [8] harness LLMs to convert Moreover, effective prompt design becomes a critical concern, natural language descriptions into code. Even without these given the necessity of extracting data from natural language specific tools, developers can leverage LLM-based chatbots, outputs. To address these complexities, this paper introduces AskIt, a domain-specific language (DSL) specifically designed for like ChatGPT based on GPT-4 [14], BingAI, and Bard, for the LLMs. AskIt simplifies LLM integration by providing a unified same purpose. interface that not only allows for direct task execution using However, integrating LLMs into software development is LLMs but also supports the entire cycle of code generation and not without challenges. One primary decision developers face execution. This dual capability is achieved through (1) type- is whether to embed the LLM directly into the application or guided output control, (2) template-based function definitions, and (3) prompt generation for both usage modes. Our evalua- employ it for code generation. The distinction between these tions underscore AskIt’s effectiveness. Across | J12: Phindile Mposwa | K12: Include | L12: Sibongiseni Tsitsa | M12: Include | N12: Include | O12: Included: applies AI to domain-specific language/model engineering
A13: 12 | B13: IEEE Xplore | C13: Phindile Mposwa, Sibongiseni Tsitsa | D13: Augmenting the Generality and Performance of Large Language Models for Software Engineering | E13: Augmenting the Generality and Performance of | F13: 2025 | G13: 2025 IEEE/ACM 47th International Conference on Software Engineering: Companion Proceedings (ICSE-Companion) | H13: https://doi.org/10.1109/ICSE-Companion66252.2025.00059 | I13: Large Language Models (LLMs) are revolutioniz- researchers have also been concerned with building and eval- ing software engineering (SE), with special emphasis on code uatingLLMsacrossabroaderrangeofSEtasks,ashighlighted generation and analysis. However, their applications to broader in recent surveys [13]–[15]. Despite the variety of datasets, SEpracticesincludingconceptualization,design,andothernon- networkarchitectures,modelsizes,prompting,andfine-tuning code tasks, remain partially underexplored. This research aims to augment the generality and performance of LLMs for SE by techniques documented in these surveys, there is a high (1) advancing the understanding of how LLMs with different imbalancetowardcoding-relatedtasks.Furthermore,thereare characteristicsperformonvariousnon-codetasks,(2)evaluating no works focused on evaluating the foundational knowledge themassourcesoffoundationalknowledgeinSE,and(3)effec- (i.e., factual and conceptual knowledge [16]) of LLMs in SE. tively detecting hallucinations on SE statements. The expected Building on the ideas presented in [17], [18] regarding the contributions include a variety of LLMs trained and evaluated on domain-specific datasets, new benchmarks on foundational level of applicability that LLMs can potentially achieve, to knowledgeinSE,andmethodsfordetectinghallucinations.Initial effectively support SE practitioners in real-world scenarios, results in terms of performance improvements on various non- a certain level of generality (i.e., range of supported tasks) code tasks are promising. andperformancearerequired.Tosatisfythisdualneed,tothe | J13: Phindile Mposwa | K13: Exclude | L13: Sibongiseni Tsitsa | M13: Exclude | N13: Exclude | O13: Excluded: Discusses AI for code/software tasks but does not address software model engineering (no UML, BPMN, DSL, metamodel, or model transformation involved)
A14: 13 | B14: IEEE Xplore | C14: Phindile Mposwa, Sibongiseni Tsitsa | D14: Automated Business Process Model Generation with Large Language Models A Systematic Literature Review | E14: recently attracted growing attention at the intersection of Business Process Management (BPM), Natural | F14: 2026 | G14: IEEE Access. This is the author's version which has not been fully edited and | H14: https://doi.org/10.1109/ACCESS.2026.3723936 | I14: Theautomatedgenerationofbusinessprocessmodelsfromnaturallanguagedescriptionshas recently attracted growing attention at the intersection of Business Process Management (BPM), Natural Language Processing (NLP), and Large Language Models (LLMs). This paper presents a Systematic Literature Review (SLR) on the current state of research in this emerging field. Following the guidelines of Kitchenham et al. and the PRISMA framework, 29 studies published between January 1st, 2023 and March10th,2026wereidentified,selected,andanalyzed. Thereviewaddressestworesearchquestionsfocusingontheappliedmethodologicalapproaches,theused LLMs, the employed modeling languages, as well as the evaluation strategies, challenges, and limitations reportedintheliterature.TheresultsshowaclearshiftfromtraditionalNLP-basedtechniquestowardLLM- onlyandhybridapproaches.OpenAI’sGPTfamily,especiallyGPT-4anditsvariants,dominatesthefield, while BPMN is by far the most frequently used target process modeling language. Furthermore, existing studies evaluate automated process model generation primarily through output-focused methods, such as quantitativemetrics,expertreviews,andcomparisonswithalternativeorhuman-createdprocessmodels. Atthesametime,thereviewedstudiesrevealimportantchallenges,includingthecontinuedneedforhuman involvementandtheoutputquality.Overall,currentapproachesshowstrongpotential,buttheystillactmore asintelligentassistantsthanasfullyautonomousprocessmodelers. | J14: Phindile Mposwa | K14: Include | L14: Sibongiseni Tsitsa | M14: Include | N14: Include | O14: Included: applies AI to model generation; applies AI to BPMN/process model engineering
A15: 14 | B15: IEEE Xplore | C15: Phindile Mposwa, Sibongiseni Tsitsa | D15: Automated Classification of Metamodel Repositories A Machine Learning Approach | E15: Phuong T. Nguyen, Juri Di Rocco, Ludovico Iovino | F15: 2019 | H15: https://doi.org/10.1109/MODELS.2019.00011 | I15: Manualclassificationmethodsofmetamodelreposi- strictly depends on the chosen similarity measure. Structural toriesrequirehighlytrainedpersonnelandtheresultsareusually similarities, which generally offer better accuracy, have poorer influencedbythesubjectivityofhumanperception.Therefore,au- performancewhencomparedwithtraditionallexicaltechniques, tomatedmetamodelclassificationisverydesirableandstringent. including cosine similarity [7] and dice coefficient [19] that in Inthiswork,MachineLearningtechniqueshavebeenemployed for metamodel automated classification. In particular, a tool contrast have limited accuracy [5]. implementing a feed-forward neural network is introduced to Machine Learning (ML) algorithms attempt to simulate classify metamodels. An experimental evaluation over a dataset humans’ learning activities, aiming to acquire real-world of 555 metamodels demonstrates that the technique permits to knowledge autonomously [41]. In this way, ML systems learn from manually classified data and effectively categorize are capable of generalizing from concrete examples, without incomingunlabeleddatawithaconsiderablyhighpredictionrate: thebestperformancecomprehends95.40%assuccessrate,0.945 needing to be manually programmed [21]. Thanks to this as precision, 0.938 as recall, and 0.942 as F1 score. characteristic, ML algorithms find their applications in various domains, including web search by learning from a user’s long- | J15: Phindile Mposwa | K15: Include | L15: Sibongiseni Tsitsa | M15: Include | N15: Include | O15: Included: addresses metamodel engineering with AI
A16: 15 | B16: IEEE Xplore | C16: Phindile Mposwa, Sibongiseni Tsitsa | D16: Automating Code Generation for MDE using Machine Learning | E16: King’s College London, Strand, | F16: 2023 | G16: 2023 IEEE/ACM 45th International Conference on Software Engineering: Companion Proceedings (ICSE-Companion) | H16: https://doi.org/10.1109/ICSE-Companion58688.2023.00060 | I16: The overall aim of our research is to improve the quality conditions, such as low complexity and redundancy, techniquesforsynthesizingcodegeneratorsintheModel-Driven high efficiency, etc. Engineering(MDE)context.Codegenerationisoneofthemain We aim to address this problem by automating the pro- elementsofModel-DrivenEngineering,involvingtransformation duction of code generators from examples, by using AI from specification models to produce executable code. A code generatorisdesignedtoreducethemanualprogramconstruction techniques, particularly symbolic machine learning (ML). work used to implement a software system, but building a code generator itself still currently needs much manual effort. II. RESEARCHHYPOTHESIS Meanwhile, existing code generators are typically not flexible to Our research hypothesis is that symbolic machine learning adjust for changing development requirements and are hard to canbeusedtolearncodegeneratorrulesfromexamples,ina reuse for different target languages. Therefore,weaimtoprovidetechniquestoimprovetheprocess way that enables the effective creation of code generators. of building code generators, and let them be more reusable. Currently, we researched the related new and traditional ap- III. STATEOFTHEART proachesforgeneratingcodeandprojectsusingAIforprogram Related work includes the mainstream MDE code gener- translation, code completion or program generation. Based on ation techniques of model-to-text, model-to-model and text- thisresearchwedecidedtofocusonasymbolicmachinelearning methodrelatedtotheprogramming-by-exampleconcepttobuild to-text transformation approaches, and more novel AI-based code generators. We use this “Code Generation By Example” program translation and code completion approaches. (CGBE) concept with tree-to-tree structure mappings as the information format. CGBE has good performance in terms of A. MDE Approaches trainingdatasetsizeandtimewhenappliedtolearningaUML- Model-to-Model (M2M) code generation approaches use | J16: Phindile Mposwa | K16: Include | L16: Sibongiseni Tsitsa | M16: Include | N16: Include | O16: Included: applies AI to UML/software model artefacts; applies AI within model-driven engineering context
A17: 16 | B17: IEEE Xplore | C17: Phindile Mposwa, Sibongiseni Tsitsa | D17: Automating Feature Requests for User-Driven Model Evolution at Runtime | E17: Dresden, Germany | F17: 2023 | G17: IEEE International Conference on Model Driven Engineering Languages and Systems Companion (MODELS-C) | H17: https://doi.org/10.1109/MODELS-C59198.2023.00149 | I17: As software projects progress, requirements can isimplementedbythedevelopmentteamandbecomespartof change and diverge between individual users. This happens in thenextrelease.Thisincrementalevolutionprocessisthestate particularinconsumersoftware.Subsequently,themaintenance of the art in software development. Because this process is ofsuchsoftwarebecomesacomplexandresource-intensivetask. complexandinvolvesdifferentpeople,errorscanhappenalong However, system parts can be modified and individualized at runtime if domain-specific evolution and configuration tasks the way. A request can be forgotten, ambiguously described, are transferred to the user. This reduces development efforts andthusfalselyrejectedormisunderstood.Theoverallprocess andcontributestosustainableandlong-livingsoftwareproducts may also take too long to deliver the feature in time. The calledeternalsoftware.Inmodel-drivenengineering,atargetfor workforce requirement and ineffective manual management this evolution is the domain’s metamodel. The adaptive object work make this process unsustainable. modelarchitecturestyleisaknownapproach,enablingvariable metamodelsatruntime.However,specifyingtransformationsfor Looking at the state of the art in research, system adaption evolving the metamodel can be challenging, particularly for and evolution at runtime became an established area over end-users. Editor-based solutions are complex to develop and the last two decades. This research involves different fields require multiple user interactions to achieve a desired change. and disciplines, such as Dynamic Software Product Lines [4], We propose a new approach based on textual feature requests the application of techniques from Model Driven Architec- from community-driven software development to address this issue.Wedefinealanguageforfeaturerequeststhattargetmodel ture at runtime [5]–[7], models@run.time [8], and Adaptive evolution.Wedefinethislanguageontopofformaldeltamodels. Object Models (AOM) [9], [10]. Conseq | J17: Phindile Mposwa | K17: Include | L17: Sibongiseni Tsitsa | M17: Include | N17: Include | O17: Included: addresses software/systems modelling
A18: 17 | B18: IEEE Xplore | C18: Phindile Mposwa, Sibongiseni Tsitsa | D18: BPMN-LLM Transforming BPMN Models Into Smart Contracts Using Large Language Models | F18: 2025 | G18: 2025 IEEE. All rights reserved, | H18: https://doi.org/10.1109/MS.2025.3553293 | J18: Phindile Mposwa | K18: Include | L18: Sibongiseni Tsitsa | M18: Include | N18: Include | O18: Included: applies AI to BPMN/process model engineering
A19: 18 | B19: IEEE Xplore | C19: Phindile Mposwa, Sibongiseni Tsitsa | D19: Creating and Migrating Chatbots with Conga | E19: Creating and Migrating Chatbots with C | F19: 2021 | G19: 2021 IEEE/ACM 43rd International Conference on Software Engineering: Companion Proceedings (ICSE-Companion) | H19: https://doi.org/10.1109/ICSE-Companion52605.2021.00030 | I19: Chatbots are agents that enable the interaction of channels.Choosinganinadequatetoolmayleadtoincreased users and software by means of written or spoken natural effort [4], lower chatbot quality or project failure. languageconversation.Theiruseisgrowing,andmanycompanies • Challenge 2: How to design chatbots independently of the arestartingtooffertheirservicesviachatbots,e.g.,forbooking, particulartooltoenableearlyreasoningandanalysis,prior shopping or customer support. For this reason, many chatbot to the implementation? Chatbot development tools are very developmenttoolshaveemerged,whichmakeschoosingthemost appropriatetooldifficult.Moreover,thereishardlyanysupport diverse, ranging from low-level programming frameworks for migrating chatbots between tools. (like Rasa) to lowcode development platforms based on To alleviate these issues, we propose a model-driven engi- forms(likeDialogflow).Graspingthedesignbehindachat- neering solution that includes: (i) a domain-specific language bot implementation may be challenging due to accidental, to model chatbots independently of the development tool; (ii) a recommender that suggests the most suitable development technical details of the tools themselves. tool for the given chatbot requirements and model; (iii) code • Challenge 3: How to keep up with the rapidly evolving generatorsthatsynthesizethechatbotcodefortheselectedtool; ecosystem of chatbot tools? With a few exceptions [5], and(iv)parserstoextractchatbotmodelsoutofexistingchatbot most chatbot tools are closed, proprietary software with no implementations.OursolutionissupportedbyawebIDEcalled supportformigrationbetweentools,e.g.,tobenefitfromthe CONGAthatcanbeusedforbothchatbotcreationandmigration. A demo video is available at https://youtu.be/3sw1FDdZ7XY. pricing plans of a competitor. This leads to vendor lock-in. | J19: Phindile Mposwa | K19: Include | L19: Sibongiseni Tsitsa | M19: Include | N19: Include | O19: Included: addresses software/systems modelling; generates or transforms models
A20: 19 | B20: IEEE Xplore | C20: Phindile Mposwa, Sibongiseni Tsitsa | D20: Cross-Domain Deep Code Search with Meta Learning | E20: YitianChai,HongyuZhang,BeijunShen,XiaodongGu | F20: 2022 | G20: 2022 IEEE/ACM 44th International Conference on Software Engineering (ICSE) | H20: https://doi.org/10.1145/3510003.3510125 | I20: 1 INTRODUCTION Recently,pre-trainedprogramminglanguagemodelssuchasCode- Recently,deepneuralnetworks(DNN)havebeenwidelyutilizedfor BERThavedemonstratedsubstantialgainsincodesearch.Despite codesearch[4,9,13,14,28,38].Unliketraditionalkeywordmatch- theirsuccess,theyrelyontheavailabilityoflargeamountsofpar- ingmethods[2,7,16,17,21,22],deepcodesearchmodelsemploy alleldatatofine-tunethesemanticmappingsbetweenqueriesand deepneuralnetworkstolearntherepresentationsofbothqueries code.Thisrestrictstheirpracticalityindomain-specificlanguages andcode,andmeasuretheirsimilaritiesthroughvectordistances. withrelativelyscarceandexpensivedata.Inthispaper,wepropose TheapplicationofDNNssignificantlyimprovestheunderstanding CDCS,anovelapproachfordomain-specificcodesearch.CDCS ofcodesemantics,therebyachievingsuperbperformanceincode employsatransferlearningframeworkwhereaninitialprogram searchtasks[9,13,18,40]. representationmodelispre-trainedonalargecorpusofcommon Amajorchallengefordeepcodesearchistheadaptationofdeep programminglanguages(suchasJavaandPython),andisfurther learningmodelstodomain-specificlanguages.State-of-the-artcode adaptedtodomain-specificlanguagessuchasSolidityandSQL.Un- searchmethodsaremainlydesignedforcommonlanguagessuch likecross-languageCodeBERT,whichisdirectlyfine-tunedinthe asJavaandPython.Theyrelyheavilyontheavailabilityoflarge targetlanguage,CDCSadaptsafew-shotmeta-learningalgorithm paralleldatatolearnthesemanticmappingsbetweencodeand calledMAMLtolearnthegoodinitializationofmodelparameters, naturallanguage[11].Ontheotherhand,thereisanemerging whichcanbebestreusedinadomain-specificlanguage.Weevaluate trendofdomain-specificlanguagessuchasSolidityforsmartcon- theproposedapproachontwodomain-specificlanguages,namely tracts[37,39,44]wherecodesearchisalsoneeded.Thereisoften SolidityandSQL,withmodeltransferredfromtwowidelyused insufficienttrainingdatainspecificdomains,causingpoorfitof languages(PythonandJava).ExperimentalresultsshowthatCDCS deeplearningmodels.Furthermore | J20: Phindile Mposwa | K20: Exclude | L20: Sibongiseni Tsitsa | M20: Exclude | N20: Exclude | O20: Excluded: Generates code directly without using or producing a software model; does not address model generation, transformation, or validation
A21: 20 | B21: IEEE Xplore | C21: Phindile Mposwa, Sibongiseni Tsitsa | D21: Data Analytics and Machine Learning Methods Techniques and Tool for Model-Driven Engineering of Smart IoT Services | E21: Data Analytics and Machine Learning Methods, | F21: 2021 | G21: 2021 IEEE/ACM 43rd International Conference on Software Engineering: Companion Proceedings (ICSE-Companion) | H21: https://doi.org/10.1109/ICSE-Companion52605.2021.00130 | I21: Thisdoctoraldissertationproposesanovelapproach their live-dimension (i.e., re-configuration, re-deployment, to enhance the development of smart services for the Internet live-update, live-enhancement and live-extension), and their of Things (IoT) and smart Cyber-Physical Systems (CPS). The self-dimension, referred to as Self-* capabilities (i.e., self- proposed approach offers abstraction and automation to the documenting, self-monitoring/diagnosis, self-optimizing, self- software engineering processes, as well as the Data Analytics (DA) and Machine Learning (ML) practices. This is realized healingandself-adapting/training)[3].Inaddition,theInternet in an integrated and seamless manner. We implement and is continuously expanding into a pervasive, global and col- validate the proposed approach by extending an open source laborative network of almost every entity/actor (i.e., object or modeling tool, called ThingML. ThingML is a domain-specific thing)surroundingus,includingahugenumberofsensorsand languageandmodelingtoolwithcodegenerationfortheIoT/CPS actuators in our smart environments, thus incorporating and domain.NeitherThingMLnoranyotherIoT/CPSmodelingtool supportsDA/MLatthemodelinglevel.Therefore,astheprimary integrating them into the IoT. Computing devices networked contribution of the doctoral dissertation, we add the necessary into the IoT are even much more heterogeneous, e.g., their syntaxandsemanticsconcerningDA/MLmethodsandtechniques power supplies/storages, processors, main memories and data tothemodelinglanguageofThingML.Moreover,wesupportthe storage capacities can have a very broad spectrum. Thus, APIsofseveralMLlibrariesandframeworksfortheautomated unprecedented challenges are faced by the designers and generation of the source code of the target software in Python andJava.Ourapproachenablesplatform-independent,aswellas developers of such systems [4]. platform-specificmodels.Further,weassistincarryingoutsemi- Prior research [3], [5] has proven that Mod | J21: Phindile Mposwa | K21: Include | L21: Sibongiseni Tsitsa | M21: Include | N21: Include | O21: Included: applies AI within model-driven engineering context
A22: 21 | B22: IEEE Xplore | C22: Phindile Mposwa, Sibongiseni Tsitsa | D22: Decomposing Semantic Loss in Model Transformations with Neural Embeddings | F22: 2026 | H22: https://doi.org/10.1109/ICECET65726.2026.11632676 | I22: Model transformations between heterogeneous Existing techniques can detect semantic loss [2], [3]— metamodels inevitably lose semantic information, yet practi- for instance, through bisimulation or behavioral analysis—but tioners lack tools to diagnose why losses occur: is the tar- they stop at a binary verdict: either preservation holds, or get metamodel inherently unable to express certain source it does not. A practitioner who discovers that a significant constructs, or does the transformation implementation fail to exploit available equivalences? We address this diagnostic gap fraction of source semantics is lost after migration cannot byextendingthemegamodel—thearchitecturalmodelcapturing distinguish between two fundamentally different situations: metamodelrelationships—withquantitativeexpressivitymetrics. We formalize two orthogonal loss components: the Metamodel 1) Inherent metamodel limitation. The target lan- Expressivity Gap (MEG) and the Transformation Coverage Ratio guage cannot express certain source constructs. Java’s (TCR), and prove they decompose total semantic loss exactly. synchronizedblockshavenostructuralequivalentin To make MEG computable without manual expert analysis, Python’sAST.Noamountoftransformationengineering we propose encoding metamodel concepts as vectors via neural will recover this loss; the practitioner must design ex- sentencetransformersandcomputingcross-metamodelsimilarity automatically. A proof-of-concept evaluation on Java-to-Python plicit compensation mechanisms (e.g., wrapping critical AST metamodels demonstrates the feasibility of the approach. sections with threading.Lock). | J22: Phindile Mposwa | K22: Include | L22: Sibongiseni Tsitsa | M22: Include | N22: Include | O22: Included: applies AI to model transformation; addresses metamodel engineering with AI
A23: 22 | B23: IEEE Xplore | C23: Phindile Mposwa, Sibongiseni Tsitsa | D23: Diagram-Aware Automatic Review of Software Design Documents Using Multimodal Large Language Models | E23: Kawasaki, Japan Kawasaki, Japan | F23: 2026 | G23: 2026 IEEE International Conference on Software Analysis, Evolution and Reengineering (SANER) | H23: https://doi.org/10.1109/SANER67736.2026.00108 | I23: With the growing capabilities of Large Language Models (LLMs), their application to software engineering tasks has garnered increasing attention. While our previous work focusedonautomatedreviewofsoftwaredesigndocumentscom- posedoftextandtables,diagram-basedartifactssuchasUMLor screentransitiondiagramsremainedoutsidethescopeofanalysis. Reviewing such documents requires accurate interpretation of structural and semantic elements, including nodes, edges, and transition conditions. Thispaperproposesahybriddiagram-understandingmethod thatleveragesmultimodalLLMstogetherwithdiagramstructure extracted from Office Open XML (OOXML) representations, guided by Chain-of-Thought prompting, to incrementally in- Fig.1. IllustrationofMultimodalLLMUtilizationintheReviewProcess terpret diagrams in real-world design documents. The method enables integrated analysis across diagrams, tables, and textual content within the review process. Evaluation results show that graph-structured UML-style diagrams, including screen tran- theproposedapproachachieveshighaccuracyintasksinvolving sition diagrams and business process flows. These diagrams structural recognition, such as consistency checking. However, encode functional behavior, UI flow, and system structure in the results also highlight persistent challenges in semantic-level review tasks, particularly in interpreting complex transition graph-based formats, and thus must be interpreted accurately conditions. These findings provide insights into the current to support comprehensive review. capabilitiesandlimitationsofmultimodalLLMsforhigh-stakes While recent multimodal LLMs such as GPT-4V and GPT- design document reviews. 4o support image input, our initial experiments indicated IndexTerms—SoftwareDesignReview,LargeLanguageMod- thatrawimage-baseddiagramcomprehensionisofteninsuffi- els, Diagram Understanding cient for high-stakes review tasks. Complex diagrams require precise recognition of node labels, edge relationships, and | J23: Phindile Mposwa | K23: Include | L23: Sibongiseni Tsitsa | M23: Include | N23: Include | O23: Included: applies AI to model transformation; applies AI to UML/software model artefacts
A24: 23 | B24: IEEE Xplore | C24: Phindile Mposwa, Sibongiseni Tsitsa | D24: Digital Forensics Domain and Metamodeling Development Approaches | E24: College of Computer Science and College of Computer Science and College of Computer Science and | F24: 2021 | H24: https://doi.org/10.1109/ICSCEE50312.2021.9497935 | I24: Metamodeling is used as a general technique for [14]. Therefore, semantic metamodeling language (high integrating and defining models from different domains. This abstract model) is required to organize, unify, and structure the technique can be used in diverse application domains, especially DFs domain knowledge in one standardized model. For this for purposes of standardization. Also, this process mainly has a purpose, the metamodeling approach is a proper method to focus on the identification of general concepts that exist in develop a sematic metamodeling language (metamodel) for the various problem domain and their relations and to solve DFs domain. Metamodeling is used as a general technique for complexity, interoperability, and heterogeneity aspects of integrating and defining models from different domains [15]. different domains. Several diverse metamodeling development Common concepts of these different views can be identified approaches have been proposed in the literature to develop and shared. The metamodeling technique consequently can be metamodels. Each metamodeling development process has some applied in quite different application domains, especially for advantages and disadvantages too. Therefore, the objective of standardization purposes. Metamodeling is simply the this paper is to provide a comprehensive review of existing identification of general concepts that exist in each problem metamodeling development approaches and conduct a domain and their relations. It is used to solve the complexity, comparative study among them-eventually selecting the best interoperability, and heterogeneity of the domain [16]. approach for metamodel development in the perspective of digital forensics. Metamodels should therefore be rigorously defined as well as being well-structured. The metamodel is a model about a | J24: Phindile Mposwa | K24: Include | L24: Sibongiseni Tsitsa | M24: Include | N24: Include | O24: Included: addresses software/systems modelling
A25: 24 | B25: IEEE Xplore | C25: Phindile Mposwa, Sibongiseni Tsitsa | D25: Enhancing Model-Driven Reverse Engineering Using Machine Learning | F25: 2024 | G25: 2024 IEEE/ACM 46th International Conference on Software Engineering: Companion Proceedings (ICSE-Companion) | H25: https://doi.org/10.1145/3639478.3639797 | I25: differentlevelscanbeautomaticallytransformedintoeachother. Organizationsoftenrelyonlargeapplicationsthatareclassifiedas Reverseengineeringtechniquesforsoftwaresystemshavebeenex- legacysystemsduetotheirdependenceonoutdatedprogramming tensivelystudiedoverthepast20years,andnumerousapproaches, languagesorplatforms.Tomodernizethesesystems,itisnecessary includingthemodel-drivenapproach(MDRE)—-thesubjectofour tounderstandtheirarchitecture,functionality,andbusinessrules. study—-havebeenintroduced.Raibuletetal.[19]presentedacom- Ourresearchaimstodefineanovelmodel-drivenreverseengineer- prehensiveanalysisofMDREapproachesintheliterature,upto ing(MDRE)approachtoextractUnifiedModelingLanguage(UML) 2017.Throughasystematicliteraturereview(SLR),theauthors andObjectConstraintLanguage(OCL)representationsfromsource highlight15MDREapproachesanddiscusstheirvariousfeatures codeusingLargeLanguageModels(LLMs). andobjectives.WealsoconductedanSLRof938relevantpublica- tionsinthisdomainfrom2000to2023togainacomprehensive understandingofcurrentresearchinMDREapproaches.Wefound | J25: Phindile Mposwa | K25: Include | L25: Sibongiseni Tsitsa | M25: Include | N25: Include | O25: Included: applies AI to reverse engineering/code-to-model extraction; applies AI to UML/software model artefacts; applies AI within model-driven engineering context
A26: 25 | B26: IEEE Xplore | C26: Phindile Mposwa, Sibongiseni Tsitsa | D26: Evaluating Security and Quality of Banking Software Generated by Large Language Models | E26: Evaluating Security and Quality of Banking | F26: 2025 | H26: https://doi.org/10.1109/ASYU67174.2025.11208402 | J26: Phindile Mposwa | K26: Exclude | L26: Sibongiseni Tsitsa | M26: Exclude | N26: Exclude | O26: Excluded: Discusses AI for code/software tasks but does not address software model engineering (no UML, BPMN, DSL, metamodel, or model transformation involved)
A27: 26 | B27: IEEE Xplore | C27: Phindile Mposwa, Sibongiseni Tsitsa | D27: Focus Session Hardware and Software Techniques for Accelerating Multimodal Foundation Models | E27: Focus Session: Hardware and Software Techniques | F27: 2026 | H27: https://doi.org/10.23919/DATE69613.2026.11539480 | I27: This work presents a multi-layered methodology for Key Challenges in Accelerating Multimodal Foundation Models (MFMs) efficientlyacceleratingmultimodalfoundationmodels(MFMs).It Energy-efficient Cross-modal Domain-specific Security & combineshardwareandsoftwareco-designoftransformerblocks Processing Integration & Adaptation Reliability with an optimization pipeline that reduces computational and Alignment memoryrequirements.Duringmodeldevelopment,itemploysper- formance enhancements through fine-tuning for domain-specific adaptation. Our methodology further incorporates hardware and AI software techniques for optimizing MFMs. Specifically, it em- ploys MFM compression using hierarchy-aware mixed-precision (cid:131)Low power/energy quantization and structural pruning for transformer blocks and (cid:131)Low latency MLP channels. It also optimizes operations through speculative (cid:131)High throughput decoding, model cascading that routes queries through a small- to-large cascade and uses lightweight self-tests to determine when to escalate to larger models, as well as co-optimization of sequence length, visual resolution & stride, and graph-level operator fusion. To efficiently execute the model, the processing dataflow is optimized based on the underlying hardware archi- tecture together with memory-efficient attention to meet on-chip bandwidth and latency budgets. To support this, a specialized hardwareacceleratorforthetransformerworkloadsisemployed, which can be developed through expert design or an LLM-aided designapproach.Wedemonstratetheeffectivenessoftheproposed methodologyonmedical-MFMsandoncodegenerationtasks,and conclude with extensions toward energy-efficient spiking-MFMs. | J27: Phindile Mposwa | K27: Exclude | L27: Sibongiseni Tsitsa | M27: Exclude | N27: Exclude | O27: Excluded: Editorial, preface, or tutorial without full technical results (does not present a framework, method, algorithm, tool, dataset, or empirical evaluation)
A28: 27 | B28: IEEE Xplore | C28: Phindile Mposwa, Sibongiseni Tsitsa | D28: From Conceptual Models to Knowledge Graphs A Generic Model Transformation Platform | E28: TU Wien, Business Informatics Group TU Wien, Business Informatics Group | F28: 2021 | G28: IEEE International Conference on Model Driven Engineering Languages and Systems Companion (MODELS-C) | H28: https://doi.org/10.1109/MODELS-C53483.2021.00093 | I28: Semantic processing of conceptual models is a fo- and UML profile models). The CM2KG platform thus excels cus of research since several years, bridging the disciplines existing works on graph-based analysis of conceptual models of knowledge-based systems, conceptual modeling, and model- by being generic (i.e., modeling language and modeling tool driven software engineering. With the uptake of Knowledge independent), extensible (i.e., new language- and tool-specific Graphs, the research in this area gained further momentum. In this paper, we introduce a generic and extensible platform transformationscanbeeasilyrealized),andscalable(i.e.,even thatenablestheautomatedtransformationofconceptualmodels verylargeKnowledgeGraphscanbeefficientlyprocessed[4]). intoKnowledgeGraphs.Theplatformcantransformanymodel As a running example, we show the transformation of created by a state-of-the-art metamodeling platform (EMF and conceptualmodelsoftheUnifiedModelingLanguage(UML) ADOxx)intostandardizedKnowledgeGraphrepresentationslike into Knowledge Graphs represented in GraphML (i.e., the GraphML, RDF, and OWL. In the paper at hand, we introduce ourplatformandevaluateitwithacorpusof5.000UMLmodels knowledgebase).Toexemplifythevalueofthetransformation that we transform into Knowledge Graphs and subsequently – or more particularly the value of the Knowledge Graph in exemplifytherichfunctionalitiesenabledbythegraphstructure MDSE – we show how the graph structure enables efficient by an automated detection of UML model smells. reasoning by means of graph queries. This reasoning aims to | J28: Phindile Mposwa | K28: Include | L28: Sibongiseni Tsitsa | M28: Include | N28: Include | O28: Included: applies AI to model transformation; applies AI to model repair/refactoring; addresses metamodel engineering with AI; applies AI to UML/software model artefacts
A29: 28 | B29: IEEE Xplore | C29: Phindile Mposwa, Sibongiseni Tsitsa | D29: From Requirements to Models A Case Study of Large Language Models on Epidemiological Modeling | E29: Aaditya Karamchandani, Fatemeh Seyeddabbaghi, and Marios Fokaefs | F29: 2025 | G29: 2025 IEEE International Conference on Collaborative Advances in Software and COmputiNg (CASCON) | H29: https://doi.org/10.1109/CASCON66301.2025.00082 | I29: Epidemiologicalmodelingisacriticalstepinunder- applications in specialized modeling contexts. However, the standing and studying diseases. Although conventional modeling applicationofLLMstostructuredscientificmodelingdomains, techniques exist, such as compartmental or agentic models, particularly epidemiological modeling, remains largely unex- supporting tools are not necessarily standardized. Consequently, plored territory requiring systematic investigation. learning a new tool may take a significant amount of effort. In thiswork,weexploretheuseofLargeLanguageModels(LLMs) This paper addresses the fundamental question of whether as a means to quickly transition from requirements, in the form of graphical model representations and initial parameters, LLMs can effectively bridge the gap between conceptual to a software-aided modeling platform with simulation and epidemiological models and their formal computational rep- verificationcapabilities.Ourmethodologyemploysametamodel- resentations. We investigate the capability of modern LLMs based language specification for prompt engineering, combined to automatically generate structured epidemiological mod- with multimodal inputs comprising textual descriptions and els from natural language descriptions and visual diagrams, epidemiological diagrams. We evaluated LLM performance in three epidemiological models of varying complexity: a simple focusing specifically on the EpiMDE platform [3] and its SIR compartmental model, a COVID-19 pandemic model, and Seirmodel XML format. Our approach leverages the mul- an HIV transmission model. Initial results demonstrate the timodal capabilities of contemporary LLMs to process both potentialofLLMstosignificantlyreducemanualmodelingeffort textual specifications and epidemiological diagrams, poten- while maintaining accuracy in structural representation and tially revolutionizing the model development workflow for parameter extraction. The study provides insights into optimal input confi | J29: Phindile Mposwa | K29: Include | L29: Sibongiseni Tsitsa | M29: Include | N29: Include | O29: Included: addresses metamodel engineering with AI; applies AI within model-driven engineering context
A30: 29 | B30: IEEE Xplore | C30: Phindile Mposwa, Sibongiseni Tsitsa | D30: From Zero to Sixty at the Speed of RAG Improving YAML Recipe Generation via Retrieval | F30: 2025 | G30: 2025 IEEE/ACM International Workshop on Large Language Models for Code (LLM4Code) | H30: https://doi.org/10.1109/LLM4Code66737.2025.00011 | I30: LLMs have been shown to match or even exceed configuration and software lifecycle management tools (such the performance of specialized Deep Learning models on code as maven and jules) remains relatively understudied, despite generation tasks for general purpose imperative languages, such thesedeclarativelanguagesmakingupconsiderableportionsof as Python, Java, C++, and Rust. Conversely, there is only industrial codebases. To our knowledge, one of the few works limited work investigating whether such impressive out of the boxgeneralizationtransfersontolessubiquitousdomain-specific isthatbyIBMResearchandRedHat[4],whichevaluatesthe languages,whichareoftendeclarative,basedonXML,JSON,or ability of LLMs in generating Ansible YAML IT automation YAML. To bridge this gap, we explore the capabilities of LLMs playbooks. In a similar spirit, our work seeks to understand for composing code automation recipes without resorting to any the ability of LLMs to generate YAML recipes for the code form of task-specific finetuning. We experiment with two GPT refactoring automation framework OpenRewrite [5]. versions and CodeLlama-13b-Instruct, and in our experiments, we find that after extensive prompt engineering and chain-of- OpenRewrite is an open source framework for large-scale thought prompting, these models’ accuracy in recipe selection code refactoring automation to help with API migrations, does not go beyond ≈ 30%. For parameter filling of YAML vulnerability patches, and maintaining stylistic consistency. recipes, the accuracy of these models remains below ≈ 50%. Internally,itworksbymodifyingtheformatting-preservingse- However,bydecomposingthetaskintotwostages:denseretrieval mantictreerepresentationofthecode,whichisthenconverted and generative slot filling, and while still keeping our setup training-free,themodelsareabletoattainanaccuracyinarange back to code. Core code transformations are implemented by of ≈ 50% to ≈ 67% in recipe selection, and ≈ 60% to ≈ 76% the OpenRewrite | J30: Phindile Mposwa | K30: Exclude | L30: Sibongiseni Tsitsa | M30: Exclude | N30: Exclude | O30: Excluded: Discusses AI for code/software tasks but does not address software model engineering (no UML, BPMN, DSL, metamodel, or model transformation involved)
A31: 30 | B31: IEEE Xplore | C31: Phindile Mposwa, Sibongiseni Tsitsa | D31: Generating Software Architecture Description from Source Code using Reverse Engineering and Large Language Model | E31: Source Code using Reverse Engineering and Large | F31: 2025 | H31: https://doi.org/10.1109/MODELS-C68889.2025.00080 | I31: Software Architecture Descriptions (SADs) are in- developers, each requiring a different level of abstraction. In dispensable for navigating the complexity of modern software this context, two views are especially critical: the static view, systems.Theyenablehigh-levelreasoning,guidedesigndecisions, typically presented as component diagrams, which describes and facilitate communication among diverse stakeholders. Yet structural elements and their relationships; and the behavioral in practice, SADs are frequently missing, outdated, or poorly alignedwiththesystem’sactualimplementation.Asaresult,de- view, often modeled through state machine diagrams, which velopersareforcedtoderivearchitecturalinsightsdirectlyfrom captures component dynamics and operational lifecycles. source code—a time-intensive task that increases mental effort, In practice, however, SADs are often missing, incomplete, slowsonboarding,andcontributestothegradualdegradationof or outdated [2]–[4]. Teams frequently rely on source code architectural clarity over a system’s lifetime. To address these as the sole reference point for understanding system struc- challenges, we propose an automated generation of SADs from source code by combining reverse engineering (RE) techniques ture and behavior. Yet, source code alone lacks architectural withLargeLanguageModel(LLM).Ourapproachrecoversboth abstraction and is not suited for stakeholder comprehension. static and behavioral views by extracting a comprehensive com- This gap leads to increased onboarding effort, reduced design ponentdiagram,filtersarchitecturallysignificantelements—core clarity, and a gradual erosion of system-level understanding, components—via prompt-guided LLM analysis, and generates especially in real-world and complex projects [4], [5]. state machine diagrams to model component behavior based on code logic. This dual-view representation offers a scalable and To mitigate this gap, reverse engineering (RE) [6] has maintainablealternativetom | J31: Phindile Mposwa | K31: Include | L31: Sibongiseni Tsitsa | M31: Include | N31: Include | O31: Included: applies AI to reverse engineering/code-to-model extraction
A32: 31 | B32: IEEE Xplore | C32: Phindile Mposwa, Sibongiseni Tsitsa | D32: Gotten A Model-Driven Solution to Engineer Domain-specific Metamorphic Testing Environments | E32: Madrid, Spain Madrid, Spain Madrid, Spain | F32: 2023 | G32: IEEE International Conference on Model Driven Engineering Languages and Systems Companion (MODELS-C) | H32: https://doi.org/10.1109/MODELS-C59198.2023.00021 | I32: Testing is essential for assessing the correctness of are input test cases related as required by a given MR (e.g., software systems. Metamorphic testing (MT) is an approach x 1 =−x 2 in our example). especially suited when the system under test lacks oracles, Typically,MTenginesarecreatedmanually,whichincursa or they are expensive to compute. However, creating an MT high effort and often leads to ad-hoc solutions that are hardly environmentforaspecificdomain(e.g.,cloudsimulation,model transformation, machine learning) requires substantial effort. extensible. This is so as a full-fledged MT solution needs to To alleviate these difficulties, we present a model-driven tool provide support to encode the MRs, generate follow-up test that automates the construction of MT environments. Starting cases,executetheSuTwiththetestcasesthatsatisfytheinput fromameta-modelwiththedomainconcepts,andadescription partoftheMRs,andcheckwhethertheexecutionresultsfulfil of the domain execution environment, our tool produces an theoutputpartoftheMRs.However,MRsarefrequentlyhard- MT environment featuring comprehensive support for the MT process.Thisincludesthedefinitionofdomain-specificmetamor- codedwithintheMTsolution,whichisnotextensibleanddoes phic relations, their evaluation, detailed reporting of the testing not offer full support for the MT cycle [7]. results, andthe automatedsearch-based generationof follow-up To alleviate this problem, we propose GOTTEN, a model- test cases. This paper illustrates the tool on a case-study in the driven solution to engineer MT environments for specific domain of video streaming APIs. A video showcasing the tool is domains[7].TheapproachisbasedonaDSLtospecifyMRs, available at https://youtu.be/DeuIW6V4LaQ. IndexTerms—Metamorphictesting,Model-drivenengineering, andonrepresentingtheinputtestcasesasmodelsconformant Domain-specific languages, Video streaming APIs to a domain meta-model. GOTTEN provides full support for the MT cycle, including the automatic | J32: Phindile Mposwa | K32: Include | L32: Sibongiseni Tsitsa | M32: Include | N32: Include | O32: Included: applies AI to model transformation; addresses metamodel engineering with AI; applies AI to domain-specific language/model engineering; applies AI within model-driven engineering context
A33: 32 | B33: IEEE Xplore | C33: Phindile Mposwa, Sibongiseni Tsitsa | D33: Harnessing ChatGPT for Model Transformation in Software Architecture From UML State Diagrams to Rebeca Models for Formal Verification | E33: School of Innovation, Design and Engineering | F33: 2025 | G33: 2025 IEEE 22nd International Conference on Software Architecture Companion (ICSA-C) | H33: https://doi.org/10.1109/ICSA-C65153.2025.00061 | I33: Software architecture relies heavily on modeling Object Management Group (OMG), an established industry techniques to describe, analyze, and verify system designs. The standards organization [1] OMG standards such as Action Unified Modeling Language (UML) is widely recognized as Language for Foundational UML [2], Precise Semantics of both a de facto and de jure standard for modeling various UMLStateMachines[3],SemanticsofaFoundationalSubset types of systems. While UML has formalized semantics that enhance consistency and precision, it is not inherently designed for Executable UML Models [4], and Precise Semantics of formodelchecking. Rebeca,anactor-basedmodelinglanguage, UML Composite Structures [5], have significantly advanced is designed to enable formal verification of concurrent reactive the formalization of UML semantics. While the OMG stan- systems. Previous efforts to bridge UML and Rebeca through dards for UML provide formalized semantics that enhance model transformations have required combining multiple UML consistency and precision, they are not inherently designed diagramsandadeepunderstandingofRebeca,limitingpractical applicability. for model checking. Instead, they can serve as a foundation In this paper, we explore the potential of leveraging large forintegratingwithtoolsormethodologiesthatenableformal language models, specifically GPT-4, to automate the trans- verification,bridgingthegapbetweenhigh-levelUMLmodels formation of UML state diagrams into Rebeca models. Using andrigorousvalidationtechniques.Thisgapcreatesanoppor- a few-shot learning approach, we investigated the feasibility tunity to explore how model-driven techniques can enhance of this translation process. Initial results revealed that UML state diagrams alone were insufficient for generating accurate the usability and precision of UML for formal architectural Rebeca models. To address this limitation, we augmented the verification. diagramswithmetadata,enablingGPT-4toproducemodelsthat | J33: Phindile Mposwa | K33: Include | L33: Sibongiseni Tsitsa | M33: Include | N33: Include | O33: Included: applies AI to model transformation; applies AI to model validation; applies AI to UML/software model artefacts; applies AI within model-driven engineering context
A34: 33 | B34: IEEE Xplore | C34: Phindile Mposwa, Sibongiseni Tsitsa | D34: Integrating Model Transformation in Agent-Oriented Software Engineering | E34: Cuiyun Hu, Xinjun Mao and Hong Ning | H34: https://doi.org/10.1109/WI-IAT.2009.127 | I34: To integrate model transformation technology in This paper proposes an approach to integrating model agent-oriented software engineering is helpful to improve the transformation technology in AOSE, in order to bridge the quality and efficiency of agent-based software development, gap between design and implementation. The idea is and therefore to make AOSE to be widely adopted by specified in an agent-oriented methodology ODAM [4], researchers and practitioners in software engineering which is based on organization metaphor and supporting community. This paper integrates model transformation complex adaptive MAS. The core of our work is to technology into an agent-oriented methodology ODAM that is investigate the model transformation algorithms. The rest based on organization metaphor and proposed for complex of this paper is structured as follows. Section 2 discusses adaptive systems. The model transformation consists of two the role of model transformations in ODAM. Section 3 steps: from platform-independent models to platform-specific introduces the model transformation algorithms in details. models, from platform-specific models to code. The transformation algorithms in each phase are designed. A Section 4 describes supported toolkits that implement the software tool that implements the algorithms has been algorithms. Conclusions are made in Section 5. developed as a part of agent-oriented supporting environment. II. MODELTRANSFORMATIONS IN ODAM | J34: Phindile Mposwa | K34: Include | L34: Sibongiseni Tsitsa | M34: Include | N34: Include | O34: Included: addresses software/systems modelling; transforms software models
A35: 34 | B35: IEEE Xplore | C35: Phindile Mposwa, Sibongiseni Tsitsa | D35: Java Code Generation Method Based on UML Class Diagrams and Large Language Model | E35: Diagrams and Large Language Model | F35: 2026 | H35: https://doi.org/10.1109/NNICE68970.2026.11465726 | I35: We propose an automatic Java code generation A feasible alternative is to extract model information from method that integrates UML class diagrams with large language the XML files exported by UML tools and convert it into usable models. First, we employ DOM4J parsing and FreeMarker code. Yet these XML files typically contain redundant, tool- templates to transform complex, tool-exported UML XML into a specific, or overly detailed metadata. This noise increases unified and concise XML representation. We then construct parsing complexity and reduces the usability of raw XML as umltocode, a task-specific dataset of aligned UML XML and Java model input. To address this problem, we employ the DOM4J pairs, and fine-tune CodeLlama to perform direct UML-to-Java parsing library together with FreeMarker templates to convert generation. Finally, we evaluate generation quality using a the exported XML into a concise and task-friendly format. We structural consistency-oriented scoring strategy. Experimental then fine-tune the large language model CodeLlama to directly results indicate that fine-tuning substantially improves both code generate Java code from these normalized XML files. structure fidelity and semantic accuracy, enabling fast and reliable Empirically, this approach can improve both generation synthesis of high-quality Java source code from class diagram accuracy and structural completeness, particularly for complex specifications. diagrams involving interfaces, static elements, and abstract | J35: Phindile Mposwa | K35: Include | L35: Sibongiseni Tsitsa | M35: Include | N35: Include | O35: Included: applies AI to reverse engineering/code-to-model extraction; applies AI to UML/software model artefacts
A36: 35 | B36: IEEE Xplore | C36: Phindile Mposwa, Sibongiseni Tsitsa | D36: LLM-Driven Approach to Automated Sustainability of IoT Systems | E36: Niš, Serbia dragana.krstic@elfak.ni.ac.rs | I36: Due to huge number and heterogeneity of devices achieving system’s goals when it comes to the perceived within Internet of Things (IoT)-based architectures, scalability Quality of Service (QoS) from perspective of end-users. On and maintainability of such systems rise many challenges when the other side, various events that occur across different it comes to long-term sustainability, especially regarding phases of IoT system’s lifecycle, especially failures, scalability and maintainability aspects. In this paper, we explore anomalies, topology changes and performance drops, state-of-art Large Language Model (LLM)-based techniques as potentially introduce bottlenecks when it comes to overall well as Agentic AI approaches in order to automate these usage experience and functionality offered [1]. In such cases, aspects and reduce the cognitive load and need for human usually a set of maintenance-related actions has to be taken in intervention. As intermediary step for system representation, we order to reduce their negative impact. However, considering leverage Model-Driven Engineering (MDE) approach in order the underlying complexity of the infrastructure, such to ensure verifiability. As outcome, two case studies relying on operation could require high cognitive load and significant GPT-4o model are presented. amount of time, which might further affect system’s usability and even lead to catastrophic outcomes in case of sensitive | J36: Phindile Mposwa | K36: Include | L36: Sibongiseni Tsitsa | M36: Include | N36: Include | O36: Included: applies AI within model-driven engineering context
A37: 36 | B37: IEEE Xplore | C37: Phindile Mposwa, Sibongiseni Tsitsa | D37: LLM-Driven MDA Pipeline for Generating UML Class Diagrams and Code | E37: Class Diagrams and Code | F37: 2025 | H37: https://doi.org/10.1109/ACCESS.2025.3615828 | I37: Thetransformationoftextualspecificationsintoformalsoftwaremodelsisamajorchallenge in software design automation. This study presents an integrated approach that combines the natural languageinterpretationcapabilitiesoftransformermodelswithexplicitconceptstructuringusingadomain specific language (DSL). This DSL, designed as a pivotal intermediate layer, ensures continuity between semanticextraction,UMLmodeling,andautomaticPythoncodegeneration.Byfollowingthemodel-driven architecture(MDA)paradigm,theproposedpipelinefollowsastructuredprogressionfromtexttomodelto codewhilemaintainingahighleveloftraceabilityandcontrollability.Theexperimentalevaluationconducted onadedicatedannotatedcorpusdemonstratestheaccuracyofthemodelsonUMLentitiesandhighlights theimportanceofDSLforvalidation,editing,andexploitationofresults.Thisapproachpavesthewayfor thedevelopmentofintelligentmodelingtoolsandstructuringofautomatedtransformationchains. INDEXTERMS Classdiagram,UML,MDA,DSL,LLMs,NLP,IOBannotation,sourcecode. | J37: Phindile Mposwa | K37: Include | L37: Sibongiseni Tsitsa | M37: Include | N37: Include | O37: Included: applies AI to UML/software model artefacts; applies AI to domain-specific language/model engineering; applies AI within model-driven engineering context
A38: 37 | B38: IEEE Xplore | C38: Phindile Mposwa, Sibongiseni Tsitsa | D38: Large Language Models Fine Tuning Code Generation | E38: Large Language Models, Fine Tuning, Code | F38: 2024 | I38: Automated software synthesis, text-to-code paper will discuss the problem of code generation and its (code-generation), can be an important aid to software historically most important approaches. Some of the solutions developers. Developments in this area have existed practically using language models are underlined and have received since the advent of computing. The new artificial intelligence considerable attention. From the programming languages, we methods, deep learning (DL), and one type of them, large highlight SQL, the language for managing relational language models (LLMs) emerged in the last decade, represent databases, since in the final part of the paper we present an a new opportunity for creating this type of application. We example of the development of a sql-generating system. survey the transformer technology that underlies the operation of language models. Present paper briefly reviews the topic of II. TRANSFORMERS AND LARGE LANGUAGE MODELS software synthesis and code generation, briefly mentioning the main trends. The document concludes with an empirical study A. Machine Learning demonstrating the described results, where the T5 language In the new millennium, one of the key drivers of IT model is fine-tuned to generate SQL queries. A fine-tuning set development is the increasing amount of information that can of a few thousand examples train T5 to produce quality queries. be captured by ubiquitous computing devices (internet, IoT, The economic principle of diminishing returns (Gossen I) mobile applications, etc.). The need to deal with data at applies, and it is not worth using too large a fine-tuning set. In unprecedented volumes and speeds has led R&D and fact, it is the attractiveness of fine-tuning. businesspeople to create and apply new data processing technologies. Big Data is the umbrella term for these new | J38: Phindile Mposwa | K38: Include | L38: Sibongiseni Tsitsa | M38: Include | N38: Include | O38: Included: applies identifiable AI technique; supports model-to-code synthesis
A39: 38 | B39: IEEE Xplore | C39: Phindile Mposwa, Sibongiseni Tsitsa | D39: Learning to Transform Evaluating LLMs on Model Transformation by Example | E39: Duy Dao, Alessio Bucaioni, Antonio Cicchetti | F39: 2025 | H39: https://doi.org/10.1109/MODELS-C68889.2025.00081 | I39: Large language models have shown promising po- persist,particularlywhenaddressingless-exploredtransforma- tentialinreducingtheaccidentalcomplexityofmodel-drivenen- tionscenariosandensuringthecorrectnessandgeneralizability gineering,particularlyinautomatingmodeltransformationtasks. of the generated transformations [1]. However,existingresearchhasshownthatlargelanguagemodels Inthiscontext,ourresearchaimstoaddresstheselimitations oftenstrugglewithcorrectness,generalizability,andperformance by investigating the feasibility and effectiveness of leverag- incomplextransformationscenarios.Thispaperinvestigatesthe feasibilityofapplyinglargelanguagemodelswithintheparadigm ing LLMs within the paradigm of Model Transformation by of model transformation by example, an intuitive technique Example (MTBE). In MDE, MTBE is an intuitive approach thatderivestransformationlogicfromprototypicalsource-target that simplifies transformation tasks by allowing practitioners model pairs, thereby reducing cognitive load and bypassing the to derive transformation rules from a prototypical set of need for formal transformation specifications. interrelated source and target models, specified in a purely We empirically benchmark five LLMs, ChatGPT-4.5, DeepSeek V3, DeepHermes 3 LLaMA 3 8B, QwQ 32B, and declarative manner [5]. Our central intuition is that, when OlympicCoder 32B, across three transformation scenarios of applied in the context of LLMs, MTBE can facilitate the increasing complexity: RDBMS-to-UML, UML-to-Java, and definition of transformations by feeding concrete example SysML-to-AAS. Each scenario is evaluated under three con- pairs directly to the models. By alleviating cognitive load, figurations, varying the number of example pairs provided. In thisparadigmhasthepotentialtoenhancethecorrectnessand eachconfiguration,theLLMsaretaskedwithdirectlygenerating target models given source models, example pairs, and initial reliability of transformations generated by LLMs. mappingrules.Mode | J39: Phindile Mposwa | K39: Include | L39: Sibongiseni Tsitsa | M39: Include | N39: Include | O39: Included: applies AI to model transformation; applies AI to UML/software model artefacts; applies AI to SysML model engineering; applies AI within model-driven engineering context
A40: 39 | B40: IEEE Xplore | C40: Phindile Mposwa, Sibongiseni Tsitsa | D40: Leveraging Large Language Models for Event Storming in Domain-Driven Design A Controlled Experiment | E40: Lingli Cao, He Zhang, Shanshan Li,, Chenxing Zhong, Danyang Li, Ying Fan, Yi Zhang, Uwe Zdun | F40: 2026 | G40: 2026 IEEE 23rd International Conference on Software Architecture (ICSA) | H40: https://doi.org/10.1109/ICSA66085.2026.00039 | I40: EventStorming(ES),asthekeymodelingtechnique applicationsistobringtogetherdevelopersanddomainexperts within the Domain-Driven Design (DDD) methodology, provides toco-constructasharedunderstandingofthebusinessdomain, teams with a fast, visual approach that helps them deeply typically resulting in a comprehensive business flow model understand and explore complex business domains, thereby and helping practitioners quickly identify bounded contexts enablingmoreeffectivesoftwaresystemdesignanddevelopment. ComparedtotraditionalUMLmodelingtechniques,ESempha- and aggregates [3]. sizes collaborative exploration and rapid iteration. However, its However,theeffectivenessofESishighlydependentonthe effectiveness is highly dependent on the facilitation of domain facilitationbydomainexperts[4].Furthermore,ESmeetings, experts. Moreover, since ES sessions are typically conducted whicharetypicallyconductedusingphysicalordigitalwhite- using physical or digital whiteboards, they often incur high boards, often incur significant coordination costs, particularly coordinationcosts,especiallyindistributedorasynchronousen- vironments.WiththerecentadvancesinLargeLanguageModels indistributedorasynchronousenvironments.Recentadvances (LLMs), there is growing interest in leveraging their reasoning inLargeLanguageModels(LLMs)offerapromisingsolution and text generation capabilities to support software modeling to these challenges. LLMs excel at natural language process- tasks.Thispaperpresentsacontrolledexperimenttoinvestigate ing, enabling them to interpret requirements formulated in theeffectivenessofLLMsinfacilitatingESmodeling.Atotalof naturallanguageandassistindefiningimportantelementssuch 240postgraduateparticipants(60teams)wereassignedtothree conditions:manualES,LLM-assistedESwithbasicprompts,and as domain events. This capability can reduce the reliance on LLM-assistedESwithoptimizedprompts.Thegeneratedmodels domainexpertsandfacilitatetheefficientgenerationofinitial werequantitativelyevaluat | J40: Phindile Mposwa | K40: Include | L40: Sibongiseni Tsitsa | M40: Include | N40: Include | O40: Included: applies AI to UML/software model artefacts; applies AI within model-driven engineering context
A41: 40 | B41: IEEE Xplore | C41: Phindile Mposwa, Sibongiseni Tsitsa | D41: Metamodel Matching Experiments and Comparison | E41: Denivaldo Lopes Slimane Hammoudi Jose´ de Souza and Alan Bontempo | I41: Recently, Model Driven Engineering (MDE) has SAMT4MDE)withothertoolsandapproachesinthedatabase beenproposedforsupportingthedevelopment,maintenanceand domain. evolutionofsoftwaresystems.ModelDrivenArchitecture(MDA), This paper is organized in the following way. In section II, SoftwareFactoriesandEclipseModelingFramework(EMF)are wediscussschemamatchinginthedatabasedomain.Insection representative MDE approaches. These MDE approaches have some concepts and techniques in common such as modeling, III, we present our approach to take into account metamodel metamodels and model transformation. However, other concepts matching. In section IV, we illustrate the application of our andtechniquesshouldbeenvisagedsuchasmetamodelmatching. approach and tool for mapping UML to C#. In section V, In this paper, we discuss some issues and provide some insights we present a comparison between our approach and other into metamodel matching. For this purpose, we use UML and approaches,providingtheirbenefitsandlimitations.Insection the C# platform to illustrate our approach and to evaluate our MappingToolforMDE(MT4MDE)andSemi-AutomaticMatch- VI,weconcludethispaper,presentingthefuturedirectionsof ingToolforMDE(SAMT4MDE).Afterwards,comparisonswith our research. other tools are presented. II. APPROACHESFORSCHEMAMATCHING | J41: Phindile Mposwa | K41: Include | L41: Sibongiseni Tsitsa | M41: Include | N41: Include | O41: Included: addresses software/systems modelling; transforms software models
A42: 41 | B42: IEEE Xplore | C42: Phindile Mposwa, Sibongiseni Tsitsa | D42: Metamodeling and model transformations in modeling and simulation | E42: Systems Engineering Group, Faculty of Technology, Policy and Management | F42: 2011 | G42: Proceedings of the 2011 Winter Simulation Conference | I42: Metamodeling and model transformations are the key concepts in Model Driven Development (MDD) approaches as they provide a mechanism for automated development of well structured and maintainable systems. However, neither defining a metamodel nor developing a model transformation is an easy task. In this paper, we provide an overview of metamodeling and model transformations in MDD and discuss abouttheuseofaMDDapproachinModelingandSimulation(M&S).Inordertosupportthedevelopment of successful model transformations, we define the criteria for the evaluation of model transformations. 1 INTRODUCTION In Model Driven Development (MDD), models are the primary artifacts of the development process and they represent the system on different levels of abstraction. A model is an abstract representation of a system defined in a modeling language, where a modeling language is a means of expressing systems in a formal and precise way by using diagrams, rules, symbols, signs, letters, numerals, etc.. Me | J42: Phindile Mposwa | K42: Include | L42: Sibongiseni Tsitsa | M42: Include | N42: Include | O42: Included: addresses software/systems modelling; transforms software models
A43: 42 | B43: IEEE Xplore | C43: Phindile Mposwa, Sibongiseni Tsitsa | D43: Mitigating Hallucinations in SysML v2 Generation Using LLMs and a Tri-Layered Knowledge Graph Reasoning Framework | E43: Qualis, Richard A. | F43: 2025 | H43: https://doi.org/10.1109/MODELS-C68889.2025.00054 | I43: Thispaperpresentsastructuredreasoningpipeline usability barriers hinder adoption [18]. Recent progress in thatintegratesLargeLanguageModels(LLMs)withatri-layered large language models (LLMs) such as GPT offers new knowledge graph (KG) framework to automate the generation potential for automating formal modeling. However, these of SysML v2 modeling artifacts from structured requirements. models are prone to hallucinations, outputs that appear valid TheapproachaddressesthepersistentchallengeofLLMhalluci- nations in digital and model-based systems engineering (MBSE) butaresemanticallyincorrectorcontextuallyunfounded[19], by grounding generative outputs in curated knowledge sources. [32]. Hallucination is especially problematic for engineering TwocoreKGsareconstructedusingacustomPython-basedRea- artifacts, where traceability and correctness are essential. soning Engine: one encodes reusable SysML patterns annotated While hallucinations in natural language and code gen- acrossninediagramtypes,andtheothercapturesdomain-specific eration are well-documented, their implications for formal system models (e.g., aerospace, automotive). A third, system- specific KG is automatically synthesized by parsing capability- modeling (e.g., SysML v2) remain underexplored. Our study linkedrequirementsandaligningthemwiththefoundationalKGs addresses this gap by introducing a structured reasoning and structured prompt templates. These KGs enable context- pipeline that combines LLMs with a tri-layered knowledge aware,hierarchicalsystemmodelgenerationandinformadual- graph (KG) architecture to reduce hallucinations and improve parameter prompting strategy: one set is auto injected post-KG semantic fidelity. constructiontopreservedomainintegrity,andanotherisderived through our Reasoning Engine over system data prior to LLM Two research questions drive this work: invocation. The resulting prompts are validated and refined to RQ-1: How does a tri-layered KG architecture-integrating produce accurat | J43: Phindile Mposwa | K43: Include | L43: Sibongiseni Tsitsa | M43: Include | N43: Include | O43: Included: applies AI to SysML model engineering
A44: 43 | B44: IEEE Xplore | C44: Phindile Mposwa, Sibongiseni Tsitsa | D44: Model-Driven Development Where Does the Code Come From | E44: Edmond, OK, USA Highland Heights, KY, USA Richardson, TX, USA | F44: 2011 | G44: IEEE International Conference on Semantic Computing | H44: https://doi.org/10.1109/ICSC.2011.76 | I44: Model-driven development (MDD) drastically changes consistent with the software development. The design the traditional view of software modeling, which no longer serves documents gradually lose their values as the development merely as documentation that will be put aside at a certain point proceeds. This tendency also highlights other serious problems, during the development. Instead, MDD has made models an namely, maintenance and documentation problems. As the integral part of the development process. As a result, software design documents are always out of date, developers who did designers and developers can focus on high-level problem solving not participate in the initial development have a hard time to instead of low-level implementation details. However, the current understand the system through the available documents. research focus is on model transformations and overlooks the Therefore, it is also difficult for them to maintain the system importance of code generation, which includes the generation of well. infrastructural code (the static aspects of the system) and business code (the behavioral aspects of the system). In this MDD overcomes the aforementioned problem through two paper, we first analyze the root cause about why existing MDD key themes, namely, raising the level of abstraction of approaches are only good at generating the infrastructural code. specifications and raising the level of automation [14]. For Then, we propose a comprehensive approach that considers example, model-driven architecture (MDA) [17], the industry functional, dynamic, and object modeling. This approach is able standard for MDD defined by OMG, classifies models as to generate both infrastructural and business code. Finally, we platform independent models (PIM), platform specific models present a case study to evaluate the proposed approach. Through (PSM), and code. PIMs are used to construct high-level this case study, we identify some insights on automated code specif | J44: Phindile Mposwa | K44: Include | L44: Sibongiseni Tsitsa | M44: Include | N44: Include | O44: Included: addresses software/systems modelling; transforms software models; supports model-to-code synthesis
A45: 44 | B45: IEEE Xplore | C45: Phindile Mposwa, Sibongiseni Tsitsa | D45: Model-Driven Development of Web Application Backend Using Node.js Framework | E45: Bangkok, Thailand Bangkok, Thailand | F45: 2025 | I45: Model-Driven Development (MDD) has emerged as The Model-Driven Architecture (MDA) [4] is the OMG’s a promising software engineering paradigm that uses models as vision of MDD which is built on OMG standards including the the primary artifacts to support software development including Unified Modeling Language (UML) [5], UML Profile, and web application development. This paper presents a novel XML Metadata Interchange (XMI). MDA employs the application of the MDD principles for Node.JS backend transformation chain between models of different levels of development, focusing on both forward and reverse engineering abstraction: Computation-Independent Model (CIM) which is a processes. A UML Profile for Node.js, supporting both SQL and high-level model that describes the business context and NoSQL databases, is introduced for building design models of web requirements, Platform-Independent Model (PIM) which applications. Transformation engines are provided for model-to- describes the structure and behavior of the system independently code (M2C) and code-to-model (C2M) transformation. The of any technical platform, Platform-Specific Model (PSM) proposed approach was evaluated through three case studies. The which is a model that adds technical details to the PIM to map it forward engineering results demonstrated high model-to-code to a specific platform or technology stack, and Code Model transformation rates especially for Model (86.18-94.53%) and which is represented in a target programming language. The Route (70.73-90.52%), with consistent performance across SQL MDA concept of model-to-text transformation enables code (MySQL) and NoSQL (MongoDB) implementations. The reverse engineering results showed 100% correctness in code-to-model generation from PSMs, which can significantly reduce transformation for different implementations of backend code. development time despite requiring software engineers to This approach significantly reduces development time for code comp | J45: Phindile Mposwa | K45: Include | L45: Sibongiseni Tsitsa | M45: Include | N45: Include | O45: Included: addresses software/systems modelling; generates software models; transforms software models; reverse engineers models from code
A46: 45 | B46: IEEE Xplore | C46: Phindile Mposwa, Sibongiseni Tsitsa | D46: Model-Driven Fault Injection in Java Source Code | E46: Campinas, SP, Brazil Campinas, SP, Brazil Firenze, Italy | F46: 2020 | G46: 2020 IEEE 31st International Symposium on Software Reliability Engineering (ISSRE) | H46: https://doi.org/10.1109/ISSRE5003.2020.00046 | I46: The injection of software faults in source code Wheninjectingcodechanges,theartificialfaultsintroduced requiresaccurateknowledgeoftheprogramminglanguage,both inthesoftwareshouldberealistic,i.e.,similartotherealsoft- to craft faults and to identify injection locations. As such, ware bugs, and the criteria for the injection should depend on fault injection and code mutation tools are typically tailored the target system and on the purpose of the testing campaign for a specific language and have limited extensibility. In this [25]. Therefore, several authors have analyzed which are the paper we present a model-driven approach to craft and inject software faults in source code. While its concrete application is mostcommonfaultsintroducedbydevelopers,andthesupport presented for Java, the workflow we propose does not depend of automated tools that inject realistic faults has improved in on a specific programming language. Following Model-Driven recent years. While it would be useful to reuse existing tools Engineering principles, the faults and the criteria to select to create custom faults, or to alter some of the implemented injection locations are described using structured, machine- ones, this can be a hard task in practice [3]. In fact, to create readable specifications based on a domain-specific language. Then, automated transformations craft artifacts based on OCL new injectors for code-change faults, a strong knowledge of and Java, which represent the faults to be injected and are able the language and of its low-level artifacts is needed (e.g., the to select the candidate injection locations. Finally, artifacts are abstract syntax tree or the compiler). executedagainstthetargetsourcecode,performingtheinjection In this paper we present and exercise a model-driven ap- inthedesiredlocations.Wedeviseasupportingtoolandexercise proach to craft and inject software faults in source code. Fol- theapproachinjecting13differentkindsofsoftwarefaultsinthe Java source code of s | J46: Phindile Mposwa | K46: Include | L46: Sibongiseni Tsitsa | M46: Include | N46: Include | O46: Included: addresses software/systems modelling
A47: 46 | B47: IEEE Xplore | C47: Phindile Mposwa, Sibongiseni Tsitsa | D47: Model-Driven Prompt Engineering | E47: Universitat Oberta de Catalunya (UOC) Luxembourg Institute of Science and Technology (LIST) | F47: 2023 | H47: https://doi.org/10.13039/501100011033 | I47: Generative artificial intelligence (AI) systems are the input format improves usability and is flexible enough to capableofsynthesizingcomplexcontentsuchastext,sourcecode support numerous application scenarios. or images according to the instructions described in a natural Nevertheless,ashortcomingofgenerativeAIsystemsisthat languageprompt.Thequalityoftheoutputdependsoncrafting thequalityoftheoutputdependsonthestructureoftheinput a suitable prompt. This has given rise to prompt engineering, the process of designing natural language prompts to best take prompt[6]–[12].Asaresult,theAIcommunityhasproposed advantage of the capabilities of generative AI systems. a set of strategies, best practices, guidelines and supporting Through experimentation, the creative and research commu- tools for creating good prompts. The process that involves nities have created guidelines and strategies for creating good crafting, evaluating and fine-tuning prompts is called prompt prompts. However, even for the same task, these best practices engineering. vary depending on the particular system receiving the prompt. Moreover,somesystemsofferadditionalfeaturesusingacustom Achallengeofpromptengineeringisthefactthatitisessen- platform-specific syntax, e.g., assigning a degree of relevance to tiallyaplatform-specificprocess.Promptsthatperformwellin specific concepts within the prompt. a particular system may under-perform in other systems [13], In this paper, we propose applying model-driven engineering [14], or even in different versions of the same system. For to support the prompt engineering process. Using a domain- instance, the release of version 2 of the Stable Diffusion specificlanguage(DSL),wedefineplatform-independentprompts that can later be adapted to provide good quality outputs in a open-sourcetext-to-imagesystemcausedusercomplaintsthat target AI system. The DSL also facilitates managing prompts prompts previously considered as “good” were producing by providing mechanisms for pr | J47: Phindile Mposwa | K47: Include | L47: Sibongiseni Tsitsa | M47: Include | N47: Include | O47: Included: applies AI to domain-specific language/model engineering; applies AI within model-driven engineering context
A48: 47 | B48: IEEE Xplore | C48: Phindile Mposwa, Sibongiseni Tsitsa | D48: Model-Driven Quantum Code Generation Using Large Language Models and Retrieval-Augmented Generation | E48: Large Language Models and Retrieval-Augmented | F48: 2025 | H48: https://doi.org/10.1109/MODELS67397.2025.00031 | I48: This paper introduces a novel research direction Additionally, today’s software developers typically lack tech- formodel-to-text/codetransformationsbyleveragingLargeLan- nical skills in these platforms, for example, regarding their guage Models (LLMs) that can be enhanced with Retrieval- models of computation, hardware architecture, Software De- AugmentedGeneration(RAG)pipelines.Thefocusisonquantum velopmentKits(SDKs),libraries,constraints,andoptimization and hybrid quantum-classical software systems, where model- driven approaches can help reduce the costs and mitigate the techniques. For instance, Gemeinhardt et al. [5] proposed risks associated with the heterogeneous platform landscape and a novel approach to enable model-driven composition-based lack of developers’ skills. We validate one of the proposed quantum circuit design and implementation. Also, Jime´nez- ideas regarding generating code out of UML model instances Navajas et al. [6] deployed the Epsilon Generation Language of software systems. This Python code uses a well-established to generate Python code that works with Qiskit for quantum library, called Qiskit, to execute on gate-based or circuit-based quantum computers. The RAG pipeline that we deploy incor- andhybridquantum-classicalapplications.Weusedthemodel porates sample Qiskit code from public GitHub repositories. instances provided by them in our experimental study. Experimental results show that well-engineered prompts can The key contribution of this paper is proposing a new re- improve CodeBLEU scores by up to a factor of four, yielding searchdirectiondefinedbydeployingLLMs,suchasthestate- more accurate and consistent quantum code. However, the of-the-art Generative Pre-trained Transformer (GPT) models proposedresearchdirectioncangobeyondthisthroughfurther investigationinthefuturebyconductingexperimentstoaddress provided by OpenAI (e.g., GPT-4o), as a text generation our other research questions and ideas proposed here, such engine (e.g., to | J48: Phindile Mposwa | K48: Include | L48: Sibongiseni Tsitsa | M48: Include | N48: Include | O48: Included: applies AI to UML/software model artefacts; applies AI within model-driven engineering context
A49: 48 | B49: IEEE Xplore | C49: Phindile Mposwa, Sibongiseni Tsitsa | D49: Model-driven systems engineering for netcentric system of systems with DEVS unified process | E49: tate integration with architecture solutions like Service Oriented Architecture (SOA), Event Driven Archi- | F49: 2013 | G49: Proceedings of the 2013 Winter Simulation Conference | I49: Model-Based Systems Engineering (MBSE) employs model-based technologies and established systems engineering practices. Model-Driven Engineering (MDE) provides various concepts to automate model based practices using metamodeling. We describe the DEVS Unified Process (DUNIP) that aims to bring together MBSE and MDE as Model-driven Systems Engineering (MDSE) and apply it in a netcentric en- vironment. We historically look at various model-based and model-driven flavors and suggest MDSE/DUNIP as one of the derived methodologies. We describe essential elements in DUNIP that facili- tate integration with architecture solutions like Service Oriented Architecture (SOA), Event Driven Archi- tectures (EDA), Systems Entity Structures (SES) ontology, and frameworks like Department of Defense Architecture Framework (DoDAF 2.0). We discuss systems requirement specifications, verification and validation, metamodeling, Domain Specific Languages (DSLs), and model transformation technologies as applica | J49: Phindile Mposwa | K49: Include | L49: Sibongiseni Tsitsa | M49: Include | N49: Include | O49: Included: addresses software/systems modelling; transforms software models
A50: 49 | B50: IEEE Xplore | C50: Phindile Mposwa, Sibongiseni Tsitsa | D50: Model Driven and Modular Software Architecture for Scalable Development | E50: Ichalkaranji, India. April -, | F50: 2026 | I50: The growing sophistication of contemporary fraternity has given more concentration on architectural software systems dictates architectural designs that facilitate paradigms that facilitate modularity, automation, and scalable scalability, maintainability and speedy development. development practices [1]. Conventional monolithic development models find it hard to Model-Driven Engineering (MDE) is one of the most meet dynamic requirements, huge development teams and continuous integration practices. This paper will recommend a powerful techniques in this situation that focus on the usage Model-Driven and Modular Software Architecture (MDMSA) of abstract models as the key products during the software model to overcome these issues whereby the model-driven development lifecycle. Rather than having to use manual engineering methodology will be combined with the modular code, model-driven development allows the developers to architecture to facilitate scalable software development. The build high-level system models that can be automatically given approach focuses on the tradition of using high-level compiled into executable software elements. This will system models to automatically create platform-specific enhance productivity in the development and consistency of components and has no conflicts of concern because of the clear the system design and implementation. Past researchers have separation of concerns that occurs during modular demonstrated that model-driven methods have the capability decomposition. The modules capture certain functionality and to simplify the development process and improve are interrelated by well-known interfaces which enhance their maintenance of the system by creating automated code and reuse, maintenance, and the ability to extend the system. In system validation processes [2], [3]. addition, the architecture facilitates automated code generation, component orchestration and continuous integration pipelines, Simultaneously, modular softwa | J50: Phindile Mposwa | K50: Include | L50: Sibongiseni Tsitsa | M50: Include | N50: Include | O50: Included: addresses software/systems modelling; supports model-to-code synthesis
A51: 50 | B51: IEEE Xplore | C51: Phindile Mposwa, Sibongiseni Tsitsa | D51: Modeling and Digital Twins Insights and Strategies for Software Engineers | E51: Modeling and Digital | H51: https://doi.org/10.1109/MS.2024.3510892 | J51: Phindile Mposwa | K51: Exclude | L51: Sibongiseni Tsitsa | M51: Exclude | N51: Exclude | O51: Excluded: Does not apply an identifiable AI technique to a model-engineering task; lacks connection to software modelling (UML, BPMN, metamodel, DSL) or AI-driven automation
A52: 51 | B52: IEEE Xplore | C52: Phindile Mposwa, Sibongiseni Tsitsa | D52: Mutation-based Model Synthesis in Model Driven Engineering | I52: a model transformation. Model transformations havemanyusessuchastospecifyformalismtrans- With the increasing use of models for software formations, to define operational/denotational se- development and the emergence of model-driven mantics,toobtaintheconcretesyntaxofthemodel, engineering, it has become important to build ac- and for evolving the model for various purposes curate and precise models that present certain [4]. These applications of model transformations characteristics. Model transformation testing is a make it a very important part of the MDE frame- domain that requires generating a large number worksinceinpracticeseveralmodelsundergosuch of models that satisfy coverage properties (cover transformations. Thereforegivenamodeltransfor- the code of the transformation or the structure of mation we ask, is the model transformation error- the metamodel). However, manually building a free,isitefficient,anddoesitcoveralltheimpor- set of models to test a transformation is a tedio | J52: Phindile Mposwa | K52: Include | L52: Sibongiseni Tsitsa | M52: Include | N52: Include | O52: Included: applies AI to model transformation; addresses metamodel engineering with AI; applies AI within model-driven engineering context
A53: 52 | B53: IEEE Xplore | C53: Phindile Mposwa, Sibongiseni Tsitsa | D53: No Resource No Benchmarks No Problem Evaluating and Improving LLMs for Code Generation in No-Resource Languages | E53: No Resource, No Benchmarks, No Problem? | F53: 2026 | G53: IEEE Transactions on Software Engineering. This is the author's version which has not been fully edi | H53: https://doi.org/10.1109/TSE.2026.3703553 | I53: Large Language Models (LLMs) have significantly which are characterized by relatively limited training data. advanced the automation of software engineering tasks. One Whileperformanceontheselanguagesisgenerallylowerthan prominent example is code generation, where an LLM produces on high-resource ones, large-scale LLMs can still generalize code in a specified programming language based on a natural reasonably well [6]. language description. Most research in this area has focused on high-resource languages, such as Python or Java, which benefit In contrast, little attention has been paid to no-resource fromabundanttrainingdatainrepositoryplatformslikeGitHub. programming languages, i.e., languages that fall outside the A smaller body of work has explored low-resource languages pre-training distribution of LLMs. In particular, we focus on (e.g., Lua, Racket), which are underrepresented in training no-resource general-purpose languages, which share syntactic corpora. In contrast, no-resource languages for which LLMs and semantic characteristics with mainstream programming have seen virtually no training data remain largely unstudied. These languages often emerge in industry, where organizations languages but lack training data. As a consequence, commer- developproprietaryordomain-specificlanguagesunsupportedby cial tools such as Copilot [7] or ChatGPT [8] do not support commercial tools like GitHub Copilot. This results in the need theselanguages,leavingorganizationsinterestedinAI-assisted forcompaniestodeploytheirownin-housecoderecommenders. programming with the challenge of developing custom, in- To investigate possible solutions in this context, we build and house solutions. Crafting effective and economically sustain- release three code generation benchmarks for no-resource lan- guages,basedontworecentlyproposedprogramminglanguages able solutions is, however, far from trivial. for which very little training data is available. Using these We make a number of contribu | J53: Phindile Mposwa | K53: Include | L53: Sibongiseni Tsitsa | M53: Include | N53: Include | O53: Included: applies identifiable AI technique; supports model-to-code synthesis
A54: 53 | B54: IEEE Xplore | C54: Phindile Mposwa, Sibongiseni Tsitsa | D54: Ontology Driven Development of Rule-Based Expert Systems | E54: Nikita O. Dorodnykh, Aleksandr Y. Yurin Alexander B. Stolbov | F54: 2018 | I54: An ontology-driven development process of rule- the program codes, in some cases allow one to obtain only based expert systems and knowledge bases is described. The graphic artifacts (images) of KB structures. With the exception process is based on a redefined approach, namely, a model- of Protégé, which allows one to generate a limited set of driven development (MDD). The main feature of the proposed knowledge base elements, in particular, for CLIPS/COOL or process is the use of ontology as a computation-independent JESS. model (CIM). At the same time, ontology is created by analyzing the conceptual models of a subject domain, in particular, UML Thus, the development of specialized software is relevant class diagrams presented in XML-based formats. The Rule and this trend is confirmed by some examples [9, 10]. In Visual Modeling Language (RVML) is used as the extension of a particular: a tool for the development of web-based expert UML for the development of a platform-independent and systems is described in [11]. The proposed tool utilizes the platform-specific models, and also the C language integrated Semantic Web technology which permits the knowledge production system (CLIPS) is used as the target platform. The engineer and domain expert to define the knowledge without formalized descriptions of the approach stages and model having to know anything about programming languages and transformations are considered. The approach proposed allows artificial intelligence. one: to eliminate programming errors through the automatic code generation; to reduce a time of identification, In [7] Shue L., Chen, C. and Shiue W. used the ontology to conceptualization, and formalization stages due to the use of model the domain knowledge, and decision rules are used to ontologies. The Knowledge Base Development System (KBDS) represent operational knowledge. The described system and the Personal Knowledge Base Designer (PKBD) implement integrates Protégé, as a domain KB, and JESS | J54: Phindile Mposwa | K54: Include | L54: Sibongiseni Tsitsa | M54: Include | N54: Include | O54: Included: addresses software/systems modelling; supports model-to-code synthesis
A55: 54 | B55: IEEE Xplore | C55: Phindile Mposwa, Sibongiseni Tsitsa | D55: PHM4HHP Domain Specific Language | E55: alex.rojco@mail.mcgill.ca American Institute of Aeronautics and Astronautics (AIAA) | F55: 2024 | I55: A broad spectrum of space application domains are 1. INTRODUCTION increasingly making use of heterogeneous and large volumes of data with varying degrees of human in the loop. Applications include critical areas such as space habitat management, This paper introduces a conceptual reference framework – healthcare delivery, and emergency management while the Prognostics and Health Management (PHM) for Human International Space Station Environmental Control and Life Health and Performance (HHP) – to support the data-centric Support System (ECLSS) as well as PHM for Human Health and model-driven approach for HHP. The paper also explores and Performance (PHM4HHP) serve as examples of the a PHM for HHP (PHM4HHP) metamodel in terms of the applications. This paper suggests a discussion on paradigm shift from telemedicine to HHP autonomy coupled implementation of the Model Driven Engineering paradigm with 24x7 real-time self-tracking with predictive diagnostics (a.k.a. Model Based Systems Engineering approach) for PHM providing early and actionable real-time warnings on focusing on HHP on crewed space exploration missions and impending health issue that otherwise would have gone introduces a conceptual model and framework – the PHM4HHP Domain Specific Language – to support a data-centric and undetected. model-driven approach and develop requirements for integration of heterogeneous models and their respective data The first part (sections 2-5) of the paper is focusing on for the entire life-cycle of the Health Support System (HeSS) PHM4HHP concepts that make the PHM4HHP domain being designed to validate on the International Space Station different from conventional healthcare delivery while the (ISS). While the discussion starts with focusing on PHM4HHP second part (section 6-7) is a discussion on PHM4HHP concepts that make the PHM4HHP domain different from Domain Specific Language (PHM4HHP DSL) to build. conventional healthcare delivery and is to elaborate the PHM foundatio | J55: Phindile Mposwa | K55: Include | L55: Sibongiseni Tsitsa | M55: Include | N55: Include | O55: Included: addresses software/systems modelling
A56: 55 | B56: IEEE Xplore | C56: Phindile Mposwa, Sibongiseni Tsitsa | D56: Preface to MDE Intelligence 2019 1st Workshop on Artificial Intelligence and Model-Driven Engineering | E56: Intelligence and Model-Driven Engineering | F56: 2019 | H56: https://doi.org/10.1109/MODELS-C.2019.00028 | I56: Model-driven engineering (MDE) and Artificial In- MDE, which will push the limits of “classic” MDE and telligence(AI)aretwoseparatefieldsincomputerscience,which provide the right techniques to develop the next generation can clearly benefit from cross-fertilization and collaboration. of highly complex model-based system and software systems Thereareatleasttwowaysinwhichsuchintegrations—whichwe engineers will have to design tomorrow. callMDEIntelligence—canmanifest:(1)MDEcanbenefitfrom integrating AI concepts and ideas to increasing the power and The MDE Intelligence workshop [1] brought the oppor- flexibilityofmodel-driventechniquesbymeansoftheapplication tunity to discuss how to choose, evaluate, and adapt AI ofAIalgorithms.(2)Conversely,AIcanbenefitfromintegrating techniques to Model-Driven Engineering as a way to improve concepts and ideas from MDE—for example, using domain- current system and software modeling and generation pro- specific languages and model transformations allows domain cesses while, at the same time, increasing the benefits and experts to directly express and manipulate their problems while providing an auditable computation pipeline. reducing the costs of adopting MDE and AI. Specially, we To discuss and further stimulate such integrations, the 1st do believe that AI artifacts will empower the MDE tools and edition of the Workshop on Artificial Intelligence and Model- boost further the advantages, and consequently adoption, of driven Engineering (MDE Intelligence) was held on September MDE at industry level. While AI is software (and complex 16, 2019 in Munich, Germany, as part of the satellite events of software,infact),wealsobelievethatsuchAI-poweredMDE the IEEE/ACM 22th International Conference on Model-Driven approachwillalsobenefitthedesignofAIartifactsthemselves Engineering Languages and Systems (MODELS 2019). IndexTerms—MDE,ArtificialIntelligence,MDEIntelligence andspeciallytofacethechallengeofdesigning“trustable”AI software. Therefore | J56: Phindile Mposwa | K56: Include | L56: Sibongiseni Tsitsa | M56: Include | N56: Include | O56: Included: applies AI to model transformation; applies AI within model-driven engineering context
A57: 56 | B57: IEEE Xplore | C57: Phindile Mposwa, Sibongiseni Tsitsa | D57: Program translation using model-driven engineering | E57: Dept.ofInformatics,King’sCollegeLondon | F57: 2022 | G57: 2022 IEEE/ACM 44th International Conference on Software Engineering: Companion Proceedings (ICSE-Companion) | H57: https://doi.org/10.1145/3510454.3528639 | I57: 2 MDEPROCESSFORLANGUAGE Theportingortranslationofsoftwareapplicationsfromonepro- TRANSLATION gramminglanguagetoanotherisacommonrequirementofor- The translation process consists of successive steps of parsing, ganisationsthatutilisesoftware,andtheincreasingnumberand abstractionandforwardengineering(Figure1). diversityofprogramminglanguagesmakesthiscapabilityasrele- vanttodayasinpreviousdecades. Severalapproacheshavebeenusedtoaddressthischallenge, includingmachinelearningandthemanualdefinitionofexplicit translationrules.Wedefineanovelapproachusingmodel-driven engineering(MDE)techniques:reverse-engineeringsourcepro- gramsintospecificationsintheUMLandOCLformalisms,and thenforward-engineeringthespecificationstotherequiredtarget language.Thisapproachhastheadditionaladvantageofextracting specificationsofsoftwarefromcode.Weprovideanevaluation basedonacomprehensivedatasetofexamples,includingindustrial cases,andcompareourresultstothoseofotherapproachesand tools. ACMReferenceFormat: K.Lano.2022.P | J57: Phindile Mposwa | K57: Include | L57: Sibongiseni Tsitsa | M57: Include | N57: Include | O57: Included: addresses software/systems modelling
A58: 57 | B58: IEEE Xplore | C58: Phindile Mposwa, Sibongiseni Tsitsa | D58: Querying Large Automotive Software Models Agentic vs. Direct LLM Approaches | E58: Chair of Robotics, Artificial Chair of Robotics, Artificial Universite´ Paris-Saclay, | F58: 2025 | I58: Large language models (LLMs) offer new oppor- development, where precise models ensure compliance and tunities for interacting with complex software artifacts, such reliability [1]. However, the increasing size and complexity of as software models, through natural language. They present thesemodelsposesignificantchallengesforengineersinterms especially promising benefits for large software models that are of access, understanding, and manipulation [2]. difficulttograspintheirentirety,makingtraditionalinteraction andanalysisapproacheschallenging.Thispaperinvestigatestwo Recent advancements in large language models (LLMs) of- approaches for leveraging LLMs to answer questions over soft- ferpromisingavenuestoassistwithcomplexsoftwaremodels, waremodels:directprompting,wherethewholesoftwaremodel leveragingtheircapabilitiesinnaturallanguageunderstanding is provided in the context, and an agentic approach combining andcodegeneration[3].Despitethispotential,thedirectappli- LLM-based agents with general-purpose file access tools. We cationofLLMstostructuredsoftwaremodels,especiallywith evaluate these approaches using an Ecore metamodel designed for timing analysis and software optimization in automotive and formal languages like PlantUML [4], remains largely unex- embedded domains. Our findings show that while the agentic plored [5]. Current research primarily focuses on unstructured approach achieves accuracy comparable to direct prompting, text or code, overlooking the unique challenges of integrating it is significantly more efficient in terms of token usage. This LLMs with structured models, including format compatibility, efficiency makes the agentic approach particularly suitable for semantic precision, and consistency. Furthermore, the efficacy theautomotiveindustry,wherethelargesizeofsoftwaremodels makes direct prompting infeasible, establishing LLM agents as of different LLM architectures, such as agentic workflows not just a practical alternative but the only viabl | J58: Phindile Mposwa | K58: Include | L58: Sibongiseni Tsitsa | M58: Include | N58: Include | O58: Included: addresses metamodel engineering with AI; applies AI to UML/software model artefacts
A59: 58 | B59: IEEE Xplore | C59: Phindile Mposwa, Sibongiseni Tsitsa | D59: RQ2DSL An AI Agent for Automated Domain-Specific Language Grammar Generation from Requirements | E59: Dept. of Electrical and Computer Engineering Dept. of Electrical and Computer Engineering | F59: 2025 | G59: 2025 IEEE 37th International Conference on Tools with Artificial Intelligence (ICTAI) | H59: https://doi.org/10.1109/ICTAI66417.2025.00189 | I59: Domain-Specific Language (DSL) design is a foun- requires specialized expertise in both the target domain and dational yet labor-intensive task in software engineering (SE). language engineering principles [2]. However, recent advances in Large Language Models (LLMs) Traditional DSL development follows a laborious iterative offer the potential to automate key aspects of DSL develop- process involving domain analysis, grammar specification, ment, including grammar generation, paving the way for wider DSL adoption. This paper presents RQ2DSL, an AI agent for parser generation and extensive validation. This workflow automated grammar generation that transforms requirements often creates bottlenecks in DSL development, as it requires (Functional and Non-Functional) into syntactically correct DSL close collaboration between domain experts who understand grammars using LLMs. The agent’s methodology comprises an the problem space and technical experts who possess the optimally defined LLM context that contains a TextX knowl- necessary language engineering skills [3]. The complexity of edge base, reference grammars, syntactic examples and error- aware guidance with explicit validation rules, supported by this process has historically limited the widespread adoption an iterative refinement process that leverages syntax validation of DSLs, despite their proven benefits in improving code feedback. Comprehensive experiments were conducted against clarity,reducingcomplexitydevelopmenttimeandminimizing DSLs of varying complexity levels (simple, medium, high, ultra- domain-specific errors [4]. high), with scalable requirement sets ranging from 4 to 30 Recent advances in Large Language Models (LLMs) have specifications, demonstrating that RQ2DSL maintains robust performance across simple (100%), medium (92%) and high demonstrated remarkable capabilities in code generation and (92%)complexitylevels.However,acriticalcomplexitythreshold understanding, fundamentally transforming approa | J59: Phindile Mposwa | K59: Include | L59: Sibongiseni Tsitsa | M59: Include | N59: Include | O59: Included: applies AI to domain-specific language/model engineering
A60: 59 | B60: IEEE Xplore | C60: Phindile Mposwa, Sibongiseni Tsitsa | D60: SE Arena An Interactive Platform for Evaluating Foundation Models in Software Engineering | E60: Kingston, Canada | F60: 2025 | G60: 2025 IEEE/ACM Second International Conference on AI Foundation Models and Software Engineering (Forge) | H60: https://doi.org/10.1109/Forge66646.2025.00016 | I60: Foundation models (FMs), particularly large lan- a critical feature for evaluating FMs in real-world SE tasks. guagemodels(LLMs),haveshownsignificantpromiseinvarious Copilot Arena2 also faces similar challenges. software engineering (SE) tasks, including code generation, de- To address these limitations, we propose SE Arena3, an bugging,andrequirementrefinement.Despitetheseadvances,ex- interactive platform tailored for the evaluation of FMs in istingevaluationframeworksareinsufficientforassessingmodel performanceiniterative,context-richworkflowscharacteristicof SE tasks. SE Arena enhances existing frameworks by incor- SEactivities.Toaddressthislimitation,weintroduceSEArena, porating multi-round dialogues and a transparent evaluation aninteractiveplatformdesignedtoevaluateSE-focusedchatbots. methodology, allowing engineers to benchmark FMs across SE Arena provides a transparent, open-source leaderboard, diverse SE workflows. In addition, SE Arena introduces a supportsmulti-roundconversationalworkflows,andenablesend- new feature called RepoChat that automatically extracts and to-end model comparisons. Moreover, SE Arena incorporates a new feature called RepoChat, which automatically injects injectsrepository-levelcontextintotheconversation,enabling repository-related context (e.g., issues, commits, pull requests) deeper and more realistic benchmarking of FMs for day- into the conversation, further aligning evaluations with real- to-day software engineering scenarios. This approach fills worlddevelopmentprocesses.Thispaperoutlinesthedesignand criticalgapsincurrentevaluationpractices,advancingthefield capabilities of SE Arena, emphasizing its potential to advance toward more nuanced and context-aware assessments. To our the evaluation and practical application of FMs in software engineering. knowledge, SE Arena is the first platform to integrate these IndexTerms—FoundationModel,SoftwareEngineering,Chat- capabilities for SE-specific evaluations. This paper introduces bot | J60: Phindile Mposwa | K60: Include | L60: Sibongiseni Tsitsa | M60: Include | N60: Include | O60: Included: applies AI within model-driven engineering context
A61: 60 | B61: IEEE Xplore | C61: Phindile Mposwa, Sibongiseni Tsitsa | D61: SHERPA A Model-Driven Framework for Large Language Model Execution | E61: Boqi Chen , Kua Chen , Jose´ Antonio Herna´ndez Lo´pez | F61: 2025 | H61: https://doi.org/10.1109/MODELS67397.2025.00024 | I61: Recently, large language models (LLMs) have Largelanguagemodels(LLMs)producestochasticsequences achievedwidespreadapplicationacrossvariousfields.Despitetheir of predictions based on input prompts [3]. With the emergence impressive capabilities, LLMs suffer from a lack of structured of advanced LLMs such as GPT-4o [4] and Qwen-2.5 [5], reasoningability,particularlyforcomplextasksrequiringdomain- theyhavebecomepowerfultoolsforautomatingcomplextasks specificbestpractices,whichareoftenunavailableinthetraining data. Although multi-step prompting methods incorporating across diverse domains using natural language. LLMs have human best practices, such as chain-of-thought and tree-of- shownremarkablecapabilitiesinvariousapplications,including thought, have gained popularity, they lack a general mechanism code generation [6], question answering [7], and planning [8], to control LLM behavior. In this paper, we propose SHERPA, [9]. In MDE, recent efforts have also shown promising results a model-driven framework to improve the LLM performance in fully automating the generation of diverse types of models on complex tasks by explicitly incorporating domain-specific best practices into hierarchical state machines. By structuring directly from natural language descriptions [10]. the LLM execution processes using state machines, SHERPA Problem description. However, the stochastic nature of LLMs enablesmorefine-grainedcontrolovertheirbehaviorviarulesor raises significant concerns around the potential hallucination decisionsdrivenbymachinelearning-basedapproaches,including in the generated outputs [11]. Moreover, specific human best LLMs. We show that SHERPA is applicable to a wide variety of practice is rarely reflected in training data, which limits LLMs’ tasks—specifically, code generation, class name generation, and question answering—replicating previously proposed approaches performanceincomplexanddomain-specifictasks.Approaches while further improving the performance. We demon | J61: Phindile Mposwa | K61: Include | L61: Sibongiseni Tsitsa | M61: Include | N61: Include | O61: Included: applies AI within model-driven engineering context
A62: 61 | B62: IEEE Xplore | C62: Phindile Mposwa, Sibongiseni Tsitsa | D62: SMATCH-M-LLM Semantic Similarity in Metamodel Matching With Large Language Models | E62: Nafisa Ahmed, Hin Chi Kwok, Mohammad Hamdaqa, Wesley K. G. Assunc¸a˜o | F62: 2025 | G62: 2025 IEEE/ACM 22nd International Conference on Mining Software Repositories (MSR) | H62: https://doi.org/10.1109/MSR66628.2025.00040 | I62: Metamodelmatchingplaysacrucialroleindefining for identifying metamodel correspondences, a vital step for transformation rules in model-driven engineering by identi- creatingeffectivetransformationrulesandfortaskslikemodel fying correspondences between different metamodels, forming synchronization, differencing, and merging [10]. thefoundationforeffectivetransformations.Currenttechniques Early metamodel matching leveraged linguistic similarity face significant challenges due to syntactical and structural heterogeneity.Toaddressthis,matchingtechniquesoftenemploy techniques, but they frequently encounter challenges due to semantic similarity to identify correspondences. Traditional se- syntactic heterogeneity between metamodels [11], [12]. To mantic matchers, however, rely on ontology matching tools or address this, researchers leveraged semantic similarities ap- lexical databases, which often struggle when metamodels use proachesinspiredbyontologymatching[13].However,effec- different terminologies or hierarchical structures. Inspired by tive ontology matching techniques necessitate metamodels to the contextual understanding capabilities of Large Language Models (LLMs), this paper explores the capability of GPT-4 possess common terminologies and structures [14]. The lack potentials as a semantic matcher and alternative to existing of these commonalities can result in suboptimal outcomes, as methods for metamodel matching. However, metamodels can be observed when matching disparate metamodels like WebML large,whichcanoverwhelmLLMsifprovidedinasingleprompt, with UML or Ecore, limiting the techniques’ utility in model leading to reduced accuracy. Therefore, we propose prompting migration scenarios that lack these alignments. LLMs with fragments of the source and target metamodels, LexicaldatabaseslikeWordNet[15]areemployedtodetect identifying correspondences through an iterative process. The fragmentstobeprovidedinthepromptareidentifiedbasedonan semantic similarities acro | J62: Phindile Mposwa | K62: Include | L62: Sibongiseni Tsitsa | M62: Include | N62: Include | O62: Included: addresses metamodel engineering with AI; applies AI to UML/software model artefacts; applies AI within model-driven engineering context
A63: 62 | B63: IEEE Xplore | C63: Phindile Mposwa, Sibongiseni Tsitsa | D63: SOEN-101 Code Generation by Emulating Software Process Models Using Large Language Model Agents | E63: Feng Lin, Dong Jae Kim, Tse-Hsun (Peter) Chen | F63: 2025 | G63: 2025 IEEE/ACM 47th International Conference on Software Engineering (ICSE) | H63: https://doi.org/10.1109/ICSE55347.2025.00140 | I63: Software process models are essential to facilitate niques like few-shot learning [18, 49] have been shown to collaboration and communication among software teams to improve code generation results. In particular, few-shot learn- solve complex development tasks. Inspired by these software ing coupled with few-shot sampling [24, 17] or information engineering practices, we present FlowGen – a code generation retrieval augmented technique [27, 6] have been shown to framework that emulates software process models based on multipleLargeLanguageModel(LLM)agents.Weemulatethree improve code generation. Moreover, one can integrate per- process models, FlowGen , FlowGen , and FlowGen , sonalization in the prompt, instructing LLMs to be domain Waterfall TDD Scrum by assigning LLM agents to embody roles (i.e., requirement experts in a specific field, which can further improve LLM engineer, architect, developer, tester, and scrum master) that responses [41, 34]. Such personalization techniques highlight correspondtoeverydaydevelopmentactivitiesandorganizetheir thepotentialofusingmultipleLLMsworkingtogethertoassist communication patterns. The agents work collaboratively using chain-of-thought and prompt composition with continuous self- in complex software development activities. refinement to improve the code quality. We use GPT3.5 as Giventhecomplexityofsoftwaredevelopment,LLMagents our underlying LLM and several baselines (RawGPT, CodeT, stand out among various LLM techniques. Agents are LLM Reflexion) to evaluate code generation on four benchmarks: instances that can be customized to carry out specific tasks HumanEval, HumanEval-ET, MBPP, and MBPP-ET. Our find- that replicate human workflow [14, 11]. Recently, multi-agent ings show that FlowGen excels compared to other process Scrum models, achieving a Pass@1 of 75.2, 65.5, 82.5, and 56.7 in systemshaveachievedsignificantprogressinsolvingcomplex HumanEval,HumanEval-ET,MBPP,andMBPP-ET,respectively problems in software develop | J63: Phindile Mposwa | K63: Include | L63: Sibongiseni Tsitsa | M63: Include | N63: Include | O63: Included: applies identifiable AI technique; supports model-to-code synthesis
A64: 63 | B64: IEEE Xplore | C64: Phindile Mposwa, Sibongiseni Tsitsa | D64: SkeMo Sketch Modeling for Real-Time Model Component Generation | E64: Alisha Sharma Chapai and Eric J. Rapos | F64: 2023 | H64: https://doi.org/10.1109/MODELS58315.2023.00038 | I64: Software modeling is a powerful tool in the design developers create informal sketches to understand, design, and implementation of high-quality software systems. Models and share their ideas within the team [2]. Such sketches are can be used from high-level design to formal code generation, createdusingdifferentmedia,fromanalogmediasuchaspaper with various applications in between. Often, software models or a whiteboard to digital media such as smartphones and are initially created informally, by sketching on a whiteboard or paper during the early design phase of the system, and computers.Sketchingispreferredintheearlystageofsoftware eventuallyconvertedintoformalmodelsusingadvancedmodeling development [3] as it fosters creativity [4] and collaboration tools.Theformalizationofsketchesintoactualmodelcomponents among various stakeholders [3]. Sketching provides a means can be time-consuming, error-prone, and laborious. To address of effective communication and collaboration by expressing theseshortcomings,wepresentSkeMo,anenvironmentforreal- ideas simply and abstractly. Moreover, the availability of time model component generation from sketch-based inputs. We curated a sketch dataset of 3000 images of various class digital devices such as mobile phones, tablets, touch-screen diagram components and implemented a powerful Convolution displays, and input devices with sufficient computing power NeuralNetworktoclassifyinputsketchesasmodelcomponents. has made free-form sketching more accessible and collab- We integrated our sketch classifier into an existing web-based orative [5]. Additionally, web-connected applications have model editor and added a touch interface to support sketch- further facilitated collaboration by allowing users to refine based modeling. We evaluated the SkeMo environment in two ways: through ten-fold cross-validation of the image classifier and formalize their digital sketches collaboratively [5], [6]. andcollectionofmetricsandfeedbackfroma20-partici | J64: Phindile Mposwa | K64: Include | L64: Sibongiseni Tsitsa | M64: Include | N64: Include | O64: Included: applies an identifiable AI technique to a model-engineering task
A65: 64 | B65: IEEE Xplore | C65: Phindile Mposwa, Sibongiseni Tsitsa | D65: SoTaNa An Open-Source Software Engineering Instruction-Tuned Model | E65: Ensheng Shi , Yanlin Wang , Fengji Zhang , Bei Chen , Hongyu Zhang | F65: 2025 | G65: 2025 IEEE/ACM Second International Conference on AI Foundation Models and Software Engineering (Forge) | H65: https://doi.org/10.1109/Forge66646.2025.00010 | I65: Softwaredevelopmentplaysacrucialroleindriving They exhibit remarkable capabilities as AI assistants across innovation and efficiency in modern societies. To meet the variousdomains,includingneuralmachinetranslation[8],text demands of this dynamic field, there is a growing need for an summarization [9], and code generation [10]. These models effective software development assistant. However, existing large are composed of billions of parameters, trained on extensive language models represented by ChatGPT suffer from limited accessibility,includingtrainingdataandmodelweights.Although data, up to hundreds of billions or even a trillion tokens, otherlargeopen-sourcemodelslikeLLaMAhaveshownpromise, and fine-tuned on instruction-based datasets [11]. However, they still struggle with understanding human intent. In this their accessibility is limited to restricted APIs. Also, other paper, we present SoTaNa, an open-source software engineering information such as model weights and instruction-based instruction-tuned model. SoTaNa utilizes ChatGPT to generate datasetsarenotavailable,creatingbarrierstonewresearchand high-quality instruction-based data for the domain of software engineering and employs a parameter-efficient fine-tuning ap- advancements.Ontheotherhand,open-sourcemodelssuchas proach to enhance the open-source foundation model, LLaMA. Alpaca[12]andVicuna[13],whichfine-tuneLLaMA[14](an We evaluate the effectiveness of SoTaNa in answering Stack open-source foundation language model) on the instruction- Overflowquestionsanddemonstrateitscapabilities.Additionally, based dataset generated by LLMs, have shown promising wediscussitscapabilitiesincodesummarizationandgeneration, results in understanding human intent and generating human- as well as the impact of varying the volume of generated data on model performance. Notably, SoTaNa can run on a single like responses. Nevertheless, due to the limited availability GPU, making it accessible to a broader range of researche | J65: Phindile Mposwa | K65: Include | L65: Sibongiseni Tsitsa | M65: Include | N65: Include | O65: Included: applies identifiable AI technique; supports model-to-code synthesis
A66: 65 | B66: IEEE Xplore | C66: Phindile Mposwa, Sibongiseni Tsitsa | D66: Software Engineering and Foundation Models Insights from Industry Blogs Using a Jury of Foundation Models | E66: Software Engineering and Foundation Models: | F66: 2025 | G66: 2025 IEEE/ACM 47th International Conference on Software Engineering: Software Engineering in Practice (ICSE-S | H66: https://doi.org/10.1109/ICSE-SEIP66354.2025.00033 | I66: Foundation models (FMs) such as large language models(LLMs)havesignificantlyimpactedmanyfields,including softwareengineering(SE).TheinteractionbetweenSEandFMs has led to the integration of FMs into SE practices (FM4SE) andtheapplicationofSEmethodologiestoFMs(SE4FM).While severalliteraturesurveysexistonacademiccontributionstothese trends, we are the first to provide a practitioner’s view. We analyze 155 FM4SE and 997 SE4FM blog posts from leading technology companies, leveraging an FM-powered surveying approach to systematically label and summarize the discussed activitiesandtasks.Weobservedthatwhilecodegenerationisthe Fig.1. AnoverviewofourFM/LLMJuryapproachforlabellingblogposts. mostprominentFM4SEtask,FMsareleveragedformanyother AblogpostislabelledbyeveryFMinthejury,andthefinallabelisselected SE activities such as code understanding, summarization, and through a majority vote (using the normalized confidence score as a tie- APIrecommendation.ThemajorityofblogpostsonSE4FMare breaker). about model deployment & operation, and system architecture &orchestration.Althoughtheemphasisisonclouddeployments, there is a growing interest in compressing FMs and deploying published, peer-reviewed literature [17], [28], mostly leaving them on smaller devices such as edge or mobile devices. We out the perspectives and experiences of industry practitioners. outline eight future research directions inspired by our gained insights, aiming to bridge the gap between academic findings The input of practitioners, who work at the intersection of and real-world applications. Our study not only enriches the SE and FMs in real-world settings, is a crucial yet under- body of knowledge on practical applications of FM4SE and explored source of insights. While the research community SE4FM but also demonstrates the utility of FMs as a powerful has recognized the value of user-generated contents such as and efficient approach in conducting literature surveys within Q&A websites [2] and issue report | J66: Phindile Mposwa | K66: Exclude | L66: Sibongiseni Tsitsa | M66: Exclude | N66: Exclude | O66: Excluded: Discusses AI for code/software tasks but does not address software model engineering (no UML, BPMN, DSL, metamodel, or model transformation involved)
A67: 66 | B67: IEEE Xplore | C67: Phindile Mposwa, Sibongiseni Tsitsa | D67: Software Model Evolution with Large Language Models Experiments on Simulated Public and Industrial Datasets | E67: Models: Experiments on Simulated, Public, and | F67: 2025 | G67: 2025 IEEE/ACM 47th International Conference on Software Engineering (ICSE) | H67: https://doi.org/10.1109/ICSE55347.2025.00112 | I67: Modelingstructureandbehaviorofsoftwaresystems For example, in object-oriented design, design patterns [30] plays a crucial role in the industrial practice of software are widely used and are not part of UML [56], but could be engineering.Aswithothersoftwareengineeringartifacts,software provided as edit operations by a UML modeling tool. models are subject to evolution. Supporting modelers in evolving For source code, modern integrated development environ- software models with recommendations for model completions is still an open problem, though. In this paper, we explore the ments already support writing and evolving source code by potential of large language models for this task. In particular, we (auto-)completion. Most notably, the use of large language propose an approach, RAMC, leveraging large language models, models (LLMs) has become state-of-the-art for the auto- model histories, and retrieval-augmented generation for model completion of source code [18, 77, 5, 29, 6, 75]. completion. Through experiments on three datasets, including an The world of software models seems to be lagging behind, industrialapplication, onepublic open-source communitydataset, and one controlled collection of simulated model repositories, andnogeneralapproachforsoftwaremodelauto-completionis we evaluate the potential of large language models for model readyforindustrialapplication.Ithasbeenevenarguedthatthe completion with RAMC. We found that large language models so-called cognification of use cases in model-driven software are indeed a promising technology for supporting software model engineering might turn the difference between (perceived) evolution (62.30% semantically correct completions on real-world added value and cost from negative to positive [13]. industrial data and up to 86.19% type-correct completions). The general inference capabilities of large language models are Problem Statement. Notably, for a few domain-specific particularly useful when dealing with concepts | J67: Phindile Mposwa | K67: Include | L67: Sibongiseni Tsitsa | M67: Include | N67: Include | O67: Included: applies AI to model evolution; applies AI to UML/software model artefacts; applies AI within model-driven engineering context
A68: 67 | B68: IEEE Xplore | C68: Phindile Mposwa, Sibongiseni Tsitsa | D68: Software Trustworthiness Assessment via Large Language Models LLMs | E68: Coimbra, Portugal | F68: 2025 | H68: https://doi.org/10.1109/EDCC-C66476.2025.00034 | I68: Nowadays, almost everything in our daily lives is doesnotrequirethesystemtobeexecutable,andcanbeused handled by software. From transport systems and autonomous on parts of the overall code base separately [2]. However, the systemstohealthcareandfinancialcontracts.So,trustworthiness problem is that many SCA tools have a recall rate near to hasbecomecritical.Softwaretrustworthinessreferstothedegree 50%, thus they exhibit a performance not better than random to which a software system can be trusted, in the aspects of reliabilityandsecurity.Itmeanstheabilitytobehaveasexpected guessing[2].Theseresultssuggestthatwecannotrelyonlyon evenwhenfacingfaults,attacks,orunexpectedconditions.Static SCAbecausedoingsowouldleavealargenumberofsecurity Code Analysis (SCA) tools can be used to identify security issues undiscovered, let alone the large number of FPs that issues,suchassoftwarevulnerabilities.Though,SCAtoolshavea should be reviewed manually [2]. So, the result of the SCA greatnumberofFalsePositives(FPs)andFalseNegatives(FNs). toolsneedstobereassessedcautiouslybythehumansecurity Consequently, developers do not use them or spend a lot of timeanalyzingthealertsreportedbysuchtoolswithoutknowing experts,toincreasethereliabilityoftheprocess.Theproblem that all vulnerabilities are identified. On the other hand, Large becomes worse when considering a large project with many LanguageModels(LLMs)arebeingusedinsoftwareengineering files. tasks,suchascodegeneration,codereview,codedocumentation, LLMs such as CodeBERT [3], CodeT5 [4], and DeepSeek and even bug detection. These capabilities have attracted the [5]haveprovedthemselveswonderfullyinunderstandingpro- interestofresearcherstotheirpotentialforautomatingSoftware TrustworthinessAssessment(STA).AstheperformanceofLLMs gramminglanguages.TheabilityofLLMsincodegeneration, in STA is not satiable yet, there is an emerging need to obtain codedocumentation,andtestgenerationhasencouragedmany the best results out of their great potential. Alt | J68: Phindile Mposwa | K68: Exclude | L68: Sibongiseni Tsitsa | M68: Exclude | N68: Exclude | O68: Excluded: Discusses AI for code/software tasks but does not address software model engineering (no UML, BPMN, DSL, metamodel, or model transformation involved)
A69: 68 | B69: IEEE Xplore | C69: Phindile Mposwa, Sibongiseni Tsitsa | D69: Streamlining Epidemiological Model Generation Using Large Language Models | E69: Aaditya Karamchandani, Fatemeh Seyeddabbaghi, and Marios Fokaefs | F69: 2025 | G69: 2025 IEEE International Conference on Collaborative Advances in Software and COmputiNg (CASCON) | H69: https://doi.org/10.1109/CASCON66301.2025.00096 | I69: Epidemiological modeling is a critical step in un- (Epidemiological Model-Driven Engineering) platform [4] derstanding and studying diseases. While conventional modeling and its seirmodel XML format. The platform bridges techniques, like compartmental or agentic models, exist, sup- traditional epidemiological modeling with model-driven en- porting tools are not necessarily standardized. Consequently, gineering, supporting SEIR (Susceptible-Exposed-Infectious- learninganewtoolmayincursignificanteffort.Inthiswork,we explore the use of Large Language Models (LLMs) as a means Recovered) paradigms with complex stratifications. toquicklytransitionfromrequirements,intheformofgraphical B. Two-Stage LLM Pipeline modelrepresentationsandinitialparameterstoasoftware-aided modeling platform with simulation and verification capabilities. Our pipeline uses Google’s Gemini 2.5 Pro [5]: Stage 1 Ourmethodologyemploysametamodel-basedlanguagespecifica- generatesstructurallycorrect.seirmodelXMLwithplace- tion for prompt engineering, combined with multimodal inputs holdervaluesfromMainPrompt,LanguageSpecification,and comprising textual descriptions and epidemiological diagrams. User Input. Stage 2 calculates final numerical rates using We evaluate LLM performance across three epidemiological models of varying complexity: a simple SIR compartmental “reason-before-answer” strategy. Figure 1 illustrates a typical model, a COVID-19 pandemic model, and an HIV transmission SIR model diagram used as input. model. Initial results demonstrate the potential of LLMs to significantly reduce manual modeling effort while maintaining accuracy in structural representation and parameter extraction. The study provides insights into optimal input configurations andidentifieskeychallengesinautomatedepidemiologicalmodel generation. | J69: Phindile Mposwa | K69: Include | L69: Sibongiseni Tsitsa | M69: Include | N69: Include | O69: Included: applies AI to model generation; addresses metamodel engineering with AI; applies AI within model-driven engineering context
A70: 69 | B70: IEEE Xplore | C70: Phindile Mposwa, Sibongiseni Tsitsa | D70: Sustainability Implications of Large Language Model use in Model-Driven Engineering | F70: 2025 | H70: https://doi.org/10.1109/MODELS-C68889.2025.00101 | I70: Large language models (LLMs) have been increas- 3) How effective are LLMs at detecting and correcting ingly used for a wide range of software engineering processes, energy-efficiencyflawsincode,comparedtoMDEtech- including model-driven engineering (MDE). LLMs have been niques for energy-use analysis and improvement? used to perform reverse engineering of code to models, to gen- erate code from models, and to perform model transformations, as alternatives to rule-based techniques for these activities. In II. CODEPRODUCTIONAPPROACHES this paper we examine the energy-use implications of applying LLMs for code generation and reverse engineering within an Three code production practices are considered here: (i) MDEprocess.WealsoconsiderLMMcapabilitiesforoptimising manual code production, using IDEs such as Visual Studio; software energy use. (ii) automated code generation from software models, using IndexTerms—MDE,LLM,codegeneration,reverseengineer- a model transformation (MT) or (iii) synthesis of code by an ing, sustainable software. LLM, based on user prompts and contextual information. | J70: Phindile Mposwa | K70: Include | L70: Sibongiseni Tsitsa | M70: Include | N70: Include | O70: Included: applies AI to model transformation; applies AI to reverse engineering/code-to-model extraction; applies AI to model-to-code synthesis; applies AI within model-driven engineering context
A71: 70 | B71: IEEE Xplore | C71: Phindile Mposwa, Sibongiseni Tsitsa | D71: Synthetic Model Generation from Metamodel Using Conditional Tabular Generative Adversarial Network | E71: Oran, Algeria Oran, Algeria Oran, Algeria | F71: 2024 | I71: Building a dataset of models that are metamodel the need to write transformation-specific code. instances for a Model-Driven Engineering (MDE) process using Artificial intelligence techniques in general, and those of Artificial Intelligence (AI) techniques is now gaining traction. machine learning in particular, are generally based on the use These datasets are rare. For this reason, the availability of such of massive amounts of data. Indeed, machine learning algo- datasets is a challenge in the context of MDE and AI. rithms, and in particular its supervised learning techniques, The central idea of the paper is to use deep learning techniques tobuildinstancesofametamodelthatconstituteadataset.Thus, enablemachinestolearntherelationships(mappings)between our contribution focuses on creating synthetic instances of a existingexamplesinaninput-outputdatasetandthentopredict metamodel using a Conditional Tabular Generative Adversarial output data based on entirely new input data. Network (CTGAN). But in the MDE field, unlike image processing or language | J71: Phindile Mposwa | K71: Include | L71: Sibongiseni Tsitsa | M71: Include | N71: Include | O71: Included: applies AI to model generation; addresses metamodel engineering with AI; applies AI within model-driven engineering context
A72: 71 | B72: IEEE Xplore | C72: Phindile Mposwa, Sibongiseni Tsitsa | D72: Text-to-Mapper Generating Executable MyBatis ORM Artifacts from Natural Language Requirements | E72: Zhenhan Chen, Xiaoyu Lin, Yingxin Chen, Ruoyu Huang, Jiqiang Yan, Zhenghao Chi, Jiahao Dai, Zhiling Cai, | F72: 2021 | G72: IEEE Transactions on Software Engineering. This is the author's version which has not been fully edi | H72: https://doi.org/10.1109/TSE.2026.3702824 | I72: Enterprisedatabaseapplicationsaretypicallymedi- runtime control flow, and result-set mappings into Java ob- ated by Object–Relational Mapping (ORM) frameworks such as jects.Asinglemapperstatementmustsimultaneouslydescribe MyBatis rather than by raw SQL, yet most natural-language the SQL query, branch conditions over parameters (<if>, interfaces to data target single SQL strings and bypass the <choose>, <foreach>), and the alignment between projected mapper layer. This paper formulates the pioneering task of Text-to-Mapper,generatingexecutableMyBatismapperfilesfrom columns and the fields and types of target JavaBeans. Seem- natural-languagerequirementsgivendatabaseschemasandJava ingly local changes—adding a predicate, renaming a column, entity specifications. To support this setting, a high-quality or refactoring a nested association—may silently break these dataset,MyBatis-Spidertogetherwithanevaluationpipelinethat cross-artifact contracts and cause production failures, making exercisescandidatesthroughaparse-build-execute-alignruntime mapper configuration both time-consuming and error-prone. chain. To capture execution-level semantics, an execution-based metric, Object Semantic Alignment (OSA), compares the Java Existing industrial tools only partially address this diffi- objects produced by generated and reference mappers. Our culty. Template-based frameworks and code generators (e.g., empirical study of direct-transfer baselines highlights recurring MyBatis Generator, MyBatis Plus) reverse-engineer schemas field-column-typebindingerrors;motivatedbythis,weintroduce Across-Struct-Table (AST), a compact two-dimensional represen- to emit Plain Old Java Objects (POJOs), mapper interfaces, tation that makes these correspondences explicit. Systematic andcreate–read–update–delete(CRUD)XMLfromtemplates. experiments with commercial and open-weights large language These model-first approaches reduce boilerplate and improve models show that AST yields consistent OSA improvem | J72: Phindile Mposwa | K72: Exclude | L72: Sibongiseni Tsitsa | M72: Exclude | N72: Exclude | O72: Excluded: Does not apply an identifiable AI technique to a model-engineering task; lacks connection to software modelling (UML, BPMN, metamodel, DSL) or AI-driven automation
A73: 72 | B73: IEEE Xplore | C73: Phindile Mposwa, Sibongiseni Tsitsa | D73: Toward a New Era of Rapid Development Assessing GPT-4-Visions Capabilities in UML-Based Code Generation | E73: Szeged,Hungary Szeged,Hungary Szeged,Hungary | F73: 2024 | H73: https://doi.org/10.1145/3643795.3648391 | I73: 1 INTRODUCTION Theemergenceofadvancedneuralnetworkshasopenedupnew Insoftwareengineering,thedesignphaseiscrucialindefining waysinautomatedcodegenerationfromconceptualmodels,promis- thesystemarchitectureandservesasapreliminaryblueprintfor ingtoenhancesoftwaredevelopmentprocesses.Thispaperpresents development.UnifiedModelingLanguage(UML)[4]hasemerged apreliminaryevaluationofGPT-4-Vision,astate-of-the-artdeep asthedefactostandardformodelingandvisualizingthedesignof learningmodel,anditscapabilitiesintransformingUnifiedModel- softwaresystems.UMLprovidesvariousdiagramstoexpressdiffer- ingLanguage(UML)classdiagramsintofullyoperatingJavaclass entaspectsofsoftwaredesign,includingstructural,behavioral,and files.Inourstudy,weusedexportedimagesof18classdiagrams interactiondiagrams.Thesediagramsserveasacommunication comprising10single-classand8multi-classdiagrams.Weused3 mediumamongvariousstakeholders,suchasdevelopers,analysts, differentpromptsforeachinput,andwemanuallyevaluatedthe andmanagers,andprovideabasisfortheimplementationphase results.Wecreatedascoringsysteminwhichwescoredtheoc- inthesoftwaredevelopmentlifecycle.Moreover,whenUMLclass currenceofelementsfoundinthediagramwithinthesourcecode. diagramsareaccuratelyandcarefullydesigned,theycansignifi- Onaverage,themodelwasabletogeneratesourcecodefor88% cantlyreduceambiguities,decreasingthelikelihoodoferrorsin oftheelementsshowninthediagrams.Ourresultsindicatethat thecodingprocess. GPT-4-Visionexhibitsproficiencyinhandlingsingle-classUML Theclassdiagramisparticularlysignificantamongthevarious diagrams,successfullytransformingthemintosyntacticallycorrect typesofUMLdiagrams.Itoffersastaticviewofthesystem,de- classfiles.However,formulti-classUMLdiagrams,themodel’s tailingclasses,theirattributes,operations(ormethods),andthe performanceisweakercomparedtosingle-classdiagrams.Insum- relationships among them, all of which are essential for under- mary,furtherinvestigationsarenecessarytoexploitthemodel’s standingobject-orientedsoftwarede | J73: Phindile Mposwa | K73: Include | L73: Sibongiseni Tsitsa | M73: Include | N73: Include | O73: Included: applies AI to UML/software model artefacts
A74: 73 | B74: IEEE Xplore | C74: Phindile Mposwa, Sibongiseni Tsitsa | D74: Toward an Automated View Abstraction for Distributed Model-Driven Service Development | E74: Yucong Duan , Qiang Duan , Ruisheng Shi , Honghao Gao | F74: 2016 | G74: 2016 IEEE International Conference on Services Computing | H74: https://doi.org/10.1109/SCC.2016.115 | I74: ion for Distributed Model-Driven Service Development ∗ † ‡ § Yucong Duan , Qiang Duan , Ruisheng Shi , Honghao Gao ∗ Hainan University, Haikou, China, Email: duanyucong@hotmail.com † Pennsylvania State University, PA, USA, Email: qduan@psu.edu ‡ Beijing University of Posts and Telecommunications, Beijing, China, Email: shiruisheng@bupt.edu.cn § Shanghai University, China, Email: gaohonghao@shu.edu.cn Abstract—UMLviewintegrationhasbeenextensivelystudied becauseitformsthefoundationforcorrectlyconstructingmost in the area of model transformation in Model Driven Develop- systems and may reduce management complexity by bridging ment. Empirical processing rules are among the most widely the information flows among otherwise separated model files. employedapproachesforprocessingviewabstraction,whichcan supportmodelsimplification,consistencychecking,andmanage- Empiricalrulesfacechallengesfromthefollowingaspects. ment complexity reduction. However, empirical rules face some Completeness validation is required since rule completeness challenges such as completeness validation, consistency among is not formally guaranteed. Consistency validation [6] among rules, and composition priority arrangement. The challenge of rules is needed since empirical rules are collected indepen- rule composition is amplified in the environment of distributed dentlywithoutagenerationmechanism.Inaddition,composi- model driven development for web service-based systems where tion priority arrangement is important to determine the order redundant information/data is emphasized. The same redundant ofapplyingandexecutingrulesforaspecificapplication.The information can be expressed in different forms that comprise priorityoftherulesmightnotbefixedforanyapplicationcon- various topological structures for entity relationship networks text.Inthispaper,weassumethattheprioritymightbevalidin representing the same part of the system. Such variation will result in choosing different compositions of rules executed | J74: Phindile Mposwa | K74: Include | L74: Sibongiseni Tsitsa | M74: Include | N74: Include | O74: Included: addresses software/systems modelling; transforms software models
A75: 74 | B75: IEEE Xplore | C75: Phindile Mposwa, Sibongiseni Tsitsa | D75: Towards AI-Augmented Co-Compilation for Smart IoT Systems Through Domain-Specific LLMs | I75: The explosion of smart, interconnected IoT devices 1) Integrate self-* capabilities: leverage automated adap- is driving demand for higher performance, real-time process- tation, reconfiguration, and healing to improve the re- ing, and self-* capabilities (self-adaptation, self-reconfiguration, silience and responsiveness of smart applications. self-healing) across heterogeneous platforms. CPUs, GPUs, and 2) Reduce human effort: offload labor-intensive tuning FPGAs now provide exceptional compute power but greatly complicate software toolchains. We envision AI-COMPILER, tasks for each hardware type, accelerating development an LLM-driven, domain-specific framework that automates and deployment cycles. co-compilation and optimization of heterogeneous applications 3) Enable multi-objective optimization: balance perfor- in smart cities, smart transportation, and real-time analytics. mance, power consumption, latency, and reliability in Tackling multi-objective goals—power efficiency, reliability, and IoT systems. dynamic reconfiguration—AI-COMPILER aims to transform how IoT and edge infrastructures are developed, deployed, and 4) Maintain semantic fidelity across DSLs: ensure that maintained. We examine critical issues such as generalization cross-platform transformations preserve functional cor- to new hardware, human-AI collaborative tuning, and semantic rectness and domain-specific constraints. coherence across multiple DSLs, arguing that AI-COMPILER canusherinmoreagile,resilientIoTecosystemsthroughflexible, II. BACKGROUNDANDMOTIVATION context-aware code generation and adaptation. | J75: Phindile Mposwa | K75: Include | L75: Sibongiseni Tsitsa | M75: Include | N75: Include | O75: Included: applies AI to model transformation; applies AI to domain-specific language/model engineering
A76: 75 | B76: IEEE Xplore | C76: Phindile Mposwa, Sibongiseni Tsitsa | D76: Towards Class Diagram Generation from User Stories Using LLMs | E76: Software Engineering Group Software Engineering Group Institute of Information Security and Dependability | I76: Integrating large language models into software modeling has unlocked new possibilities for automating stories describe software features informally, highlighting the laborintensive processes. One promising application is the value they provide to the customer. These types of approaches automatic generation of Unified Modeling Language class foster a shared understanding among teams about what to build, diagrams from user stories, which traditionally requires who will use it, why it is needed, and when it should be significant manual effort and expertise. This paper takes the first step towards developing an application that utilizes LLMs to delivered. The simplicity and clarity of user stories make them bridge artificial intelligence and software modeling. The proposed a popular method for conveying product functionality, ensuring approach is assessed based on key metrics such as ease of that all stakeholders have a common ground for discussing integration and its ability to interpret ambiguous or incomplete requirements. By ensuring user stories are well-defined and requirements. Additionally, the paper examines the challenges of handling domain-specific constraints and the trade-offs between actionable, development teams can streamline the project rule-based and fully automated methods, evaluating how they workflow and improve overall outcomes. balance user control and system autonomy. By taking the initial By efficiently converting abstract concepts into well- steps towards streamlining class diagram generation and reducing structured models, large language models (LLMs) [3] bridge reliance on manual modeling, this study contributes to advancing automation in software engineering. the gap in software modelling. This enables teams to transition | J76: Phindile Mposwa | K76: Include | L76: Sibongiseni Tsitsa | M76: Include | N76: Include | O76: Included: applies AI to UML/software model artefacts
A77: 76 | B77: IEEE Xplore | C77: Phindile Mposwa, Sibongiseni Tsitsa | D77: Towards Model-Driven Engineering for Big Data Analytics -- An Exploratory Analysis of Domain-Specific Languages for Machine Learning | F77: 2014 | H77: https://doi.org/10.1109/HICSS.2014.101 | I77: processing (OLAP) while for the latter, probabilistic Graphical models and general purpose inference analysis techniques can be used with great success. algorithms are powerful tools for moving from impera- In the context of big data, much research focusses tive towards declarative specification of machine on technological aspects such as coping with petabyte- learning problems. Although graphical models define scale datasets. Various approaches to accomplish this the principle information necessary to adapt inference are discussed in the literature [4], with the MapReduce algorithms to specific probabilistic models, entirely paradigm being the most well-known [5]. Yet even model-driven development is not yet possible. Howev- more important than having the technology to process er, generating executable code from graphical models data is hiring talented people capable to make sense of could have several advantages. It could reduce the it. Data alone is worthless without analysis. Demand skills necessary to implement probabilistic models and for data scientists is way ahead of supply [6]. may speed up development processes. Both advantages One reason why data scientists are that hard to find address pressing industry needs. They come along with can be found by considering the skillset they have to increased supply of data scientist labor, the demand of possess. The machine learning and data mining com- which cannot be fulfilled at the moment. To explore the munities have developed a long list of different algo- opportunities of model-driven big data analytics, I rithms for tackling all sorts of analysis problems. review the main modeling languages used in machine Among the most popular examples are k-means for learning as well as inference algorithms and corre- clustering and support vector machines for classifica- sponding software implementations. Gaps hampering tion [7]. Sophisticated software tools such as WEKA direct code generation from graphical models are [8] | J77: Phindile Mposwa | K77: Include | L77: Sibongiseni Tsitsa | M77: Include | N77: Include | O77: Included: applies AI to model-to-code synthesis; applies AI to domain-specific language/model engineering; applies AI within model-driven engineering context
A78: 77 | B78: IEEE Xplore | C78: Phindile Mposwa, Sibongiseni Tsitsa | D78: Towards a Domain-Specific Language for Provisioning Multiple Cloud Testing Environments for Mobile Applications | E78: Bogota´, Colombia Bogota´, Colombia | F78: 2022 | H78: https://doi.org/10.1109/ICI2ST57350.2022.00033 | I78: Provisioning testing environments specifications. Software testing helps in the prevention of for mobile applications is one of the most significant challenges errors in a system [2]. within the software industry. Due to this high complexity that exists when provisioning test environments within the multiple available cloud platforms, it is necessary to make a significant Around66%oftheworld’spopulationhadamobiledevice, investment in human resources, like time and effort for the suchasaphone,tablet,orInternetofThingsdevice,in2021, implementation and execution of testing. There is additional and the number of smartphone users hit 3.8 billion. [3] In complexity:testingsoftwareinasingleenvironmentisnolonger 2018, more than 205 billion mobile apps were downloaded sufficient. Today’s mobile industry is constantly growing, and from the app stores [4]. Mobile applications are expected to executionenvironmentstendtobealwaysdifferent;thehardware configuration is usually different and sometimes exceeds the earn $935 billion in revenue in 2023 as opposed to the $365 software barrier. It is challenging to execute testing on each billion they did in 2018 [5]. of the existing devices, as this requires a long task of human intervention. Even if they try, companies cannot test software on every Today some platforms provide testing services in different envi- available device. Because Smartphones and tablets are two ronments. However, not all providers have the complete set of environmentsthatonewouldliketohave,andspecificknowledge examples of mobile electronics that are gaining popularity. is mandatory for using each available tool. It is a task that According to research, around a third of people worldwide requires expertise and time. This work seeks to mitigate the own a portable gadget [6]. Companies must decide which impact on time and the learning curve through a high-level devices to use to execute testing in each stage of the tool developed using a model-oriented approach, t | J78: Phindile Mposwa | K78: Include | L78: Sibongiseni Tsitsa | M78: Include | N78: Include | O78: Included: addresses software/systems modelling; applies learning-based technique to model engineering
A79: 78 | B79: IEEE Xplore | C79: Phindile Mposwa, Sibongiseni Tsitsa | D79: Training LLMs for Generating IEC 61131-3 Structured Text with Online Feedback | E79: Aaron Haag, Bertram Fuchs, Altay Kacan, Oliver Lohse | F79: 2025 | G79: 2025 IEEE/ACM International Workshop on Large Language Models for Code (LLM4Code) | H79: https://doi.org/10.1109/LLM4Code66737.2025.00013 | I79: IEC 61131-3 Structured Text (ST) is a widely based on expert feedback. With LLMs growing in size and used programming language for programmable logic controllers complexity, this method can become prohibitively expensive (PLCs) in automation systems. However, generating ST code if human experts label IEC 61131-3 conform generated code. with LLMs poses unique challenges due to limited data in Therefore,innovativealignmentmethodsbeyonddirecthuman public training datasets and the complexity of ST language syntax. This paper proposes an approach to fine-tune LLMs feedback are needed to fully leverage these models. for the generation of ST code that leverages a preference-based In response to this challenge, this work utilizes synthetic learning method through an online process involving compiler experts in an iterative online approach based on syntactic feedback and evaluation from an LLM-based ST expert. In this compiler feedback and a dedicated semantic LLM expert. To framework, the model is iteratively refined and generates new overcomethedatascarcityofPLCcodesamples,theproposed trainingsamples,whicharesubsequentlyevaluatedbyacompiler for syntactical correctness and by a specialized LLM that excels framework exclusively exploits preexisting user prompt and atassessingsemanticaccuracy,thoughitisnotoptimizedforcode code pairs derived from the APPS dataset [10] for SFT, generationitself.Thisapproachresultsinmarkedimprovements as well as additional prompts that are subsequently used in for the trained LLM, leading to higher compilation success an online finetuning scheme similar to Online AI Feedback rates and better semantic precision. As a result, the framework (OAIF) [11]. This eliminates the need for large code datasets. proveshighlysuitableforindustrialautomationapplicationsand outperforms state-of-the-art models. The approach iteratively refines the model and incorporates | J79: Phindile Mposwa | K79: Exclude | L79: Sibongiseni Tsitsa | M79: Exclude | N79: Exclude | O79: Excluded: Discusses AI for code/software tasks but does not address software model engineering (no UML, BPMN, DSL, metamodel, or model transformation involved)
A80: 79 | B80: IEEE Xplore | C80: Phindile Mposwa, Sibongiseni Tsitsa | D80: Unified Modelling and Consistency Verification of UML Multi-View Models Using Alloy | E80: Unified Modelling and Consistency Verification | F80: 2025 | H80: https://doi.org/10.1109/APSEC66846.2025.00107 | I80: As software systems grow in complexity, cannot formally verify cross-view semantic consistency, Model-Driven Development demands precise and scalable detecting fewer than 50% of errors [12]. verificationtechniques.UMLenablesmulti-viewmodeling, To address these challenges, we propose a model yet its semiformal semantics frequently lead to inconsis- transformation framework for consistency validation be- tenciesacrossdiagrams.Thispaperpresentsaconsistency verification approach for class and sequence diagrams tween CDs and SDs. The approach maps class and using the Alloy modeling language. We systematically sequence models into an Alloy model, applies a li- transformUMLmodelsintoAlloylogicthroughamodular brary of predefined consistency rules, and leverages abstraction strategy and a set of formal consistency rules the Alloy Analyzer to automatically analyse and report spanning structural, behavioral, and cross-view semantics. inconsistencies. The paper reviews UML consistency TheAlloyAnalyzerthenperformsconstraintsolving,auto- maticallydetectsviolations,andgeneratescounterexamples issues,presentsourCD/SD-to-Alloyverificationmethod, for debugging. Evaluated in a case study, the method demonstrates a case study, and concludes with findings demonstrateseffectiveinconsistencydetection,comprehen- and future work. sive rule coverage, and reliable validation of interaction logic.Resultsconfirmthattheapproachenablesautomated, II. BACKGROUNDANDRELATEDWORK fine-grained consistency checking and integrates smoothly into formal verification workflows. Multi-view inconsistencies can compromise software | J80: Phindile Mposwa | K80: Include | L80: Sibongiseni Tsitsa | M80: Include | N80: Include | O80: Included: applies AI to UML/software model artefacts; applies AI within model-driven engineering context
A81: 80 | B81: IEEE Xplore | C81: Phindile Mposwa, Sibongiseni Tsitsa | D81: Using LLMs for Writing ATL Model Transformation Code | E81: Al Ain, United Arab Emirates Al Ain, United Arab Emirates | F81: 2025 | I81: Large Language Models (LLMs) have demonstrated ATL task, including evaluation of compilation/execution errors remarkable capabilities in code generation across various pro- and formatting inconsistencies, and (3) discussion on the gramming languages and domains. In this paper, we present implications for exploiting LLMs in MDE domain. the first empirical study investigating the use of LLMs for The remainder of this paper is structured as follows. Sec- generating ATL (ATLAS Transformation Language) model trans- formation code in the context of Model-Driven Engineering tion II discusses the related work. Section III illustrates the (MDE). Through controlled experiments using minimal prompts approach, and Section IV discusses the evaluation of the and metamodels, we show that state-of-the-art LLMs such as approach. Finally, Section V concludes the paper and discusses ChatGPT and Claude can produce syntactically correct and future work. executable ATL transformations. The results confirm that LLMs have implicitly learned ATL’s structural and semantic patterns, II. RELATED WORK enabling the automatic generation of valid transformation rules. This section provides a summary of existing work in This opens new research directions for the MDE community, sug- gesting that LLMs can serve as practical assistants or co-authors this domain. Model transformation is a vital step in MDE, in building and validating model transformation solutions. with taxonomies organizing languages by execution semantics, | J81: Phindile Mposwa | K81: Include | L81: Sibongiseni Tsitsa | M81: Include | N81: Include | O81: Included: applies AI to model transformation; addresses metamodel engineering with AI; applies AI within model-driven engineering context
A82: 81 | B82: IEEE Xplore | C82: Phindile Mposwa, Sibongiseni Tsitsa | D82: Using Large Language Models to Extract UML Class Diagrams from Java Programs | F82: 2025 | H82: https://doi.org/10.1109/ICoSSE65712.2025.00020 | I82: Many organizations rely on software systems to The class diagram is the most commonly used type of UML perform their core business operations. These systems often diagram, and it defines a data-oriented view of a system, require modernization to accommodate new requirements and focusing on the classes and their relationships within the demands over time. Visual representations and diagrams help software system. Large Language Models (LLMs) are a type maintainers to understand these systems and to assist their maintenanceandevolution.Reverseengineeringisusedtoextract of machine learning (ML) technology that are trained on a different representations of software systems, and the model- massive amount of textual data and can perform a variety of driven engineering (MDE) approach can be used to assist the specificdownstreamtasks.Theyhavehadasignificantimpact reverse engineering process, leading to model-driven reverse on various domains, including software engineering, where engineering (MDRE). Large Language Models (LLMs) are an they are used in various activities, including software devel- advanced deep learning (DL) technology increasingly being ap- pliedinvariousdomains.Despitethis,theuseofLLMstoextract opment, verification, maintenance, and quality assurance [3]. diagramsfromsourcecodehasrarelybeenused.Inthispaper,we Since LLMs are trained on datasets involving programming introduceanovelMDREframework,LLM4Models,thatextracts languages, they can understand the syntax and semantics of UML class diagrams from Java source code files using LLMs. variousprograms,savingdeveloperstimeandeffortcompared The paper also introduces a set of rules to extract UML class to traditional MDRE tools. Although combining traditional diagram representations. These rules have been implemented to createtrainingdatasamples,whicharethenusedtofine-tunethe MDRE techniques with LLMs can offer many prospective pre-trained LLM. Finally, the proposed framework is explained benefits, research on th | J82: Phindile Mposwa | K82: Include | L82: Sibongiseni Tsitsa | M82: Include | N82: Include | O82: Included: applies AI to reverse engineering/code-to-model extraction; applies AI to UML/software model artefacts; applies AI within model-driven engineering context
A83: 82 | B83: IEEE Xplore | C83: Phindile Mposwa, Sibongiseni Tsitsa | D83: Using the SCADE Toolchain to Generate Requirements-Based Test Cases for an Adaptive Cruise Control System | E83: Adina Aniculaesei, Andreas Vorwald, and Andreas Rausch | F83: 2019 | H83: https://doi.org/10.1109/MODELS-C.2019.00079 | I83: In the last years, model-driven engineering has the driver are taken on by complex software systems. The gained a lot of traction, especially in industrial domains, such complexity of automotive software is reflected in extensive asautomotiveoravionics.Varioustoolswhichsupportmodel- catalogues of system requirements, which are becoming driven engineering, e.g. SCADE or MATLAB/Simulink, have more common in the automotive industry [1]. Although developed over the years in fully fledged integrated develop- ment environments, with strong capabilities for the modeling formal verification methods can be used to check parts of a of complex software systems. Model-driven engineering tools complex automotive system, neither international standards are mature enough so that the model created with them are nor national certification bodies consider these approaches amenabletoformalanalysisforthepurposeofverificationand to be sufficient for the validation of the automotive system validation.Acceptancetestingisavalidationmethodbywhich with respect to the customer and legal requirements. Thus, a system is tested extensively against legal and customer re- quirements,beforeitisallowedinseriesproduction.Duetothe before being allowed in series production, an automotive inherentcomplexityofautomotivesystems,largerequirements systemmustpassallitsacceptancetests,andthus,fulfillall catalogueshavebecomeusualinthisdomain.Checkingthata requirementsinthecatalogue.Moreover,certificationbodies complex automotive software system conforms to an extensive requirethatanautomotivesystemistestedinthefieldbefore requirements catalogue is a task which cannot be managed being allowed in public use. manuallyanymore.Inthispaper,wedesignaworkflowfortest engineerstoconstructtestcasesfromformalizedrequirements Software testing is a process which requires a lot of and examine the quality of tests via mutant testing within the expert knowledge. In the automotive domain, requirements SCADEtoolchain.Weconstruct | J83: Phindile Mposwa | K83: Include | L83: Sibongiseni Tsitsa | M83: Include | N83: Include | O83: Included: addresses software/systems modelling
A84: 83 | B84: IEEE Xplore | C84: Phindile Mposwa, Sibongiseni Tsitsa | D84: Verification Method of UML Diagrams Using Large Language Models | E84: Graduate School of Engineering and Science, Shibaura Institute of Technology, Saitama, Japan | I84: UML state diagrams are increasingly used in sec- constraint that the LLM may only use information visible in ondaryeducation,suchastheJapaneseInformaticsIcourse,yet the drawing. We realize this pipeline in two prototypes: a students often struggle with dynamic behavior even after mas- smartphoneappthatprovidescodeand,whencodegeneration tering surface notation. Existing execution environments assume fails, concise revision guidance, and a web-based prototype carefullyprepareddigitalmodelsindedicatedtools,whichcanbe demandingfornovices.Thiswork-in-progressproposesanLLM- that integrates code generation and execution and adopts based approach that generates executable code directly from compiler-like feedback that reports only fatal diagram errors. images of hand-drawn UML state diagrams, allowing students We evaluate conversion accuracy and failure patterns as an to experiment with runtime behavior while keeping the familiar initial step toward assessing whether this approach is reliable practice of sketching by hand. We implement prototypes for enough for classroom use and discuss directions for future smartphoneandwebenvironmentsandevaluateconversionaccu- racyondiagramsofvaryingcomplexity.Preliminaryexperiments classroom trials. show useful accuracy on low-complexity diagrams and confirm • We propose an LLM-based pipeline that takes a hand- thatthesystemdoesnotsilentlyfixintentionallyfaultydiagrams, drawn UML state diagram as an image, uses the LLM suggestingthatthisapproachispromisingforsupportingnovices toreconstructitsstructure,andgeneratesexecutableJava in learning dynamic behavior. codeoranexpliciterrorreport,whilerestrictingtheLLM | J84: Phindile Mposwa | K84: Include | L84: Sibongiseni Tsitsa | M84: Include | N84: Include | O84: Included: applies AI to UML/software model artefacts

Sheet ScienceDirect
A1: ScienceDirect
A3: # | B3: Title | C3: Reviewer | D3: Full-Text Decision | E3: Exclusion Reason | F3: Notes
A4: 1 | B4: Change-aware round-trip benchmarking of LLMs for reliable and efficient artifact co-evolution | C4: Thabiso Matsaba | D4: Include | F4: Pre-coded AI-DME relevant study (RQ2, RQ6, RQ8, RQ10). Evaluates LLMs (GPT-5, Gemini 2.5, DeepSeek V3, Qwen3) for round-trip consistency & co-evolution between class models and schemas under controlled edits. Measures edit persistence, structural validity, and run-to-run consistency.
A5: 2 | B5: Semanti-MOP: Bridging the semantic gap in automated architecture refactoring via instability-aware Large Language Models | C5: Thabiso Matsaba | D5: Include | F5: Pre-coded AI-DME relevant study (RQ2, RQ3, RQ6, RQ7, RQ14). Combines LLMs (RAG) and search-based optimization for architectural refactoring and microservice decomposition on Apache Flink.
A6: 3 | B6: A framework for assessing the capabilities of code generation of constraint domain-specific languages with large language models | C6: Thabiso Matsaba | D6: Include | F6: Pre-coded AI-DME relevant study (RQ4, RQ8, RQ9, RQ10). Evaluates LLM generation of formal constraint DSLs (OCL, Alloy) from textual specifications with code repair mechanisms.
A7: 4 | B7: Automatic translation of natural language requirements into CTL specifications using Large Language Models: A multi-approach evaluation | C7: Thabiso Matsaba | D7: Include | F7: Pre-coded AI-DME relevant study (RQ5, RQ8, RQ9, RQ12). Fine-tuning & prompting LLMs to translate natural language requirements into CTL formal verification models. Multi-approach evaluation.
A8: 5 | B8: Detecting semantic alignments between textual specifications and domain models | C8: Thabiso Matsaba | D8: Include | F8: Pre-coded AI-DME relevant study (RQ5, RQ6, RQ8). Applies NLP and LLMs to detect alignments and misalignments between textual specifications and domain models with high precision.
A9: 6 | B9: Assessing UML diagrams by GPT: Implications for education | C9: Thabiso Matsaba | D9: Include | F9: Pre-coded AI-DME relevant study (RQ4, RQ6, RQ8, RQ9). Evaluates GPT’s capabilities in assessing and grading UML use case, class, and sequence diagrams against expert baselines. Educational implications.
A10: 7 | B10: Automated spectrum-based model fault localization within a search framework | C10: Thabiso Matsaba | D10: Include | F10: Pre-coded AI-DME relevant study (RQ4, RQ6, RQ8). Applies Whale Optimization Algorithm and Learning-to-Rank for spectrum-based fault localization on Extended Finite State Machines (EFSM).
A11: 8 | B11: An architecture for model-based and intelligent automation in DevOps | C11: Thabiso Matsaba | D11: Include | F11: Pre-coded AI-DME relevant study (RQ1, RQ2, RQ3, RQ13). The AIDOaRt framework integrating AI/ML and Model-Driven Engineering for continuous system validation across multiple industrial case studies.
A12: 9 | B12: Convolutional neural networks for enhanced classification mechanisms of metamodels | C12: Thabiso Matsaba | D12: Include | F12: Pre-coded AI-DME relevant study (RQ2, RQ4, RQ6). Uses deep Convolutional Neural Networks (memoCNN) to automatically categorize and manage Ecore metamodel repositories.
A13: 10 | B13: An evolutionary approach for generating software models: The case of Kromaia in Game Software Engineering | C13: Thabiso Matsaba | D13: Include | F13: Pre-coded AI-DME relevant study (RQ6, RQ7, RQ11). Evolutionary model generation (EMoGen) producing industrial software models of >1000 elements in 5 hours versus 10 months of manual effort (Kromaia game).
A14: 11 | B14: Comparison of search strategies for feature location in software models | C14: Thabiso Matsaba | D14: Include | F14: Pre-coded AI-DME relevant study (RQ4, RQ6, RQ11). Evaluates metaheuristic search algorithms (random search, ILS, hill climbing, evolutionary algorithm, hybrid) across 1,895 feature location problems from 40 industrial software product lines.
A15: 12 | B15: MOMM: Multi-objective model merging | C15: Thabiso Matsaba | D15: Include | F15: Pre-coded AI-DME relevant study (RQ2, RQ3, RQ6, RQ7). NSGA-II multi-objective optimization approach for resolving conflicts in collaborative model engineering (model merging).
A16: 13 | B16: QExplore: An exploration strategy for dynamic web applications using guided search | C16: Thabiso Matsaba | D16: Include | F16: Pre-coded AI-DME relevant study (RQ2, RQ3, RQ6). Reinforcement learning (Q-learning) based exploration strategy for dynamic web applications, synthesizing behavioral state models.
A17: 14 | B17: On the understandability of machine learning practices in deep learning and reinforcement learning based systems | C17: Thabiso Matsaba | D17: Exclude | E17: Addresses ML/MLOps engineering rather than AI applied to software models (UML/SysML/DSL/metamodels) | F17: Assessed at full-text; does not meet AI-DME inclusion criteria
A18: 15 | B18: Investigating the performance of personalized models for software defect prediction | C18: Thabiso Matsaba | D18: Exclude | E18: Uses 'model' to mean a predictive machine-learning model (not a software/design model) | F18: Assessed at full-text; does not meet AI-DME inclusion criteria
A19: 16 | B19: Predictive maintenance using digital twins: A systematic literature review | C19: Thabiso Matsaba | D19: Exclude | E19: Focus on predictive maintenance / digital twins without AI-driven software model generation, transformation or validation | F19: Assessed at full-text; does not meet AI-DME inclusion criteria
A20: 17 | B20: A model-driven, metrics-based approach to assessing support for quality aspects in MLOps system architectures | C20: Thabiso Matsaba | D20: Exclude | E20: Model-driven topic present but does not apply an identifiable AI technique (LLM/ML/DL/agents) to generate, transform, validate, repair or evolve software models | F20: Assessed at full-text; does not meet AI-DME inclusion criteria
A21: 18 | B21: Barriers and enablers for traceability and federation in model-based digital twin engineering | C21: Thabiso Matsaba | D21: Exclude | E21: Digital-twin interoperability/traceability focus; insufficient AI application to software model lifecycle tasks | F21: Assessed at full-text; does not meet AI-DME inclusion criteria
A22: 19 | B22: HarmonyCAS: A model-driven framework for facilitating interoperability in context-aware systems | C22: Thabiso Matsaba | D22: Exclude | E22: Model-driven topic present but does not apply an identifiable AI technique (LLM/ML/DL/agents) to generate, transform, validate, repair or evolve software models | F22: Assessed at full-text; does not meet AI-DME inclusion criteria
A23: 20 | B23: Model-based M2M transformations based on drag-and-drop actions: Approach and implementation | C23: Thabiso Matsaba | D23: Exclude | E23: Model-driven topic present but does not apply an identifiable AI technique (LLM/ML/DL/agents) to generate, transform, validate, repair or evolve software models | F23: Assessed at full-text; does not meet AI-DME inclusion criteria
A24: 21 | B24: RAIDAD: A model-driven framework for automated and agile development of IoT data analysis software | C24: Thabiso Matsaba | D24: Exclude | E24: Model-driven topic present but does not apply an identifiable AI technique (LLM/ML/DL/agents) to generate, transform, validate, repair or evolve software models | F24: Assessed at full-text; does not meet AI-DME inclusion criteria
